Workbook

Sheet Inflation Rates 
A1: Date | B1: CPI (Annual % change)
A2: 6118 | B2: 7.9
A3: 6483 | B3: 9.8
A4: 6848 | B4: 12.3
A5: 7213 | B5: 9.2
A6: 7396 | B6: 11.9
A7: 7579 | B7: 15.4
A8: 7761 | B8: 8.7
A9: 7944 | B9: -1.8
A10: 8126 | B10: -11.1
A11: 8309 | B11: -10.8
A12: 8491 | B12: -4.8
A13: 8674 | B13: -0.4
... A395: 44104 | B395: 1.4
A396: 44196 | B396: 1.4 | G396: Years not considered | H396: Inflation Percentage
A397: 44286 | B397: 1.5
A398: 45382 | B398: 4 | G398: 44377 | H398: 3.3
A399: 45473 | B399: 3.3 | G399: 44469 | H399: 4.9
A400: 45565 | B400: 2.2 | G400: 44561 | H400: 5.9
A401: Mean | B401: =AVERAGE(B356:B400) -> 1.6866667 | G401: 44651 | H401: 6.9
A402: Standard Deviation | B402: =_xlfn.STDEV.S(B356:B400) -> 1.1925145 | G402: 44742 | H402: 7.3
G403: 44834 | H403: 7.2
G404: 44926 | H404: 7.2
G405: 45016 | H405: 6.7
G406: 45107 | H406: 6
G407: 45199 | H407: 5.6
G408: 45291 | H408: 4.7

Sheet Expense Tracker
A1: Weekly expenses | B1: 1110.1
A2: Yearly Expenses | B2: =12*4*B1 -> 53284.8
A3: Current Inflation | B3: 2.2
A5: Age | B5: Infation rates | C5: Expenses
A6: 30 | B6: =AVERAGE(B62:ALM62) -> 1.7061091 | C6: =B2*(1+B6/100) -> 54193.897
A7: 31 | B7: =AVERAGE(B63:ALM63) -> 1.7006627 | C7: =C6*(1+B7/100) -> 55115.552
A8: 32 | B8: =AVERAGE(B64:ALM64) -> 1.6763279 | C8: =C7*(1+B8/100) -> 56039.47
A9: 33 | B9: =AVERAGE(B65:ALM65) -> 1.6708117 | C9: =C8*(1+B9/100) -> 56975.784
A10: 34 | B10: =AVERAGE(B66:ALM66) -> 1.7009746 | C10: =C9*(1+B10/100) -> 57944.927
A11: 35 | B11: =AVERAGE(B67:ALM67) -> 1.6118771 | C11: =C10*(1+B11/100) -> 58878.928
A12: 36 | B12: =AVERAGE(B68:ALM68) -> 1.7116168 | C12: =C11*(1+B12/100) -> 59886.71
A13: 37 | B13: =AVERAGE(B69:ALM69) -> 1.6813549 | C13: =C12*(1+B13/100) -> 60893.618
A14: 38 | B14: =AVERAGE(B70:ALM70) -> 1.7174928 | C14: =C13*(1+B14/100) -> 61939.461
A15: 39 | B15: =AVERAGE(B71:ALM71) -> 1.7690198 | C15: =C14*(1+B15/100) -> 63035.183
A16: 40 | B16: =AVERAGE(B72:ALM72) -> 1.720499 | C16: =C15*(1+B16/100) -> 64119.702
A17: 41 | B17: =AVERAGE(B73:ALM73) -> 1.6589629 | C17: =C16*(1+B17/100) -> 65183.425
A18: 42 | B18: =AVERAGE(B74:ALM74) -> 1.6527065 | C18: =C17*(1+B18/100) -> 66260.715
... A58: 82 | B58: =AVERAGE(B114:ALM114) -> 1.7342651 | C58: =C57*(1+B58/100) -> 129360.78
A61: Age | B61: 1 | C61: 2 | D61: 3 | E61: 4 | F61: 5 | G61: 6 | H61: 7 | I61: 8 | J61: 9 | K61: 10 | L61: 11 | M61: 12 | N61: 13 | O61: 14 | P61: 15 | Q61: 16 | R61: 17 | S61: 18 | T61: 19 | U61: 20 | V61: 21 | W61: 22 | X61: 23 | Y61: 24 | Z61: 25 | AA61: 26 | AB61: 27 | AC61: 28 | AD61: 29 | AE61: 30 | AF61: 31 | AG61: 32 | AH61: 33 | AI61: 34 | AJ61: 35 | AK61: 36 | AL61: 37 | AM61: 38 | AN61: 39 | AO61: 40 | AP61: 41 | AQ61: 42 | AR61: 43 | AS61: 44 | AT61: 45 | AU61: 46 | AV61: 47 | AW61: 48 | AX61: 49 | AY61: 50 | AZ61: 51 | BA61: 52 | BB61: 53 | BC61: 54 | BD61: 55 | BE61: 56 | BF61: 57 | BG61: 58 | BH61: 59 | BI61: 60 | BJ61: 61 | BK61: 62 | BL61: 63 | BM61: 64 | BN61: 65 | BO61: 66 | BP61: 67 | BQ61: 68 | BR61: 69 | BS61: 70 | BT61: 71 | BU61: 72 | BV61: 73 | BW61: 74 | BX61: 75 | BY61: 76 | BZ61: 77 | CA61: 78 | CB61: 79 | CC61: 80 | CD61: 81 | CE61: 82 | CF61: 83 | CG61: 84 | CH61: 85 | CI61: 86 | CJ61: 87 | CK61: 88 | CL61: 89 | CM61: 90 | CN61: 91 | CO61: 92 | CP61: 93 | CQ61: 94 | CR61: 95 | CS61: 96 | CT61: 97 | CU61: 98 | CV61: 99 | CW61: 100 | CX61: 101 | CY61: 102 | CZ61: 103 | DA61: 104 | DB61: 105 | DC61: 106 | DD61: 107 | DE61: 108 | DF61: 109 | DG61: 110 | DH61: 111 | DI61: 112 | DJ61: 113 | DK61: 114 | DL61: 115 | DM61: 116 | DN61: 117 | DO61: 118 | DP61: 119 | DQ61: 120 | DR61: 121 | DS61: 122 | DT61: 123 | DU61: 124 | DV61: 125 | DW61: 126 | DX61: 127 | DY61: 128 | DZ61: 129 | EA61: 130 | EB61: 131 | EC61: 132 | ED61: 133 | EE61: 134 | EF61: 135 | EG61: 136 | EH61: 137 | EI61: 138 | EJ61: 139 | EK61: 140 | EL61: 141 | EM61: 142 | EN61: 143 | EO61: 144 | EP61: 145 | EQ61: 146 | ER61: 147 | ES61: 148 | ET61: 149 | EU61: 150 | EV61: 151 | EW61: 152 | EX61: 153 | EY61: 154 | EZ61: 155 | FA61: 156 | FB61: 157 | FC61: 158 | FD61: 159 | FE61: 160 | FF61: 161 | FG61: 162 | FH61: 163 | FI61: 164 | FJ61: 165 | FK61: 166 | FL61: 167 | FM61: 168 | FN61: 169 | FO61: 170 | FP61: 171 | FQ61: 172 | FR61: 173 | FS61: 174 | FT61: 175 | FU61: 176 | FV61: 177 | FW61: 178 | FX61: 179 | FY61: 180 | FZ61: 181 | GA61: 182 | GB61: 183 | GC61: 184 | GD61: 185 | GE61: 186 | GF61: 187 | GG61: 188 | GH61: 189 | GI61: 190 | GJ61: 191 | GK61: 192 | GL61: 193 | GM61: 194 | GN61: 195 | GO61: 196 | GP61: 197 | GQ61: 198 | GR61: 199 | GS61: 200 | GT61: 201 | GU61: 202 | GV61: 203 | GW61: 204 | GX61: 205 | GY61: 206 | GZ61: 207 | HA61: 208 | HB61: 209 | HC61: 210 | HD61: 211 | HE61: 212 | HF61: 213 | HG61: 214 | HH61: 215 | HI61: 216 | HJ61: 217 | HK61: 218 | HL61: 219 | HM61: 220 | HN61: 221 | HO61: 222 | HP61: 223 | HQ61: 224 | HR61: 225 | HS61: 226 | HT61: 227 | HU61: 228 | HV61: 229 | HW61: 230 | HX61: 231 | HY61: 232 | HZ61: 233 | IA61: 234 | IB61: 235 | IC61: 236 | ID61: 237 | IE61: 238 | IF61: 239 | IG61: 240 | IH61: 241 | II61: 242 | IJ61: 243 | IK61: 244 | IL61: 245 | IM61: 246 | IN61: 247 | IO61: 248 | IP61: 249 | IQ61: 250 | IR61: 251 | IS61: 252 | IT61: 253 | IU61: 254 | IV61: 255 | IW61: 256 | IX61: 257 | IY61: 258 | IZ61: 259 | JA61: 260 | JB61: 261 | JC61: 262 | JD61: 263 | JE61: 264 | JF61: 265 | JG61: 266 | JH61: 267 | JI61: 268 | JJ61: 269 | JK61: 270 | JL61: 271 | JM61: 272 | JN61: 273 | JO61: 274 | JP61: 275 | JQ61: 276 | JR61: 277 | JS61: 278 | JT61: 279 | JU61: 280 | JV61: 281 | JW61: 282 | JX61: 283 | JY61: 284 | JZ61: 285 | KA61: 286 | KB61: 287 | KC61: 288 | KD61: 289 | KE61: 290 | KF61: 291 | KG61: 292 | KH61: 293 | KI61: 294 | KJ61: 295 | KK61: 296 | KL61: 297 | KM61: 298 | KN61: 299 | KO61: 300 | KP61: 301 | KQ61: 302 | KR61: 303 | KS61: 304 | KT61: 305 | KU61: 306 | KV61: 307 | KW61: 308 | KX61: 309 | KY61: 310 | KZ61: 311 | LA61: 312 | LB61: 313 | LC61: 314 | LD61: 315 | LE61: 316 | LF61: 317 | LG61: 318 | LH61: 319 | LI61: 320 | LJ61: 321 | LK61: 322 | LL61: 323 | LM61: 324 | LN61: 325 | LO61: 326 | LP61: 327 | LQ61: 328 | LR61: 329 | LS61: 330 | LT61: 331 | LU61: 332 | LV61: 333 | LW61: 334 | LX61: 335 | LY61: 336 | LZ61: 337 | MA61: 338 | MB61: 339 | MC61: 340 | MD61: 341 | ME61: 342 | MF61: 343 | MG61: 344 | MH61: 345 | MI61: 346 | MJ61: 347 | MK61: 348 | ML61: 349 | MM61: 350 | MN61: 351 | MO61: 352 | MP61: 353 | MQ61: 354 | MR61: 355 | MS61: 356 | MT61: 357 | MU61: 358 | MV61: 359 | MW61: 360 | MX61: 361 | MY61: 362 | MZ61: 363 | NA61: 364 | NB61: 365 | NC61: 366 | ND61: 367 | NE61: 368 | NF61: 369 | NG61: 370 | NH61: 371 | NI61: 372 | NJ61: 373 | NK61: 374 | NL61: 375 | NM61: 376 | NN61: 377 | NO61: 378 | NP61: 379 | NQ61: 380 | NR61: 381 | NS61: 382 | NT61: 383 | NU61: 384 | NV61: 385 | NW61: 386 | NX61: 387 | NY61: 388 | NZ61: 389 | OA61: 390 | OB61: 391 | OC61: 392 | OD61: 393 | OE61: 394 | OF61: 395 | OG61: 396 | OH61: 397 | OI61: 398 | OJ61: 399 | OK61: 400 | OL61: 401 | OM61: 402 | ON61: 403 | OO61: 404 | OP61: 405 | OQ61: 406 | OR61: 407 | OS61: 408 | OT61: 409 | OU61: 410 | OV61: 411 | OW61: 412 | OX61: 413 | OY61: 414 | OZ61: 415 | PA61: 416 | PB61: 417 | PC61: 418 | PD61: 419 | PE61: 420 | PF61: 421 | PG61: 422 | PH61: 423 | PI61: 424 | PJ61: 425 | PK61: 426 | PL61: 427 | PM61: 428 | PN61: 429 | PO61: 430 | PP61: 431 | PQ61: 432 | PR61: 433 | PS61: 434 | PT61: 435 | PU61: 436 | PV61: 437 | PW61: 438 | PX61: 439 | PY61: 440 | PZ61: 441 | QA61: 442 | QB61: 443 | QC61: 444 | QD61: 445 | QE61: 446 | QF61: 447 | QG61: 448 | QH61: 449 | QI61: 450 | QJ61: 451 | QK61: 452 | QL61: 453 | QM61: 454 | QN61: 455 | QO61: 456 | QP61: 457 | QQ61: 458 | QR61: 459 | QS61: 460 | QT61: 461 | QU61: 462 | QV61: 463 | QW61: 464 | QX61: 465 | QY61: 466 | QZ61: 467 | RA61: 468 | RB61: 469 | RC61: 470 | RD61: 471 | RE61: 472 | RF61: 473 | RG61: 474 | RH61: 475 | RI61: 476 | RJ61: 477 | RK61: 478 | RL61: 479 | RM61: 480 | RN61: 481 | RO61: 482 | RP61: 483 | RQ61: 484 | RR61: 485 | RS61: 486 | RT61: 487 | RU61: 488 | RV61: 489 | RW61: 490 | RX61: 491 | RY61: 492 | RZ61: 493 | SA61: 494 | SB61: 495 | SC61: 496 | SD61: 497 | SE61: 498 | SF61: 499 | SG61: 500 | SH61: 501 | SI61: 502 | SJ61: 503 | SK61: 504 | SL61: 505 | SM61: 506 | SN61: 507 | SO61: 508 | SP61: 509 | SQ61: 510 | SR61: 511 | SS61: 512 | ST61: 513 | SU61: 514 | SV61: 515 | SW61: 516 | SX61: 517 | SY61: 518 | SZ61: 519 | TA61: 520 | TB61: 521 | TC61: 522 | TD61: 523 | TE61: 524 | TF61: 525 | TG61: 526 | TH61: 527 | TI61: 528 | TJ61: 529 | TK61: 530 | TL61: 531 | TM61: 532 | TN61: 533 | TO61: 534 | TP61: 535 | TQ61: 536 | TR61: 537 | TS61: 538 | TT61: 539 | TU61: 540 | TV61: 541 | TW61: 542 | TX61: 543 | TY61: 544 | TZ61: 545 | UA61: 546 | UB61: 547 | UC61: 548 | UD61: 549 | UE61: 550 | UF61: 551 | UG61: 552 | UH61: 553 | UI61: 554 | UJ61: 555 | UK61: 556 | UL61: 557 | UM61: 558 | UN61: 559 | UO61: 560 | UP61: 561 | UQ61: 562 | UR61: 563 | US61: 564 | UT61: 565 | UU61: 566 | UV61: 567 | UW61: 568 | UX61: 569 | UY61: 570 | UZ61: 571 | VA61: 572 | VB61: 573 | VC61: 574 | VD61: 575 | VE61: 576 | VF61: 577 | VG61: 578 | VH61: 579 | VI61: 580 | VJ61: 581 | VK61: 582 | VL61: 583 | VM61: 584 | VN61: 585 | VO61: 586 | VP61: 587 | VQ61: 588 | VR61: 589 | VS61: 590 | VT61: 591 | VU61: 592 | VV61: 593 | VW61: 594 | VX61: 595 | VY61: 596 | VZ61: 597 | WA61: 598 | WB61: 599 | WC61: 600 | WD61: 601 | WE61: 602 | WF61: 603 | WG61: 604 | WH61: 605 | WI61: 606 | WJ61: 607 | WK61: 608 | WL61: 609 | WM61: 610 | WN61: 611 | WO61: 612 | WP61: 613 | WQ61: 614 | WR61: 615 | WS61: 616 | WT61: 617 | WU61: 618 | WV61: 619 | WW61: 620 | WX61: 621 | WY61: 622 | WZ61: 623 | XA61: 624 | XB61: 625 | XC61: 626 | XD61: 627 | XE61: 628 | XF61: 629 | XG61: 630 | XH61: 631 | XI61: 632 | XJ61: 633 | XK61: 634 | XL61: 635 | XM61: 636 | XN61: 637 | XO61: 638 | XP61: 639 | XQ61: 640 | XR61: 641 | XS61: 642 | XT61: 643 | XU61: 644 | XV61: 645 | XW61: 646 | XX61: 647 | XY61: 648 | XZ61: 649 | YA61: 650 | YB61: 651 | YC61: 652 | YD61: 653 | YE61: 654 | YF61: 655 | YG61: 656 | YH61: 657 | YI61: 658 | YJ61: 659 | YK61: 660 | YL61: 661 | YM61: 662 | YN61: 663 | YO61: 664 | YP61: 665 | YQ61: 666 | YR61: 667 | YS61: 668 | YT61: 669 | YU61: 670 | YV61: 671 | YW61: 672 | YX61: 673 | YY61: 674 | YZ61: 675 | ZA61: 676 | ZB61: 677 | ZC61: 678 | ZD61: 679 | ZE61: 680 | ZF61: 681 | ZG61: 682 | ZH61: 683 | ZI61: 684 | ZJ61: 685 | ZK61: 686 | ZL61: 687 | ZM61: 688 | ZN61: 689 | ZO61: 690 | ZP61: 691 | ZQ61: 692 | ZR61: 693 | ZS61: 694 | ZT61: 695 | ZU61: 696 | ZV61: 697 | ZW61: 698 | ZX61: 699 | ZY61: 700 | ZZ61: 701 | AAA61: 702 | AAB61: 703 | AAC61: 704 | AAD61: 705 | AAE61: 706 | AAF61: 707 | AAG61: 708 | AAH61: 709 | AAI61: 710 | AAJ61: 711 | AAK61: 712 | AAL61: 713 | AAM61: 714 | AAN61: 715 | AAO61: 716 | AAP61: 717 | AAQ61: 718 | AAR61: 719 | AAS61: 720 | AAT61: 721 | AAU61: 722 | AAV61: 723 | AAW61: 724 | AAX61: 725 | AAY61: 726 | AAZ61: 727 | ABA61: 728 | ABB61: 729 | ABC61: 730 | ABD61: 731 | ABE61: 732 | ABF61: 733 | ABG61: 734 | ABH61: 735 | ABI61: 736 | ABJ61: 737 | ABK61: 738 | ABL61: 739 | ABM61: 740 | ABN61: 741 | ABO61: 742 | ABP61: 743 | ABQ61: 744 | ABR61: 745 | ABS61: 746 | ABT61: 747 | ABU61: 748 | ABV61: 749 | ABW61: 750 | ABX61: 751 | ABY61: 752 | ABZ61: 753 | ACA61: 754 | ACB61: 755 | ACC61: 756 | ACD61: 757 | ACE61: 758 | ACF61: 759 | ACG61: 760 | ACH61: 761 | ACI61: 762 | ACJ61: 763 | ACK61: 764 | ACL61: 765 | ACM61: 766 | ACN61: 767 | ACO61: 768 | ACP61: 769 | ACQ61: 770 | ACR61: 771 | ACS61: 772 | ACT61: 773 | ACU61: 774 | ACV61: 775 | ACW61: 776 | ACX61: 777 | ACY61: 778 | ACZ61: 779 | ADA61: 780 | ADB61: 781 | ADC61: 782 | ADD61: 783 | ADE61: 784 | ADF61: 785 | ADG61: 786 | ADH61: 787 | ADI61: 788 | ADJ61: 789 | ADK61: 790 | ADL61: 791 | ADM61: 792 | ADN61: 793 | ADO61: 794 | ADP61: 795 | ADQ61: 796 | ADR61: 797 | ADS61: 798 | ADT61: 799 | ADU61: 800 | ADV61: 801 | ADW61: 802 | ADX61: 803 | ADY61: 804 | ADZ61: 805 | AEA61: 806 | AEB61: 807 | AEC61: 808 | AED61: 809 | AEE61: 810 | AEF61: 811 | AEG61: 812 | AEH61: 813 | AEI61: 814 | AEJ61: 815 | AEK61: 816 | AEL61: 817 | AEM61: 818 | AEN61: 819 | AEO61: 820 | AEP61: 821 | AEQ61: 822 | AER61: 823 | AES61: 824 | AET61: 825 | AEU61: 826 | AEV61: 827 | AEW61: 828 | AEX61: 829 | AEY61: 830 | AEZ61: 831 | AFA61: 832 | AFB61: 833 | AFC61: 834 | AFD61: 835 | AFE61: 836 | AFF61: 837 | AFG61: 838 | AFH61: 839 | AFI61: 840 | AFJ61: 841 | AFK61: 842 | AFL61: 843 | AFM61: 844 | AFN61: 845 | AFO61: 846 | AFP61: 847 | AFQ61: 848 | AFR61: 849 | AFS61: 850 | AFT61: 851 | AFU61: 852 | AFV61: 853 | AFW61: 854 | AFX61: 855 | AFY61: 856 | AFZ61: 857 | AGA61: 858 | AGB61: 859 | AGC61: 860 | AGD61: 861 | AGE61: 862 | AGF61: 863 | AGG61: 864 | AGH61: 865 | AGI61: 866 | AGJ61: 867 | AGK61: 868 | AGL61: 869 | AGM61: 870 | AGN61: 871 | AGO61: 872 | AGP61: 873 | AGQ61: 874 | AGR61: 875 | AGS61: 876 | AGT61: 877 | AGU61: 878 | AGV61: 879 | AGW61: 880 | AGX61: 881 | AGY61: 882 | AGZ61: 883 | AHA61: 884 | AHB61: 885 | AHC61: 886 | AHD61: 887 | AHE61: 888 | AHF61: 889 | AHG61: 890 | AHH61: 891 | AHI61: 892 | AHJ61: 893 | AHK61: 894 | AHL61: 895 | AHM61: 896 | AHN61: 897 | AHO61: 898 | AHP61: 899 | AHQ61: 900 | AHR61: 901 | AHS61: 902 | AHT61: 903 | AHU61: 904 | AHV61: 905 | AHW61: 906 | AHX61: 907 | AHY61: 908 | AHZ61: 909 | AIA61: 910 | AIB61: 911 | AIC61: 912 | AID61: 913 | AIE61: 914 | AIF61: 915 | AIG61: 916 | AIH61: 917 | AII61: 918 | AIJ61: 919 | AIK61: 920 | AIL61: 921 | AIM61: 922 | AIN61: 923 | AIO61: 924 | AIP61: 925 | AIQ61: 926 | AIR61: 927 | AIS61: 928 | AIT61: 929 | AIU61: 930 | AIV61: 931 | AIW61: 932 | AIX61: 933 | AIY61: 934 | AIZ61: 935 | AJA61: 936 | AJB61: 937 | AJC61: 938 | AJD61: 939 | AJE61: 940 | AJF61: 941 | AJG61: 942 | AJH61: 943 | AJI61: 944 | AJJ61: 945 | AJK61: 946 | AJL61: 947 | AJM61: 948 | AJN61: 949 | AJO61: 950 | AJP61: 951 | AJQ61: 952 | AJR61: 953 | AJS61: 954 | AJT61: 955 | AJU61: 956 | AJV61: 957 | AJW61: 958 | AJX61: 959 | AJY61: 960 | AJZ61: 961 | AKA61: 962 | AKB61: 963 | AKC61: 964 | AKD61: 965 | AKE61: 966 | AKF61: 967 | AKG61: 968 | AKH61: 969 | AKI61: 970 | AKJ61: 971 | AKK61: 972 | AKL61: 973 | AKM61: 974 | AKN61: 975 | AKO61: 976 | AKP61: 977 | AKQ61: 978 | AKR61: 979 | AKS61: 980 | AKT61: 981 | AKU61: 982 | AKV61: 983 | AKW61: 984 | AKX61: 985 | AKY61: 986 | AKZ61: 987 | ALA61: 988 | ALB61: 989 | ALC61: 990 | ALD61: 991 | ALE61: 992 | ALF61: 993 | ALG61: 994 | ALH61: 995 | ALI61: 996 | ALJ61: 997 | ALK61: 998 | ALL61: 999 | ALM61: 1000
A62: 30 | B62: =_xlfn.NORM.INV(RAND(),'Inflation Rates '!$B$401,'Inflation Rates '!$B$402) -> 2.2410518 | C62: 2.8064286 | D62: 0.34930637 | E62: 2.2425559 | F62: 1.6039553 | G62: 0.86049719 | H62: -0.43043507 | I62: 1.4869649 | J62: 0.11876842 | K62: -0.21001516 | L62: 1.722321 | M62: 1.8366166 | N62: 2.2891294 | O62: 1.4916 | P62: 2.4038586 | Q62: -0.74629447 | R62: 2.3413153 | S62: 2.1389674 | T62: -0.68473145 | U62: 0.96691833 | V62: 4.0165824 | W62: 1.7773232 | X62: -0.45873992 | Y62: 3.9020671 | Z62: 1.5764335 | AA62: 1.8943157 | AB62: 1.4707105 | AC62: 2.9178816 | AD62: 0.9496293 | AE62: 0.79440672 | AF62: 1.9815362 | AG62: 1.4364523 | AH62: 1.8219146 | AI62: 1.1945225 | AJ62: 1.9511012 | AK62: 4.3287142 | AL62: 3.1511915 | AM62: 1.867726 | AN62: 2.6161877 | AO62: 0.51070938 | AP62: 0.49317545 | AQ62: 3.5209181 | AR62: 0.58316743 | AS62: 1.6085217 | AT62: 1.8315847 | AU62: 2.703562 | AV62: 1.829345 | AW62: 2.0658202 | AX62: 0.22457294 | AY62: 6.7943165 | AZ62: -0.40475173 | BA62: 3.3623358 | BB62: 1.7196624 | BC62: 3.4690965 | BD62: 2.0126356 | BE62: 0.65329574 | BF62: 1.6154631 | BG62: 2.7783292 | BH62: 2.7685933 | BI62: 2.577419 | BJ62: 2.2019349 | BK62: 1.2778661 | BL62: 2.4259156 | BM62: 0.34574786 | BN62: 3.7392582 | BO62: -0.71870823 | BP62: 0.65134291 | BQ62: 3.1361564 | BR62: 1.2991118 | BS62: 0.82121049 | BT62: 1.0692665 | BU62: 3.2289502 | BV62: 3.9419809 | BW62: 0.50149206 | BX62: 2.3411128 | BY62: 1.7434007 | BZ62: 5.0084314 | CA62: 3.453857 | CB62: 3.0480291 | CC62: 1.2209322 | CD62: 0.84802999 | CE62: 2.6420834 | CF62: 2.7503376 | CG62: 2.6086812 | CH62: -0.46249577 | CI62: -0.082549634 | CJ62: 0.88474543 | CK62: 0.97166034 | CL62: 1.721115 | CM62: 2.6921752 | CN62: 1.5117768 | CO62: 0.11405815 | CP62: 1.0595542 | CQ62: 2.2986738 | CR62: 1.5876723 | CS62: 2.0015854 | CT62: 0.48033539 | CU62: 0.15218943 | CV62: 4.056499 | CW62: 1.4870345 | CX62: 2.7379658 | CY62: 2.340588 | CZ62: 1.1830565 | DA62: 1.8159882 | DB62: 0.76654101 | DC62: 1.3699655 | DD62: 3.1976179 | DE62: 1.5595175 | DF62: 3.5506289 | DG62: 3.3526414 | DH62: 0.36331097 | DI62: 1.4487909 | DJ62: 0.66924707 | DK62: 1.3182884 | DL62: 2.4440604 | DM62: 1.2078507 | DN62: 2.4551426 | DO62: 2.3498155 | DP62: 0.14625654 | DQ62: 3.3858355 | DR62: 1.198355 | DS62: 3.1479186 | DT62: 3.294223 | DU62: 0.63905533 | DV62: 0.1292471 | DW62: 3.8247069 | DX62: 1.5922337 | DY62: 1.2088299 | DZ62: 2.7496686 | EA62: 3.6948309 | EB62: 1.9248603 | EC62: 2.5508115 | ED62: 0.68644448 | EE62: 1.6150515 | EF62: 2.6858552 | EG62: 2.6453201 | EH62: 2.0986133 | EI62: -0.62378794 | EJ62: 2.4567986 | EK62: 0.8971159 | EL62: 0.85000476 | EM62: 0.69121169 | EN62: 0.99630547 | EO62: 2.0791935 | EP62: -0.73849113 | EQ62: -0.80495311 | ER62: 2.0798146 | ES62: 1.1243353 | ET62: 3.051876 | EU62: 2.8274221 | EV62: 1.7301703 | EW62: 1.8465611 | EX62: 0.27484769 | EY62: 0.5447721 | EZ62: 1.4081994 | FA62: 0.58596485 | FB62: 3.8163695 | FC62: 1.4946305 | FD62: 2.0867851 | FE62: 0.82844059 | FF62: 3.0211924 | FG62: 2.8018061 | FH62: 2.6368691 | FI62: 1.4453768 | FJ62: 1.6686764 | FK62: 0.35699983 | FL62: 1.9704593 | FM62: 2.4391696 | FN62: 3.6761505 | FO62: 2.1650529 | FP62: 2.23256 | FQ62: 2.8166154 | FR62: 1.3814788 | FS62: 0.26189581 | FT62: 0.72589228 | FU62: 0.70894479 | FV62: 1.9599248 | FW62: 1.7922179 | FX62: -0.12317297 | FY62: -0.098762949 | FZ62: 3.4920514 | GA62: 2.0650802 | GB62: 1.7545181 | GC62: 2.0803045 | GD62: 1.4826007 | GE62: 1.1850438 | GF62: 2.9332698 | GG62: 1.263613 | GH62: 0.42038525 | GI62: 0.23472109 | GJ62: 2.2690176 | GK62: 2.5735097 | GL62: 1.129622 | GM62: 3.2484881 | GN62: 1.0529686 | GO62: 3.4090579 | GP62: 1.8808984 | GQ62: -0.22998023 | GR62: 3.2484685 | GS62: 1.6466301 | GT62: 1.2265277 | GU62: 1.0732159 | GV62: 2.5508483 | GW62: 1.5768811 | GX62: 1.4857421 | GY62: 2.4500959 | GZ62: 2.7344643 | HA62: 3.3614159 | HB62: 0.34849959 | HC62: 1.1788561 | HD62: 0.3923123 | HE62: 1.971004 | HF62: 2.8803309 | HG62: 0.68560898 | HH62: 2.4703183 | HI62: 2.083174 | HJ62: 0.7951956 | HK62: 0.89841226 | HL62: 3.2551553 | HM62: 3.7634788 | HN62: -0.93635893 | HO62: 0.71265664 | HP62: 2.7836506 | HQ62: 2.1960151 | HR62: 3.9380131 | HS62: 0.38500528 | HT62: 0.33642369 | HU62: 2.7281599 | HV62: 2.8482404 | HW62: 2.331065 | HX62: 0.80855562 | HY62: 3.3091697 | HZ62: 1.7626107 | IA62: -0.47189338 | IB62: 1.5321656 | IC62: 0.94088476 | ID62: 0.22281772 | IE62: 1.9530181 | IF62: 1.825232 | IG62: 1.6953794 | IH62: 2.9914159 | II62: 0.82217402 | IJ62: 4.5934403 | IK62: 0.32097136 | IL62: 3.3487204 | IM62: 1.6822517 | IN62: 3.3270777 | IO62: 0.59296441 | IP62: -0.75814941 | IQ62: 2.5418437 | IR62: 1.6723008 | IS62: -0.82978059 | IT62: 1.0765144 | IU62: 1.1015396 | IV62: 1.0609312 | IW62: 1.6608134 | IX62: 3.6401775 | IY62: 1.5735224 | IZ62: 0.96974222 | JA62: 2.7228328 | JB62: 0.58477442 | JC62: 2.1815409 | JD62: 2.4038108 | JE62: 2.8990861 | JF62: 1.0661218 | JG62: 1.6751646 | JH62: 0.66997316 | JI62: 2.3309149 | JJ62: 2.5868293 | JK62: 1.579207 | JL62: 1.3170569 | JM62: 2.9567261 | JN62: -0.088511742 | JO62: 1.7788421 | JP62: 0.96662926 | JQ62: 0.63987932 | JR62: 2.6477745 | JS62: 2.9818408 | JT62: -0.47129661 | JU62: 0.99292442 | JV62: 1.8737501 | JW62: 1.7269179 | JX62: 1.3454372 | JY62: 0.92271824 | JZ62: 0.86768606 | KA62: 2.8619078 | KB62: 3.0436188 | KC62: 2.2210964 | KD62: 2.0726862 | KE62: 2.0982607 | KF62: -0.1064855 | KG62: 0.54024911 | KH62: 0.67157338 | KI62: 1.0078143 | KJ62: 2.8621438 | KK62: 1.8732757 | KL62: 2.9300915 | KM62: 1.5276826 | KN62: 2.1135551 | KO62: 1.4331358 | KP62: 3.0561794 | KQ62: 0.92576414 | KR62: -0.085299916 | KS62: 1.8899534 | KT62: -0.51332593 | KU62: 2.7852356 | KV62: 3.38189 | KW62: 1.3632188 | KX62: 1.9198315 | KY62: 1.7201221 | KZ62: 2.1303848 | LA62: 1.9886732 | LB62: 2.7989986 | LC62: 2.4422025 | LD62: 1.9942642 | LE62: 1.3630191 | LF62: 1.5580806 | LG62: 1.7361767 | LH62: 3.6211535 | LI62: 0.093728435 | LJ62: -0.6790302 | LK62: 2.3295304 | LL62: 3.4661265 | LM62: 2.0024404 | LN62: 0.065799082 | LO62: 2.9088235 | LP62: 0.77104826 | LQ62: 1.2454294 | LR62: 2.0439243 | LS62: 1.4242593 | LT62: 1.415152 | LU62: 2.3080599 | LV62: 1.6874149 | LW62: 3.1880142 | LX62: 1.2084311 | LY62: 0.78013398 | LZ62: 0.64989521 | MA62: -0.084203134 | MB62: 2.5930967 | MC62: 1.0569353 | MD62: 1.5418335 | ME62: 0.68658877 | MF62: 2.2526272 | MG62: 0.79700137 | MH62: 2.697709 | MI62: 0.7474443 | MJ62: 1.3534004 | MK62: 2.2500789 | ML62: 4.4663465 | MM62: 3.087707 | MN62: 1.7302428 | MO62: 1.2313681 | MP62: 1.5673722 | MQ62: 1.3138925 | MR62: 1.0507277 | MS62: 2.0242005 | MT62: 2.125084 | MU62: 0.68110749 | MV62: 2.2125758 | MW62: 2.6460183 | MX62: 1.3870113 | MY62: 1.9183138 | MZ62: 2.5672694 | NA62: 2.7151795 | NB62: 0.64531297 | NC62: -1.3057249 | ND62: 0.84308083 | NE62: 1.4311519 | NF62: 1.3168108 | NG62: 3.1318364 | NH62: 3.5778176 | NI62: 1.7879998 | NJ62: 0.97405729 | NK62: 3.3452533 | NL62: 3.5454466 | NM62: -0.38483423 | NN62: 1.4157437 | NO62: -0.12666388 | NP62: 0.59925497 | NQ62: 2.1557869 | NR62: 0.80713275 | NS62: 3.2998069 | NT62: 1.7532549 | NU62: 0.2054903 | NV62: 1.2212321 | NW62: 0.08705159 | NX62: 1.1778911 | NY62: 1.8800719 | NZ62: 1.6846679 | OA62: 0.22304568 | OB62: 0.59666505 | OC62: 4.1644053 | OD62: 2.2613183 | OE62: 1.820716 | OF62: 2.1430732 | OG62: 2.0569459 | OH62: 1.1461929 | OI62: 2.0742851 | OJ62: 2.3190446 | OK62: 1.2112461 | OL62: 1.3957584 | OM62: -1.0205992 | ON62: 1.3745935 | OO62: 1.337382 | OP62: 2.1582093 | OQ62: -0.13208121 | OR62: 2.4072755 | OS62: -0.093587554 | OT62: 0.48534419 | OU62: 2.2839342 | OV62: 3.6515995 | OW62: 1.569927 | OX62: 2.9397174 | OY62: 0.75071983 | OZ62: 0.82895214 | PA62: 3.3194322 | PB62: 4.55031 | PC62: 2.6437746 | PD62: 1.1754124 | PE62: 0.52431278 | PF62: 1.690926 | PG62: 1.637545 | PH62: 2.5230606 | PI62: -1.4714595 | PJ62: 2.2731853 | PK62: 3.947601 | PL62: 0.44453244 | PM62: 2.4854705 | PN62: 0.47054285 | PO62: 0.55141061 | PP62: 2.3142492 | PQ62: 2.0476485 | PR62: 1.9349394 | PS62: 3.7933326 | PT62: 0.32160446 | PU62: 1.7538095 | PV62: 1.05148 | PW62: -0.0020394095 | PX62: 0.93189301 | PY62: 0.95079993 | PZ62: -0.7657874 | QA62: 3.0367167 | QB62: 2.9407873 | QC62: 1.9719621 | QD62: 0.61301924 | QE62: 1.9675765 | QF62: 0.27014239 | QG62: 3.6500139 | QH62: 0.91824759 | QI62: 1.8517809 | QJ62: 0.33155967 | QK62: 1.3547318 | QL62: 2.4776887 | QM62: 2.9394666 | QN62: 0.18867224 | QO62: 3.244636 | QP62: 2.5236467 | QQ62: -0.36672207 | QR62: 2.6302971 | QS62: 1.9881807 | QT62: 3.1187268 | QU62: 0.42696866 | QV62: 2.2911259 | QW62: 4.1180507 | QX62: -0.42680467 | QY62: 0.93839714 | QZ62: 0.35566617 | RA62: 1.1044821 | RB62: 0.2636218 | RC62: 2.6701541 | RD62: 2.736372 | RE62: 4.0934155 | RF62: 2.8642052 | RG62: 0.77983897 | RH62: 2.0886108 | RI62: 2.1290585 | RJ62: 2.1980932 | RK62: 0.016481844 | RL62: -0.01961914 | RM62: 1.2395383 | RN62: 1.7627043 | RO62: 1.71089 | RP62: 1.2271991 | RQ62: 0.86678296 | RR62: 1.1806879 | RS62: 2.9315262 | RT62: 2.22189 | RU62: 2.3024669 | RV62: -0.70869517 | RW62: 3.7477795 | RX62: 1.9659429 | RY62: 2.2918887 | RZ62: 1.7593294 | SA62: 1.5081867 | SB62: 1.979235 | SC62: 3.3177218 | SD62: 1.2034682 | SE62: 1.846605 | SF62: 3.9928617 | SG62: 1.9830291 | SH62: 1.8075805 | SI62: 2.1937646 | SJ62: 0.75957707 | SK62: 3.0722408 | SL62: 3.2955242 | SM62: 1.3402845 | SN62: 2.889379 | SO62: 2.1663389 | SP62: 3.4378874 | SQ62: -0.82411523 | SR62: 1.6776472 | SS62: 0.086741472 | ST62: 0.52907299 | SU62: 1.3856468 | SV62: 0.8563856 | SW62: 0.61611439 | SX62: 1.1765884 | SY62: 0.30304533 | SZ62: 2.1107771 | TA62: 2.81876 | TB62: 3.0924544 | TC62: 0.70593875 | TD62: 0.063549488 | TE62: 3.0536314 | TF62: 1.6822793 | TG62: 1.6479142 | TH62: 1.0301397 | TI62: 2.9896229 | TJ62: 1.210286 | TK62: 2.1862914 | TL62: 2.0301014 | TM62: 1.1788623 | TN62: 1.6476247 | TO62: 2.2629944 | TP62: 4.3847206 | TQ62: -0.897611 | TR62: 1.6660331 | TS62: 0.83815435 | TT62: 1.849507 | TU62: 2.0685098 | TV62: 1.6580703 | TW62: 2.9081359 | TX62: 1.8300059 | TY62: 2.3971299 | TZ62: 1.5431243 | UA62: 1.7855276 | UB62: 3.1218125 | UC62: 3.5523859 | UD62: 1.8436273 | UE62: -0.42141081 | UF62: 1.8549446 | UG62: 1.3017532 | UH62: 3.0912563 | UI62: 3.4600112 | UJ62: 0.19129074 | UK62: 1.691619 | UL62: 1.8750054 | UM62: 3.2398379 | UN62: 0.51568278 | UO62: 1.8427594 | UP62: 2.2385279 | UQ62: 2.8013574 | UR62: 0.0096648563 | US62: 3.0187869 | UT62: 1.7775725 | UU62: 1.593094 | UV62: 0.83411111 | UW62: 2.3335569 | UX62: 2.8558001 | UY62: 1.0954355 | UZ62: 0.41150473 | VA62: 1.6494716 | VB62: 1.9410554 | VC62: 3.2637213 | VD62: 2.5420848 | VE62: -0.44239811 | VF62: 2.0152965 | VG62: -0.17260038 | VH62: 0.29912637 | VI62: 1.651444 | VJ62: 2.7590162 | VK62: 1.9364484 | VL62: 0.63682654 | VM62: 0.054703639 | VN62: 2.5452265 | VO62: 1.5225992 | VP62: 3.1655019 | VQ62: 3.0657468 | VR62: -0.15306505 | VS62: 1.1093479 | VT62: 1.1917258 | VU62: 1.9659627 | VV62: -0.73838361 | VW62: 1.9845999 | VX62: 2.4613264 | VY62: 0.7789518 | VZ62: 1.2888563 | WA62: 1.9129549 | WB62: 0.88759667 | WC62: 0.69268623 | WD62: 0.33288509 | WE62: 1.5043043 | WF62: 1.59871 | WG62: 0.67365893 | WH62: 2.6078393 | WI62: 1.9796915 | WJ62: -0.11103162 | WK62: 1.2996896 | WL62: 0.96474906 | WM62: 3.6372235 | WN62: 2.2841902 | WO62: 3.0421172 | WP62: 1.0768251 | WQ62: -0.52390458 | WR62: 2.4207144 | WS62: 0.35857653 | WT62: 0.68296427 | WU62: 2.4815421 | WV62: 4.3077044 | WW62: 1.691771 | WX62: -0.73931085 | WY62: 1.5532835 | WZ62: 2.2147002 | XA62: 3.1810496 | XB62: 3.7648221 | XC62: 1.2037443 | XD62: 2.8717451 | XE62: 2.9365987 | XF62: 3.0820841 | XG62: 1.1308097 | XH62: 1.8178292 | XI62: -0.96074927 | XJ62: 3.0533976 | XK62: 1.0866201 | XL62: 0.086023273 | XM62: 0.21801698 | XN62: 2.3507584 | XO62: 1.4666581 | XP62: -0.16204889 | XQ62: 1.0536268 | XR62: 1.6607284 | XS62: 2.3220249 | XT62: 3.2662722 | XU62: 1.4978108 | XV62: 2.5268181 | XW62: 0.14040319 | XX62: 1.6763803 | XY62: -0.025064579 | XZ62: -0.52444859 | YA62: 2.7114674 | YB62: 3.036812 | YC62: 1.3600057 | YD62: 1.3825811 | YE62: 4.9376578 | YF62: 2.2237461 | YG62: 2.0129222 | YH62: 0.95750528 | YI62: 1.8282566 | YJ62: 4.0724482 | YK62: 2.1998181 | YL62: 1.1841267 | YM62: 1.9748492 | YN62: 1.5295105 | YO62: 1.7679191 | YP62: 1.5785092 | YQ62: 0.63990978 | YR62: 2.4525412 | YS62: 0.36250195 | YT62: 0.80250539 | YU62: 1.1822603 | YV62: 1.9532589 | YW62: 1.9712213 | YX62: 1.8551237 | YY62: 3.5853595 | YZ62: 2.6369356 | ZA62: 2.1869329 | ZB62: 1.1008545 | ZC62: 1.2023695 | ZD62: 2.0162177 | ZE62: 0.99957983 | ZF62: 1.5601255 | ZG62: 0.012081889 | ZH62: 0.59860779 | ZI62: 3.6645531 | ZJ62: 2.4100941 | ZK62: 2.0359336 | ZL62: 1.7893886 | ZM62: 0.51063493 | ZN62: 2.0615076 | ZO62: 0.007252509 | ZP62: 0.95383674 | ZQ62: 2.1486894 | ZR62: 0.39349402 | ZS62: 0.11668211 | ZT62: 2.313324 | ZU62: 3.6005282 | ZV62: 2.7892328 | ZW62: 0.204763 | ZX62: 2.8545623 | ZY62: -0.6047777 | ZZ62: 1.1485717 | AAA62: 2.4947032 | AAB62: 1.1792455 | AAC62: 2.8476324 | AAD62: 1.8017273 | AAE62: 1.5353293 | AAF62: 0.82726973 | AAG62: 0.36728203 | AAH62: 2.9279802 | AAI62: 1.4413681 | AAJ62: 1.5443504 | AAK62: 1.6453242 | AAL62: 1.4057068 | AAM62: 1.5661469 | AAN62: 2.9932804 | AAO62: 2.2894704 | AAP62: 3.6645207 | AAQ62: 2.8118317 | AAR62: 0.11449066 | AAS62: 2.1109169 | AAT62: 0.50731576 | AAU62: 3.5301849 | AAV62: 2.8810822 | AAW62: 2.6484812 | AAX62: 2.2735783 | AAY62: 1.2918373 | AAZ62: 2.0404385 | ABA62: 1.5917741 | ABB62: 0.79940665 | ABC62: 0.32178436 | ABD62: 3.5671665 | ABE62: 0.77508513 | ABF62: 3.2851092 | ABG62: 1.7033689 | ABH62: 2.1120967 | ABI62: 0.86190929 | ABJ62: 3.6210647 | ABK62: 2.7352875 | ABL62: 1.6974277 | ABM62: 0.81454856 | ABN62: 1.2513831 | ABO62: 2.575818 | ABP62: 1.6762989 | ABQ62: 2.5579083 | ABR62: 2.8348519 | ABS62: 2.4209973 | ABT62: 2.7081242 | ABU62: 2.6435698 | ABV62: 1.3014076 | ABW62: 3.0686622 | ABX62: 0.74696951 | ABY62: 0.77829538 | ABZ62: 1.4445336 | ACA62: 0.70040534 | ACB62: 0.84564194 | ACC62: 2.1722651 | ACD62: 1.5948487 | ACE62: 1.0477161 | ACF62: 3.7264125 | ACG62: 3.0060286 | ACH62: 1.9088624 | ACI62: 2.0038973 | ACJ62: 2.5216775 | ACK62: 0.62489567 | ACL62: 1.9134555 | ACM62: 2.4695557 | ACN62: 1.8122446 | ACO62: 2.7954094 | ACP62: -1.4087845 | ACQ62: 1.7055863 | ACR62: 1.4953362 | ACS62: 0.79708679 | ACT62: 0.88503889 | ACU62: 0.28090852 | ACV62: 0.93782798 | ACW62: 1.7379599 | ACX62: 3.181027 | ACY62: 1.036859 | ACZ62: 0.45076701 | ADA62: 2.8952273 | ADB62: 1.0167731 | ADC62: 2.2333422 | ADD62: 0.53095609 | ADE62: 1.6719908 | ADF62: 1.0233105 | ADG62: 3.2284834 | ADH62: 1.3244259 | ADI62: 2.159803 | ADJ62: 2.4049781 | ADK62: 2.1663966 | ADL62: 1.1847333 | ADM62: 1.1705504 | ADN62: 1.0759487 | ADO62: 2.1461943 | ADP62: 2.2547022 | ADQ62: 1.0376059 | ADR62: 0.72066255 | ADS62: 1.3726148 | ADT62: -0.24234277 | ADU62: 2.734324 | ADV62: 5.0313816 | ADW62: 1.4161032 | ADX62: 2.2487142 | ADY62: 0.89943648 | ADZ62: 2.4931075 | AEA62: 2.6361878 | AEB62: 1.5998861 | AEC62: 1.1573524 | AED62: 0.632918 | AEE62: 1.9268835 | AEF62: 2.2626094 | AEG62: 2.2615686 | AEH62: 0.5999487 | AEI62: 4.9085359 | AEJ62: 1.6719619 | AEK62: 1.0045998 | AEL62: 1.4346437 | AEM62: 1.6168687 | AEN62: -0.22109938 | AEO62: 2.6598726 | AEP62: 2.4606624 | AEQ62: 0.67581122 | AER62: 3.238433 | AES62: 0.13689142 | AET62: 0.00052707262 | AEU62: -0.12487787 | AEV62: 1.1091478 | AEW62: 1.2127938 | AEX62: 2.1246481 | AEY62: 3.4527164 | AEZ62: 0.5795169 | AFA62: 1.8372098 | AFB62: 2.467539 | AFC62: 1.189236 | AFD62: 2.9288725 | AFE62: 1.8193691 | AFF62: 0.6103434 | AFG62: 2.0881376 | AFH62: 1.2404332 | AFI62: -1.4291906 | AFJ62: 1.9768991 | AFK62: 2.5505474 | AFL62: 1.2176033 | AFM62: 2.19773 | AFN62: 0.4268426 | AFO62: 1.3070604 | AFP62: 2.6528602 | AFQ62: 2.9240949 | AFR62: 0.18675905 | AFS62: 2.7350044 | AFT62: 1.2574554 | AFU62: 2.9588737 | AFV62: 2.0829721 | AFW62: 2.321865 | AFX62: 2.8545425 | AFY62: 3.6810761 | AFZ62: 1.8632964 | AGA62: 3.9596911 | AGB62: -0.55171666 | AGC62: 1.4690095 | AGD62: 4.7797884 | AGE62: 1.5251529 | AGF62: 0.84772817 | AGG62: -0.10030493 | AGH62: 1.9186487 | AGI62: 3.1204477 | AGJ62: 2.3155891 | AGK62: 2.9231796 | AGL62: 2.6586459 | AGM62: 2.8702238 | AGN62: 1.1541628 | AGO62: 0.91054815 | AGP62: 1.5708261 | AGQ62: 2.2408888 | AGR62: 1.9912742 | AGS62: 1.2922873 | AGT62: 2.2266376 | AGU62: 3.8054055 | AGV62: 3.2729492 | AGW62: 1.856728 | AGX62: 2.6651495 | AGY62: 1.5201533 | AGZ62: 1.092092 | AHA62: 1.4852004 | AHB62: 1.4719514 | AHC62: 2.0662745 | AHD62: 1.6472167 | AHE62: 0.41125148 | AHF62: 1.5085264 | AHG62: 1.8943347 | AHH62: 2.4724697 | AHI62: 3.2918326 | AHJ62: 1.9677178 | AHK62: 1.0567045 | AHL62: 1.4383015 | AHM62: 1.1805305 | AHN62: 3.009304 | AHO62: 2.1676819 | AHP62: 0.43117422 | AHQ62: 3.1095749 | AHR62: 2.9878569 | AHS62: 0.65924384 | AHT62: 1.3091541 | AHU62: 1.4964185 | AHV62: -1.9940332 | AHW62: 1.4760523 | AHX62: 2.4737066 | AHY62: 1.2236031 | AHZ62: 2.295552 | AIA62: 3.5400076 | AIB62: 0.29747686 | AIC62: -1.306493 | AID62: 1.6311195 | AIE62: 1.3082873 | AIF62: -0.59994729 | AIG62: 1.287332 | AIH62: 1.2560263 | AII62: 2.5492904 | AIJ62: 1.3535201 | AIK62: 3.3932119 | AIL62: 1.2077028 | AIM62: 3.2484898 | AIN62: 3.6891525 | AIO62: 3.2886015 | AIP62: 0.44476636 | AIQ62: 1.9124302 | AIR62: 0.6197659 | AIS62: 1.7336512 | AIT62: 3.4208124 | AIU62: 0.4441535 | AIV62: 1.657727 | AIW62: 1.3806193 | AIX62: 0.99967941 | AIY62: 1.3260033 | AIZ62: 3.4792777 | AJA62: 1.443958 | AJB62: 3.6737374 | AJC62: 1.949942 | AJD62: 0.3676505 | AJE62: 2.9460296 | AJF62: 1.6878621 | AJG62: 1.5246588 | AJH62: -0.17097697 | AJI62: 2.0798506 | AJJ62: 2.9821852 | AJK62: 2.3380421 | AJL62: 3.0553604 | AJM62: 2.2628887 | AJN62: 1.9667041 | AJO62: 2.8126858 | AJP62: 1.0021788 | AJQ62: 1.04737 | AJR62: 4.0450186 | AJS62: 1.1438146 | AJT62: 3.4961508 | AJU62: 1.9092647 | AJV62: 0.26024528 | AJW62: -0.88230009 | AJX62: 1.716488 | AJY62: 3.1799613 | AJZ62: 1.9547 | AKA62: 1.868267 | AKB62: 0.60498588 | AKC62: -0.97671756 | AKD62: 1.3083859 | AKE62: 1.2681688 | AKF62: 1.7112154 | AKG62: 1.4856055 | AKH62: 0.97273307 | AKI62: -0.15116114 | AKJ62: 1.9516423 | AKK62: 2.4381421 | AKL62: 2.1660318 | AKM62: 1.4726144 | AKN62: 0.71975334 | AKO62: 2.2197914 | AKP62: 0.32297701 | AKQ62: 1.6909394 | AKR62: 0.98463369 | AKS62: 3.4046449 | AKT62: 0.71006021 | AKU62: 2.1141105 | AKV62: 2.9717078 | AKW62: 1.8154336 | AKX62: 1.9720168 | AKY62: 0.37383401 | AKZ62: 2.1147144 | ALA62: 0.13808953 | ALB62: 0.92420188 | ALC62: 1.4760878 | ALD62: 1.4543301 | ALE62: 1.49884 | ALF62: 0.76935491 | ALG62: 1.3800302 | ALH62: 1.3826525 | ALI62: 4.1048491 | ALJ62: -0.11649298 | ALK62: 1.6049693 | ALL62: 0.69002921 | ALM62: 2.4566105
A63: 31 | B63: =_xlfn.NORM.INV(RAND(),'Inflation Rates '!$B$401,'Inflation Rates '!$B$402) -> 3.0639434 | C63: 3.2827038 | D63: 1.5540832 | E63: 1.0904728 | F63: 1.0032551 | G63: 0.78228814 | H63: 1.5169672 | I63: 1.0024894 | J63: 1.1540737 | K63: -0.19055344 | L63: 1.4192897 | M63: -1.1018369 | N63: 3.2186672 | O63: 1.1942484 | P63: 0.16088683 | Q63: 1.5869591 | R63: 1.825116 | S63: -0.24659902 | T63: 1.0935446 | U63: -0.19590899 | V63: -0.076619284 | W63: 1.7430394 | X63: 0.92728052 | Y63: 0.42153436 | Z63: -0.19439841 | AA63: 3.4227803 | AB63: 1.8808497 | AC63: 0.96472317 | AD63: 2.5729464 | AE63: -0.1609105 | AF63: 1.3734125 | AG63: -0.055474526 | AH63: 1.7094573 | AI63: 2.761682 | AJ63: 2.2492158 | AK63: 2.2698968 | AL63: 4.247476 | AM63: 0.99799447 | AN63: 2.8975998 | AO63: 2.2454039 | AP63: 0.46215668 | AQ63: 0.52431546 | AR63: 2.2917331 | AS63: 0.31968749 | AT63: 1.5518139 | AU63: 0.99390825 | AV63: 1.8849577 | AW63: 2.1163695 | AX63: 1.7277376 | AY63: 2.2400395 | AZ63: 2.577451 | BA63: 0.12952601 | BB63: 0.50256613 | BC63: 2.661652 | BD63: 2.6886492 | BE63: 2.5362167 | BF63: 2.7620823 | BG63: 1.9020728 | BH63: 3.3030892 | BI63: 1.7924719 | BJ63: 1.0083963 | BK63: 2.2722298 | BL63: 0.75262231 | BM63: 1.9935187 | BN63: 1.7633302 | BO63: -0.48405234 | BP63: 2.8146644 | BQ63: 2.5748485 | BR63: 1.9508231 | BS63: 2.1854814 | BT63: 3.7227544 | BU63: 2.3759165 | BV63: -0.099308107 | BW63: 1.9131427 | BX63: 3.889562 | BY63: -0.21058689 | BZ63: 2.7048501 | CA63: 0.79387797 | CB63: 1.5989285 | CC63: 1.7165707 | CD63: 2.5111947 | CE63: 4.044202 | CF63: 4.002625 | CG63: 0.39932317 | CH63: 1.5357295 | CI63: 0.98734881 | CJ63: 2.2187231 | CK63: 3.2880846 | CL63: 1.6745895 | CM63: 1.9859186 | CN63: 1.6398614 | CO63: 0.82954523 | CP63: 2.3700022 | CQ63: 0.9875149 | CR63: 2.9326359 | CS63: 2.5248752 | CT63: 1.808842 | CU63: 2.4091276 | CV63: 2.670934 | CW63: 1.0538045 | CX63: 2.2341889 | CY63: 1.3670633 | CZ63: 1.3303861 | DA63: -0.68350108 | DB63: 1.6015739 | DC63: 1.0151352 | DD63: 3.3374675 | DE63: 2.7973621 | DF63: 0.094451974 | DG63: 2.0286145 | DH63: 4.4493098 | DI63: 2.56002 | DJ63: 1.9657708 | DK63: 2.3671166 | DL63: 1.1298344 | DM63: 3.0486066 | DN63: 1.8686317 | DO63: 0.35326072 | DP63: 0.3967143 | DQ63: 1.8051552 | DR63: 1.4715883 | DS63: 1.3331259 | DT63: 0.33104249 | DU63: 0.91856011 | DV63: -0.58109915 | DW63: 2.1524538 | DX63: -2.1365546 | DY63: 0.032952436 | DZ63: 1.2762418 | EA63: 1.1009581 | EB63: 1.5668335 | EC63: 1.6176776 | ED63: 2.8515068 | EE63: 0.39872122 | EF63: 2.3859967 | EG63: 1.4055051 | EH63: 0.79145872 | EI63: 0.17535478 | EJ63: 1.9177554 | EK63: -0.87486014 | EL63: 1.0602761 | EM63: 0.23226927 | EN63: 0.36535812 | EO63: 0.80497484 | EP63: 2.2009546 | EQ63: 4.0917156 | ER63: 3.2739754 | ES63: 0.84718019 | ET63: 0.38419225 | EU63: 1.7672679 | EV63: -0.18668598 | EW63: 3.2903815 | EX63: 1.7467621 | EY63: 2.0891547 | EZ63: 2.5472082 | FA63: 2.2348674 | FB63: 1.1829359 | FC63: 2.1064149 | FD63: 1.9938739 | FE63: -0.53004964 | FF63: 2.5710184 | FG63: 2.0788184 | FH63: 2.5026908 | FI63: 2.2512402 | FJ63: 2.4299521 | FK63: 1.5632625 | FL63: 1.4026094 | FM63: 1.8339261 | FN63: 3.4128773 | FO63: 0.38219785 | FP63: 1.5855931 | FQ63: -0.64008245 | FR63: 2.3437926 | FS63: 1.1415943 | FT63: 3.3685858 | FU63: 1.6725184 | FV63: 0.95287743 | FW63: 0.23266727 | FX63: 2.4081368 | FY63: 2.6045966 | FZ63: 2.25746 | GA63: 3.0750283 | GB63: 0.83627351 | GC63: 1.0747607 | GD63: 3.2590873 | GE63: 1.8703463 | GF63: 2.2700623 | GG63: 2.0932659 | GH63: 2.0362601 | GI63: 0.13046647 | GJ63: -0.5570033 | GK63: 2.1697153 | GL63: 1.9468584 | GM63: 2.7074376 | GN63: 2.883755 | GO63: 1.7159076 | GP63: 2.2851296 | GQ63: 0.7680064 | GR63: 0.19935258 | GS63: 1.6637704 | GT63: 0.26905261 | GU63: 3.5780956 | GV63: 0.31102928 | GW63: 3.7710355 | GX63: 1.1957186 | GY63: 3.6128788 | GZ63: 3.3935566 | HA63: 0.80272374 | HB63: 0.82894173 | HC63: 1.1881573 | HD63: 0.87947445 | HE63: 0.14150228 | HF63: 2.5621884 | HG63: 0.48024663 | HH63: 1.8117702 | HI63: 3.2583539 | HJ63: 1.8045925 | HK63: -0.31285384 | HL63: 3.2310541 | HM63: 2.3487733 | HN63: -0.040389489 | HO63: 3.6064581 | HP63: 1.3958671 | HQ63: 1.6670532 | HR63: 1.8769817 | HS63: 1.7546215 | HT63: 1.9437856 | HU63: 2.1459618 | HV63: 2.5869203 | HW63: 3.7281244 | HX63: 1.9190559 | HY63: 1.3685674 | HZ63: 1.368287 | IA63: 0.26365133 | IB63: 1.023382 | IC63: 2.1751452 | ID63: 3.6936058 | IE63: 1.0640732 | IF63: -0.008677799 | IG63: 2.6974897 | IH63: 4.7407649 | II63: 1.0218944 | IJ63: 2.2619873 | IK63: 3.1075112 | IL63: -0.19447089 | IM63: 2.0832278 | IN63: 1.9622934 | IO63: 1.8961428 | IP63: 2.3979961 | IQ63: 0.98158626 | IR63: 0.99256983 | IS63: 1.9317272 | IT63: -0.264897 | IU63: 0.83900208 | IV63: 4.0600008 | IW63: 3.8931789 | IX63: 0.41257108 | IY63: 1.1716273 | IZ63: 1.9397326 | JA63: -0.21032529 | JB63: 1.4117173 | JC63: 0.84123405 | JD63: 2.3191792 | JE63: 3.3202188 | JF63: 2.6497491 | JG63: 2.1356146 | JH63: 1.5624517 | JI63: 3.830253 | JJ63: 0.28240599 | JK63: 2.2155027 | JL63: 1.3266186 | JM63: 1.1287606 | JN63: -0.43055378 | JO63: 0.51310667 | JP63: 0.43377686 | JQ63: 4.3287723 | JR63: 2.9773795 | JS63: 0.74483917 | JT63: 2.2177763 | JU63: 0.010000083 | JV63: 2.9324852 | JW63: 2.6746242 | JX63: 0.41542678 | JY63: 0.13326197 | JZ63: 0.34696871 | KA63: 1.6427858 | KB63: 2.6645797 | KC63: 2.8348404 | KD63: 2.6743223 | KE63: 2.8369589 | KF63: 0.64261524 | KG63: 1.8544235 | KH63: 2.2377073 | KI63: 1.1520405 | KJ63: 1.354853 | KK63: 2.3015087 | KL63: 2.1335777 | KM63: 2.0336067 | KN63: 4.3394166 | KO63: 0.82184504 | KP63: 1.7479247 | KQ63: 1.8942187 | KR63: 1.9302097 | KS63: 2.8433726 | KT63: -0.55496591 | KU63: 2.7663099 | KV63: 3.3147601 | KW63: 3.6480954 | KX63: 0.14628763 | KY63: -0.46319503 | KZ63: 0.47468926 | LA63: 1.9427533 | LB63: 2.1044919 | LC63: 0.58798482 | LD63: 1.4959106 | LE63: 1.9032487 | LF63: 1.8937824 | LG63: 4.4169393 | LH63: 1.5406609 | LI63: 1.7307819 | LJ63: 1.1663731 | LK63: 2.8710675 | LL63: 3.1926875 | LM63: 2.6379382 | LN63: -0.45968503 | LO63: 1.8485537 | LP63: 1.7338018 | LQ63: 1.1886966 | LR63: 3.0000963 | LS63: 2.958326 | LT63: 0.30171651 | LU63: 4.8065661 | LV63: 0.53612824 | LW63: 1.247101 | LX63: 1.5011541 | LY63: 4.0646762 | LZ63: 1.9686677 | MA63: 1.133299 | MB63: 0.90167792 | MC63: 2.9666198 | MD63: 0.0065905265 | ME63: 1.5150668 | MF63: 3.2508038 | MG63: 1.993532 | MH63: 0.26037523 | MI63: 3.5382161 | MJ63: 1.8263049 | MK63: 2.2008078 | ML63: 2.4677757 | MM63: 3.5624826 | MN63: 1.6182208 | MO63: 1.6986666 | MP63: 2.0198228 | MQ63: 1.6311592 | MR63: 1.0193397 | MS63: 0.24214034 | MT63: 2.1782542 | MU63: 0.31025479 | MV63: 0.28747101 | MW63: 1.6495858 | MX63: 3.1432958 | MY63: 1.0647465 | MZ63: 1.3939443 | NA63: 5.8063723 | NB63: 4.1188599 | NC63: 1.5197106 | ND63: 0.97870093 | NE63: 4.4195998 | NF63: 1.8661198 | NG63: 2.8511855 | NH63: 0.16287528 | NI63: -0.88707842 | NJ63: 1.7551075 | NK63: 2.7133965 | NL63: 4.1629392 | NM63: 0.61902913 | NN63: 2.4699796 | NO63: 0.099779301 | NP63: 2.8962923 | NQ63: 2.1890555 | NR63: 1.4632826 | NS63: 1.4070088 | NT63: 1.3129276 | NU63: 1.2710788 | NV63: 3.250567 | NW63: 1.6825079 | NX63: 1.6984851 | NY63: 1.9685766 | NZ63: 2.6152791 | OA63: 2.7861484 | OB63: -0.25671322 | OC63: 2.5704662 | OD63: 2.4785121 | OE63: 1.7544421 | OF63: 1.6877721 | OG63: 2.5737346 | OH63: 0.81752156 | OI63: -0.091109757 | OJ63: 0.02002528 | OK63: 2.9251996 | OL63: 3.2677204 | OM63: 1.7286001 | ON63: 1.6040039 | OO63: 1.9685037 | OP63: 1.3165574 | OQ63: 2.259405 | OR63: 3.0568594 | OS63: 0.38584393 | OT63: 0.35506603 | OU63: 1.3371229 | OV63: 0.62759131 | OW63: 2.4261969 | OX63: 0.71771876 | OY63: 4.1796757 | OZ63: 2.6538696 | PA63: -0.8817984 | PB63: 0.6957465 | PC63: 1.4694713 | PD63: 0.14505753 | PE63: 2.7053855 | PF63: 1.4575266 | PG63: 3.1730962 | PH63: 2.6347751 | PI63: 1.6296843 | PJ63: 1.7673757 | PK63: 1.9484189 | PL63: 1.2192924 | PM63: 0.1982646 | PN63: 1.8818095 | PO63: 1.1914644 | PP63: 3.8441241 | PQ63: 2.1050617 | PR63: 0.75574035 | PS63: 3.2015698 | PT63: 2.5775408 | PU63: 1.0460434 | PV63: 1.7760331 | PW63: 2.38403 | PX63: 2.3604362 | PY63: 1.2948382 | PZ63: 2.2357139 | QA63: 0.90742486 | QB63: -0.060300957 | QC63: 2.2073004 | QD63: 2.9340177 | QE63: 1.9967024 | QF63: 2.8536858 | QG63: 2.0997957 | QH63: 3.7889872 | QI63: 2.3704195 | QJ63: 1.8062723 | QK63: 1.9268637 | QL63: 2.1042913 | QM63: 4.1120295 | QN63: 3.1182121 | QO63: 0.68547444 | QP63: 0.97481635 | QQ63: 1.7848997 | QR63: 0.75832367 | QS63: -0.30770661 | QT63: 2.5952712 | QU63: 2.1428992 | QV63: 3.452694 | QW63: 2.5043187 | QX63: 2.2619735 | QY63: 1.7953421 | QZ63: 2.3389281 | RA63: 1.1394239 | RB63: 2.9539141 | RC63: 1.0816931 | RD63: 2.0932199 | RE63: 0.3903489 | RF63: 2.5222854 | RG63: 2.9553312 | RH63: 1.8461011 | RI63: 0.6390171 | RJ63: 2.627066 | RK63: 3.3056459 | RL63: -0.90873095 | RM63: 0.085496673 | RN63: 1.5545432 | RO63: 2.6548551 | RP63: 1.8685125 | RQ63: 1.9564498 | RR63: 5.020864 | RS63: 1.7931383 | RT63: 1.5192503 | RU63: 2.1074669 | RV63: 3.2149577 | RW63: 2.2095139 | RX63: 1.913445 | RY63: 2.605824 | RZ63: 3.4572497 | SA63: 1.3579368 | SB63: 0.7407659 | SC63: 0.53643698 | SD63: 1.8209776 | SE63: 0.070614505 | SF63: 2.7827755 | SG63: 1.7049296 | SH63: 1.6031695 | SI63: 4.3031677 | SJ63: 0.37103187 | SK63: -1.4630821 | SL63: 2.2640188 | SM63: 1.5339985 | SN63: 1.8822947 | SO63: 2.3933367 | SP63: -0.53321357 | SQ63: 1.2264258 | SR63: 1.0686715 | SS63: 1.448337 | ST63: 2.1042089 | SU63: -0.11530683 | SV63: 2.7155516 | SW63: 1.1272387 | SX63: 2.5543871 | SY63: 3.6248541 | SZ63: 3.4993515 | TA63: 1.069333 | TB63: -0.97840895 | TC63: 0.51830993 | TD63: 1.6161569 | TE63: 3.8783363 | TF63: 3.6826229 | TG63: -0.18178071 | TH63: 3.285002 | TI63: 1.7538698 | TJ63: 2.4666314 | TK63: 0.13415302 | TL63: 0.20113427 | TM63: 2.0940628 | TN63: 1.9331669 | TO63: -0.92706512 | TP63: 0.68723593 | TQ63: 0.81789361 | TR63: 1.6561948 | TS63: 1.5564569 | TT63: 0.79655611 | TU63: 1.5700654 | TV63: 0.46835866 | TW63: 1.6962428 | TX63: 0.99050593 | TY63: 2.0508376 | TZ63: 1.5852445 | UA63: 1.2324419 | UB63: 2.7406423 | UC63: 1.6120979 | UD63: 3.0394405 | UE63: 2.6789959 | UF63: 1.9024856 | UG63: 2.3644168 | UH63: 1.5498219 | UI63: 1.6538546 | UJ63: 1.0813388 | UK63: 0.28496083 | UL63: -0.73240592 | UM63: 2.6259822 | UN63: 2.5464796 | UO63: 3.9167015 | UP63: 1.5641268 | UQ63: 1.3985911 | UR63: 1.335159 | US63: -0.45094555 | UT63: 2.3923459 | UU63: 3.1555336 | UV63: 0.3739156 | UW63: 1.3196779 | UX63: 0.094611761 | UY63: -0.66235129 | UZ63: 2.0815516 | VA63: -0.14989577 | VB63: 2.1073871 | VC63: 1.5764457 | VD63: 2.2165242 | VE63: 3.1512784 | VF63: 0.40658344 | VG63: 0.77892637 | VH63: 0.80474114 | VI63: -0.30986 | VJ63: 1.2031832 | VK63: 5.3985094 | VL63: 0.58137589 | VM63: 1.901751 | VN63: -0.65615674 | VO63: 1.3919548 | VP63: 2.4356188 | VQ63: 2.9274763 | VR63: -1.6584934 | VS63: 2.1875641 | VT63: 1.1821839 | VU63: 2.9819557 | VV63: 0.26093493 | VW63: 0.70798683 | VX63: 2.2459341 | VY63: 3.5795392 | VZ63: 1.58294 | WA63: 2.7027779 | WB63: 1.0818861 | WC63: 3.1734224 | WD63: -0.23179257 | WE63: 1.6017803 | WF63: 3.0653659 | WG63: 1.651249 | WH63: 1.1813389 | WI63: -0.45386399 | WJ63: 1.3071228 | WK63: 2.5350599 | WL63: 1.821855 | WM63: 3.1856772 | WN63: 2.0424466 | WO63: 1.8320865 | WP63: 2.0998151 | WQ63: 3.1871787 | WR63: 2.4140117 | WS63: 1.7264338 | WT63: -0.012114419 | WU63: 1.4304775 | WV63: 3.9580037 | WW63: 2.6412298 | WX63: 2.5200028 | WY63: 0.95733089 | WZ63: 2.1802942 | XA63: -0.11194746 | XB63: 0.94934721 | XC63: 3.0422672 | XD63: 2.5883221 | XE63: 1.074335 | XF63: 1.502146 | XG63: 0.43988331 | XH63: 2.9546807 | XI63: 0.26983861 | XJ63: 2.1442916 | XK63: 1.3315949 | XL63: 3.7096188 | XM63: -0.2682414 | XN63: 1.0761523 | XO63: 1.6916565 | XP63: 3.0709537 | XQ63: -0.21515751 | XR63: 1.490481 | XS63: 3.1089562 | XT63: 1.3693674 | XU63: -0.40608371 | XV63: 2.2204676 | XW63: 3.6368889 | XX63: 2.2698253 | XY63: 3.4048619 | XZ63: 2.849066 | YA63: 2.1934513 | YB63: 3.6862633 | YC63: 1.6038347 | YD63: 0.41683469 | YE63: 2.7814367 | YF63: 0.93512494 | YG63: 0.43114957 | YH63: -1.4680674 | YI63: 3.0373191 | YJ63: -0.43342718 | YK63: 2.8383525 | YL63: 1.418109 | YM63: 1.9882167 | YN63: 2.7577998 | YO63: 2.3583092 | YP63: 1.4526404 | YQ63: 3.398407 | YR63: 2.3426652 | YS63: 1.0860003 | YT63: 2.4423022 | YU63: 0.64214197 | YV63: 1.6617378 | YW63: 2.2591994 | YX63: 0.77937707 | YY63: 0.50620945 | YZ63: 1.4054595 | ZA63: 1.08573 | ZB63: 1.5847227 | ZC63: 2.7720405 | ZD63: 1.730364 | ZE63: 1.6058386 | ZF63: -1.0781427 | ZG63: 3.1793868 | ZH63: 1.3575661 | ZI63: 0.64942475 | ZJ63: 1.3023593 | ZK63: 1.4239408 | ZL63: 1.8168852 | ZM63: 2.300272 | ZN63: 2.4035885 | ZO63: 1.1268523 | ZP63: 1.3641414 | ZQ63: 2.808167 | ZR63: 1.5029865 | ZS63: 1.8353215 | ZT63: -0.73104171 | ZU63: 1.0819386 | ZV63: 2.780585 | ZW63: 1.5352889 | ZX63: 2.6411249 | ZY63: 1.0175305 | ZZ63: 3.2975099 | AAA63: 3.5412477 | AAB63: 2.96768 | AAC63: 1.4484741 | AAD63: 2.4955956 | AAE63: -0.07937871 | AAF63: 1.3993201 | AAG63: 1.1741109 | AAH63: 2.9749532 | AAI63: 1.6285362 | AAJ63: 2.9977196 | AAK63: 2.118168 | AAL63: 0.83949784 | AAM63: 0.70242584 | AAN63: 5.3974417 | AAO63: 1.6553223 | AAP63: 1.211291 | AAQ63: -0.34344359 | AAR63: -1.1046587 | AAS63: 0.27007572 | AAT63: 1.7665683 | AAU63: 2.0222947 | AAV63: 1.5621753 | AAW63: 2.5957032 | AAX63: 3.2403843 | AAY63: 1.2215023 | AAZ63: 0.092459209 | ABA63: 1.0091399 | ABB63: 2.08492 | ABC63: 2.3785539 | ABD63: 1.9963981 | ABE63: 1.8690371 | ABF63: -0.99430473 | ABG63: 1.4086089 | ABH63: 2.6241521 | ABI63: 2.3849093 | ABJ63: 2.1344689 | ABK63: 3.3952251 | ABL63: 3.2744191 | ABM63: 2.0088919 | ABN63: 1.010489 | ABO63: 3.567392 | ABP63: 0.019905641 | ABQ63: 2.8033986 | ABR63: 2.4315164 | ABS63: 3.6855749 | ABT63: 2.4688657 | ABU63: 1.4952078 | ABV63: 0.86171858 | ABW63: 3.0722072 | ABX63: 0.5464808 | ABY63: 1.8051396 | ABZ63: 0.8369804 | ACA63: 1.634101 | ACB63: 1.6750476 | ACC63: 1.1471032 | ACD63: 0.36631605 | ACE63: 1.7253868 | ACF63: 0.24547533 | ACG63: 0.82256865 | ACH63: 0.35606258 | ACI63: 1.6211711 | ACJ63: 1.8670048 | ACK63: 0.85685162 | ACL63: 2.1141451 | ACM63: 1.1038781 | ACN63: 1.5865562 | ACO63: 1.1063433 | ACP63: 1.862523 | ACQ63: 0.95875113 | ACR63: 4.9249411 | ACS63: 3.5604694 | ACT63: 1.8875668 | ACU63: 3.8823699 | ACV63: -0.55529503 | ACW63: 1.9714986 | ACX63: 3.0789591 | ACY63: 2.6425966 | ACZ63: 0.17272772 | ADA63: 2.2053012 | ADB63: 2.3877159 | ADC63: -0.06758311 | ADD63: 1.7925042 | ADE63: 1.0040475 | ADF63: 1.8900759 | ADG63: 2.2750579 | ADH63: 1.5670402 | ADI63: 3.0579549 | ADJ63: 2.7465889 | ADK63: 3.2754268 | ADL63: 2.1295558 | ADM63: 0.53895116 | ADN63: 1.1989391 | ADO63: 1.078232 | ADP63: 2.7410593 | ADQ63: 2.7417874 | ADR63: 0.93041407 | ADS63: 3.2642224 | ADT63: 2.1927048 | ADU63: -1.3615098 | ADV63: 1.5731721 | ADW63: -0.22756833 | ADX63: 3.5658492 | ADY63: 0.57603515 | ADZ63: 1.2422807 | AEA63: 1.2418526 | AEB63: 0.77701654 | AEC63: 3.8426146 | AED63: 0.86751061 | AEE63: 1.1814708 | AEF63: 3.3965575 | AEG63: 3.8750875 | AEH63: 2.8539564 | AEI63: 4.5610236 | AEJ63: 3.80243 | AEK63: 0.95081478 | AEL63: -0.67982485 | AEM63: 4.5807049 | AEN63: 2.9038132 | AEO63: 2.8525317 | AEP63: 1.6707848 | AEQ63: 1.5232553 | AER63: 0.67130521 | AES63: 0.54477103 | AET63: 2.9982045 | AEU63: 0.61984957 | AEV63: 2.6647133 | AEW63: 2.5116097 | AEX63: 2.154363 | AEY63: 0.21139777 | AEZ63: 1.4884816 | AFA63: 2.3058343 | AFB63: 1.3295248 | AFC63: -1.2913819 | AFD63: -0.69162323 | AFE63: 1.2663927 | AFF63: 2.1375777 | AFG63: 1.4355485 | AFH63: 1.886251 | AFI63: 2.9293791 | AFJ63: 0.10310028 | AFK63: 2.8004607 | AFL63: 0.5243729 | AFM63: 0.54709532 | AFN63: 0.98781524 | AFO63: 1.4076139 | AFP63: 3.2016092 | AFQ63: 1.6105241 | AFR63: 0.64772704 | AFS63: 0.62958783 | AFT63: 0.63385778 | AFU63: 2.9931276 | AFV63: 0.83373983 | AFW63: 1.0713871 | AFX63: 1.7488894 | AFY63: 1.3774997 | AFZ63: 1.4746276 | AGA63: 3.4922474 | AGB63: -0.31925874 | AGC63: 3.5899726 | AGD63: 1.6240738 | AGE63: 2.0285139 | AGF63: 0.70283086 | AGG63: 0.74003319 | AGH63: 2.9618281 | AGI63: 3.0272008 | AGJ63: 1.1031683 | AGK63: 2.6372067 | AGL63: 1.8945111 | AGM63: 3.7555384 | AGN63: 0.98279329 | AGO63: 1.7898129 | AGP63: 1.7348893 | AGQ63: 1.3619387 | AGR63: 1.3499859 | AGS63: 1.0948819 | AGT63: 1.6042161 | AGU63: 2.6431523 | AGV63: 0.68584352 | AGW63: 1.2646065 | AGX63: 1.6784147 | AGY63: 2.521644 | AGZ63: 1.3722653 | AHA63: 1.5715938 | AHB63: 0.90092318 | AHC63: 4.5384563 | AHD63: 0.19279314 | AHE63: 3.6339572 | AHF63: 2.2186457 | AHG63: 0.99523452 | AHH63: 1.1359487 | AHI63: -0.092075787 | AHJ63: 3.5656416 | AHK63: 0.705618 | AHL63: -0.94282725 | AHM63: 0.71129469 | AHN63: 0.41430271 | AHO63: 0.65984942 | AHP63: 1.3004287 | AHQ63: 0.011423673 | AHR63: 1.6602077 | AHS63: 2.8128143 | AHT63: 2.2613682 | AHU63: 0.69052623 | AHV63: 1.7152525 | AHW63: -1.1431576 | AHX63: 2.383158 | AHY63: 1.2631363 | AHZ63: -1.7310874 | AIA63: -0.60207846 | AIB63: 2.4603709 | AIC63: 0.17651119 | AID63: 1.8579434 | AIE63: 0.86232929 | AIF63: 1.2128873 | AIG63: 1.2080319 | AIH63: 0.56492299 | AII63: 3.4388282 | AIJ63: 2.5110098 | AIK63: 2.5217017 | AIL63: 0.41345722 | AIM63: 1.6456324 | AIN63: 1.9532603 | AIO63: 3.6416752 | AIP63: 2.0922461 | AIQ63: 2.3054572 | AIR63: 0.89333103 | AIS63: 0.95618545 | AIT63: 3.4430194 | AIU63: 1.0960951 | AIV63: 2.7914404 | AIW63: 1.336154 | AIX63: 1.5895105 | AIY63: 1.6065257 | AIZ63: -0.126471 | AJA63: 0.067138481 | AJB63: 1.058621 | AJC63: 4.3774858 | AJD63: 2.6654279 | AJE63: 1.9113235 | AJF63: -0.58608444 | AJG63: 4.3857877 | AJH63: 1.1339746 | AJI63: 3.0970125 | AJJ63: 2.8182246 | AJK63: 0.23935581 | AJL63: 1.5708787 | AJM63: 3.3133111 | AJN63: 1.3590041 | AJO63: 1.1905966 | AJP63: 1.5186103 | AJQ63: 2.9758131 | AJR63: 0.53239194 | AJS63: 1.5480135 | AJT63: 1.2900727 | AJU63: 1.8867309 | AJV63: 1.5211838 | AJW63: -0.05854373 | AJX63: -0.034533177 | AJY63: 0.5587099 | AJZ63: 0.6678876 | AKA63: 1.3495628 | AKB63: 2.8999526 | AKC63: 2.8656381 | AKD63: 1.5530574 | AKE63: 3.945138 | AKF63: 2.3512924 | AKG63: 3.6070733 | AKH63: 1.4453297 | AKI63: 2.4769766 | AKJ63: 1.020289 | AKK63: 2.2192481 | AKL63: 3.2639064 | AKM63: 0.74061255 | AKN63: 0.37057643 | AKO63: 3.0576767 | AKP63: 1.316971 | AKQ63: 1.188065 | AKR63: 2.1398414 | AKS63: 1.9776613 | AKT63: 0.075894841 | AKU63: 2.0834814 | AKV63: 1.8540402 | AKW63: 1.484287 | AKX63: 2.9528397 | AKY63: -0.085181386 | AKZ63: 1.1782107 | ALA63: 2.3616278 | ALB63: 2.0526311 | ALC63: 1.349289 | ALD63: 2.9239785 | ALE63: 2.6001349 | ALF63: 1.01338 | ALG63: 2.81666 | ALH63: -0.041809205 | ALI63: 1.5557319 | ALJ63: 2.7268419 | ALK63: -0.73881223 | ALL63: 2.568411 | ALM63: -0.22222771
A64: 32 | B64: =_xlfn.NORM.INV(RAND(),'Inflation Rates '!$B$401,'Inflation Rates '!$B$402) -> 2.1370674 | C64: 0.30300663 | D64: 0.42320358 | E64: 2.7931879 | F64: 1.2239345 | G64: -0.4960109 | H64: 0.63082363 | I64: 1.6704259 | J64: 1.4850157 | K64: 3.7762589 | L64: 0.035163039 | M64: 2.0603836 | N64: 2.6507775 | O64: 2.6972562 | P64: 3.756852 | Q64: 2.2417861 | R64: 3.1351446 | S64: 0.80740294 | T64: 3.0266268 | U64: 0.6581934 | V64: 1.6154699 | W64: 0.5735233 | X64: 3.011529 | Y64: 1.4108694 | Z64: 2.5753895 | AA64: 1.5454865 | AB64: 0.58092872 | AC64: 1.8115254 | AD64: -0.08898416 | AE64: 3.0703445 | AF64: 0.7780063 | AG64: 0.19651823 | AH64: 0.86680198 | AI64: 2.1743144 | AJ64: 0.44591458 | AK64: 0.93712355 | AL64: 3.0333355 | AM64: 3.2109103 | AN64: -0.21277836 | AO64: 1.4485936 | AP64: 0.039261115 | AQ64: 0.83677898 | AR64: 2.3086696 | AS64: 0.88584121 | AT64: 2.2866351 | AU64: 1.2799582 | AV64: 1.0234901 | AW64: 2.593733 | AX64: 1.3673478 | AY64: 1.1467926 | AZ64: 0.6124997 | BA64: -0.37317455 | BB64: -0.10700597 | BC64: 1.880614 | BD64: 0.54265703 | BE64: -1.7358135 | BF64: 2.0896154 | BG64: 0.86092035 | BH64: 0.97923723 | BI64: 3.2786115 | BJ64: 3.414819 | BK64: 0.75404186 | BL64: 0.84047971 | BM64: 0.45122636 | BN64: 3.2086009 | BO64: 3.5324908 | BP64: 3.1727339 | BQ64: 1.5741437 | BR64: 3.2829344 | BS64: 0.89866309 | BT64: 0.31869255 | BU64: 0.8928274 | BV64: 0.77543252 | BW64: 1.0454383 | BX64: 1.4544233 | BY64: 2.243075 | BZ64: 2.9034584 | CA64: 1.6777049 | CB64: 0.97603515 | CC64: 2.1878613 | CD64: 1.4389151 | CE64: 3.6260009 | CF64: 1.2253757 | CG64: 1.7469157 | CH64: 0.91658725 | CI64: 2.2834171 | CJ64: 1.6007187 | CK64: 1.5796323 | CL64: 3.3636874 | CM64: 1.7507827 | CN64: 3.2904914 | CO64: 1.1104707 | CP64: 3.6883651 | CQ64: 2.6429559 | CR64: 2.7130559 | CS64: 2.650789 | CT64: 0.99307309 | CU64: 2.2379353 | CV64: 1.7448152 | CW64: 0.55877562 | CX64: 0.7434531 | CY64: 0.30844074 | CZ64: 1.8583905 | DA64: 1.1240861 | DB64: 1.3105527 | DC64: 1.5850001 | DD64: 2.1329195 | DE64: 2.0686434 | DF64: 3.5545871 | DG64: 2.568835 | DH64: 2.5962416 | DI64: 2.1739113 | DJ64: 0.64957528 | DK64: 1.8448892 | DL64: 2.5740629 | DM64: 1.6510668 | DN64: -1.0693624 | DO64: 2.0699622 | DP64: 3.020261 | DQ64: 1.3422906 | DR64: 2.2048355 | DS64: 0.56436115 | DT64: 2.4026148 | DU64: 1.8470795 | DV64: 1.8121295 | DW64: 1.9724844 | DX64: 0.9674616 | DY64: 1.1742723 | DZ64: 2.0833331 | EA64: 1.6191326 | EB64: 1.8010084 | EC64: 0.86779394 | ED64: 0.18269591 | EE64: 1.6643942 | EF64: 0.72846546 | EG64: 2.3301143 | EH64: 0.93922793 | EI64: 3.6017168 | EJ64: -0.16641459 | EK64: 2.5732329 | EL64: 1.6492592 | EM64: 1.4253023 | EN64: 2.5282096 | EO64: 1.8152932 | EP64: 1.9050711 | EQ64: 1.5620113 | ER64: 2.4022468 | ES64: 1.741578 | ET64: 1.922901 | EU64: 3.9693669 | EV64: -0.51594193 | EW64: 0.64299847 | EX64: -4.9227425 | EY64: 0.35798719 | EZ64: 2.8161857 | FA64: 1.5000711 | FB64: 0.25720273 | FC64: 0.063292965 | FD64: 0.60827403 | FE64: 1.7017104 | FF64: 2.5942755 | FG64: 3.2938317 | FH64: -0.49335798 | FI64: 2.2630169 | FJ64: 1.6960066 | FK64: 3.5232043 | FL64: 0.11075425 | FM64: 2.6379007 | FN64: 4.480786 | FO64: 1.7063697 | FP64: 1.8382885 | FQ64: 1.8286533 | FR64: 0.73880719 | FS64: 2.5689024 | FT64: 2.7366624 | FU64: 1.1886687 | FV64: -0.17633066 | FW64: 0.47068217 | FX64: 3.8967459 | FY64: 2.128809 | FZ64: 1.5768649 | GA64: 1.3277748 | GB64: 2.1969759 | GC64: 1.627209 | GD64: 2.1259672 | GE64: 2.1346191 | GF64: 0.6936284 | GG64: 0.35344302 | GH64: 2.054585 | GI64: 2.98861 | GJ64: 2.3148162 | GK64: -0.27468389 | GL64: 1.4422061 | GM64: 1.2938674 | GN64: 3.1708353 | GO64: 1.5932701 | GP64: 0.62616326 | GQ64: 0.97503849 | GR64: 2.4853221 | GS64: 2.0433016 | GT64: 2.3979878 | GU64: 1.3791675 | GV64: 2.3469069 | GW64: 0.75063299 | GX64: 1.7118529 | GY64: 0.19041691 | GZ64: 1.2608139 | HA64: 4.8510071 | HB64: 1.4709661 | HC64: 2.424929 | HD64: 1.3384228 | HE64: 1.6450174 | HF64: 4.3199644 | HG64: 3.4013749 | HH64: 0.33459729 | HI64: 1.3976535 | HJ64: 2.4114307 | HK64: 2.3821529 | HL64: -0.098125207 | HM64: 1.2620338 | HN64: 0.4743361 | HO64: 4.5514094 | HP64: 0.78243917 | HQ64: 0.70905411 | HR64: 3.2915993 | HS64: 0.57197485 | HT64: -0.085852285 | HU64: 2.8101747 | HV64: 1.8703872 | HW64: 2.5406433 | HX64: 0.54153989 | HY64: 2.9944875 | HZ64: 0.89054201 | IA64: 1.061144 | IB64: 2.0682052 | IC64: 1.8880182 | ID64: 2.5141653 | IE64: 1.1179685 | IF64: 4.1282871 | IG64: 3.6645406 | IH64: -0.11760535 | II64: 2.6830961 | IJ64: 2.4060035 | IK64: 3.0081153 | IL64: 0.68394982 | IM64: 2.4088684 | IN64: 1.2613717 | IO64: 1.6066624 | IP64: 0.43286126 | IQ64: 2.1109118 | IR64: 1.0267379 | IS64: 0.82811892 | IT64: 1.5665079 | IU64: 1.3832425 | IV64: 2.2178496 | IW64: 2.6274239 | IX64: 0.50729829 | IY64: -0.87500686 | IZ64: 0.84289017 | JA64: 0.53331337 | JB64: 0.18852188 | JC64: 1.2144607 | JD64: 1.6792538 | JE64: 0.52058127 | JF64: 3.9888846 | JG64: 1.5462811 | JH64: 2.3577549 | JI64: 1.7994216 | JJ64: 1.6301719 | JK64: 2.2807327 | JL64: 1.3636347 | JM64: 2.0160651 | JN64: 1.8127253 | JO64: 2.3730515 | JP64: -0.482931 | JQ64: 0.021640121 | JR64: 1.4007127 | JS64: -0.94523573 | JT64: 0.36735986 | JU64: 0.14862572 | JV64: 0.44311448 | JW64: 2.0653793 | JX64: 2.4349256 | JY64: 0.91385534 | JZ64: 1.6246944 | KA64: 1.2090348 | KB64: 1.2823497 | KC64: 1.1496726 | KD64: 1.6871167 | KE64: 2.5422946 | KF64: 2.6936594 | KG64: 2.3538406 | KH64: 0.19331435 | KI64: 1.901121 | KJ64: 1.6918417 | KK64: 1.4687234 | KL64: 1.3440294 | KM64: 2.0373036 | KN64: 3.945082 | KO64: 0.85536449 | KP64: 2.4652518 | KQ64: 0.74230479 | KR64: 0.098165034 | KS64: 1.4409287 | KT64: 3.3315053 | KU64: 0.82138004 | KV64: 0.93393958 | KW64: 1.5878016 | KX64: -0.0921977 | KY64: -0.2382005 | KZ64: 2.503679 | LA64: 1.6941871 | LB64: 1.7111359 | LC64: 1.3588859 | LD64: 3.3952517 | LE64: 2.7176305 | LF64: 1.065107 | LG64: 1.4275916 | LH64: 3.7887751 | LI64: 1.7533823 | LJ64: 1.5367015 | LK64: 2.6936077 | LL64: 0.13133946 | LM64: 2.18868 | LN64: 1.3010622 | LO64: 1.2971207 | LP64: 2.0618995 | LQ64: 1.3538436 | LR64: 1.8000282 | LS64: 2.0057296 | LT64: 2.7342487 | LU64: -1.2142095 | LV64: 1.2310107 | LW64: 1.0517117 | LX64: 4.2392037 | LY64: 4.0273685 | LZ64: 0.35791492 | MA64: 3.1281383 | MB64: 0.16627425 | MC64: 2.5830942 | MD64: 2.2560126 | ME64: 0.96768339 | MF64: 1.9279152 | MG64: 3.1324026 | MH64: -0.12354075 | MI64: -0.16394628 | MJ64: 1.0043886 | MK64: 1.9567698 | ML64: -0.42658829 | MM64: 2.3536708 | MN64: 2.8448699 | MO64: 0.54983051 | MP64: 0.69522922 | MQ64: 0.83879922 | MR64: 0.95258291 | MS64: -0.23557806 | MT64: 3.623728 | MU64: -1.2437184 | MV64: 2.7934205 | MW64: 1.1997931 | MX64: 3.1116008 | MY64: 2.6375045 | MZ64: 1.3322561 | NA64: 2.4154459 | NB64: 2.0814329 | NC64: 3.9081264 | ND64: 0.95748961 | NE64: 1.3146705 | NF64: 1.2313365 | NG64: 1.5096041 | NH64: 2.2315163 | NI64: 2.5463211 | NJ64: 1.363746 | NK64: 0.54173871 | NL64: -0.12861621 | NM64: 2.8216836 | NN64: 0.51750823 | NO64: 1.8216999 | NP64: 0.66099715 | NQ64: 2.187741 | NR64: 0.72828042 | NS64: 2.4526027 | NT64: 2.2987143 | NU64: 2.1139213 | NV64: 0.90482559 | NW64: 1.9347394 | NX64: 2.2656363 | NY64: 0.7168155 | NZ64: 1.3309203 | OA64: 1.9096897 | OB64: 2.3148682 | OC64: 3.5367521 | OD64: 3.1644148 | OE64: 2.2500529 | OF64: 0.9091912 | OG64: 0.71143419 | OH64: 3.8494188 | OI64: 2.7044837 | OJ64: 0.81832202 | OK64: -0.063213435 | OL64: 1.7289635 | OM64: 2.4803385 | ON64: 2.82565 | OO64: 1.765418 | OP64: 1.6450441 | OQ64: 1.7238847 | OR64: 2.4838626 | OS64: 2.917159 | OT64: 2.2736687 | OU64: 3.2976537 | OV64: -0.94136537 | OW64: 1.510582 | OX64: 2.6008205 | OY64: 3.0769298 | OZ64: 1.3074491 | PA64: 3.3403143 | PB64: 0.31670002 | PC64: 2.4759213 | PD64: 0.11387029 | PE64: 0.65901501 | PF64: 3.52949 | PG64: 4.3602251 | PH64: 1.6905185 | PI64: 1.3207808 | PJ64: 4.5154864 | PK64: 2.7009773 | PL64: 0.20379179 | PM64: 1.2610116 | PN64: 0.73420448 | PO64: 1.722179 | PP64: 1.180753 | PQ64: 2.2465821 | PR64: 1.227737 | PS64: 2.8151952 | PT64: 3.1055572 | PU64: 1.9711219 | PV64: 2.7516617 | PW64: 2.0476866 | PX64: 0.92376213 | PY64: 1.0578601 | PZ64: 3.3400133 | QA64: 0.28277561 | QB64: 0.39216087 | QC64: 0.10993454 | QD64: 1.2591522 | QE64: 1.782438 | QF64: 3.001886 | QG64: 0.12659028 | QH64: 4.3274748 | QI64: 0.37351978 | QJ64: 1.2821829 | QK64: 2.7532539 | QL64: -0.38575098 | QM64: 1.5079999 | QN64: -1.0988242 | QO64: 2.0197948 | QP64: 2.7673843 | QQ64: 4.7640577 | QR64: 0.25289348 | QS64: 1.1614698 | QT64: -0.13893482 | QU64: 0.77220687 | QV64: -0.1459982 | QW64: 0.84592615 | QX64: 2.9718254 | QY64: -2.0142526 | QZ64: 0.89363216 | RA64: 3.4138474 | RB64: 0.78929541 | RC64: 0.86454946 | RD64: 0.23639783 | RE64: 1.1569589 | RF64: 1.8006481 | RG64: 1.9560104 | RH64: 1.5165849 | RI64: 1.2397101 | RJ64: 2.374655 | RK64: 0.51541975 | RL64: 3.1083495 | RM64: 5.0861788 | RN64: 1.778915 | RO64: 1.542135 | RP64: 2.563031 | RQ64: 2.2333445 | RR64: 1.1226009 | RS64: 1.5573091 | RT64: 1.8851718 | RU64: 2.6775367 | RV64: 0.71358216 | RW64: 2.8552436 | RX64: 1.7677138 | RY64: 1.4799367 | RZ64: 3.1243137 | SA64: 1.9531913 | SB64: 1.4776198 | SC64: 1.1395746 | SD64: -1.0240426 | SE64: -0.79596294 | SF64: 1.4103847 | SG64: 1.8231557 | SH64: 1.9476685 | SI64: -1.3458475 | SJ64: 3.582436 | SK64: 0.80628312 | SL64: 1.7782747 | SM64: 2.6818718 | SN64: 1.6408966 | SO64: 0.27635855 | SP64: 1.6715713 | SQ64: 2.1740952 | SR64: 1.453121 | SS64: 0.86351597 | ST64: -0.52413819 | SU64: 3.2452076 | SV64: 1.6559227 | SW64: 1.0534114 | SX64: 4.20713 | SY64: 3.0402406 | SZ64: 0.78012244 | TA64: 1.6766988 | TB64: 0.67135156 | TC64: 1.4499854 | TD64: 1.4826162 | TE64: 0.019864183 | TF64: 1.2739037 | TG64: 0.045662239 | TH64: 1.6990306 | TI64: -1.5229313 | TJ64: 0.28824766 | TK64: -1.1645969 | TL64: 0.2985893 | TM64: 1.0803881 | TN64: 1.812803 | TO64: 0.74077217 | TP64: 1.9874152 | TQ64: -0.14522155 | TR64: 1.6341188 | TS64: 2.8454922 | TT64: 2.0649359 | TU64: 0.028800291 | TV64: 2.5002047 | TW64: 1.0846474 | TX64: 3.2686476 | TY64: 0.35798479 | TZ64: 0.46331995 | UA64: 2.2398723 | UB64: 1.3245106 | UC64: 3.8896071 | UD64: 1.2436146 | UE64: 0.18084564 | UF64: 0.56653045 | UG64: 0.66107507 | UH64: 0.61549201 | UI64: 1.9935517 | UJ64: 1.3041886 | UK64: 2.094025 | UL64: 2.5742904 | UM64: 1.5940671 | UN64: 2.6699728 | UO64: 1.7087324 | UP64: -1.0804231 | UQ64: 2.1239613 | UR64: 3.0008983 | US64: 2.0773032 | UT64: 1.3661872 | UU64: 2.0231885 | UV64: 3.1583401 | UW64: 4.066194 | UX64: 2.0225292 | UY64: 1.5236213 | UZ64: 4.037042 | VA64: 3.4816863 | VB64: 3.1039187 | VC64: -0.023584504 | VD64: 1.4039982 | VE64: 0.30229787 | VF64: 3.4316255 | VG64: 3.5339163 | VH64: 1.8005278 | VI64: -0.69353673 | VJ64: 2.7339908 | VK64: 3.3980307 | VL64: 1.7617969 | VM64: 0.30658759 | VN64: 3.8762064 | VO64: -0.74300749 | VP64: 1.2256546 | VQ64: 3.5407962 | VR64: 2.1023392 | VS64: 1.819377 | VT64: 3.9376605 | VU64: 3.2421237 | VV64: 1.2043875 | VW64: 0.076624224 | VX64: -0.012220654 | VY64: 0.025941635 | VZ64: 0.76101481 | WA64: -0.29107342 | WB64: 2.248797 | WC64: 2.2500269 | WD64: 1.975256 | WE64: 0.31530753 | WF64: 1.875387 | WG64: 2.7520612 | WH64: 1.4778242 | WI64: 0.44374247 | WJ64: -0.18627341 | WK64: 2.6689977 | WL64: 1.7711464 | WM64: 1.6206593 | WN64: 2.4575896 | WO64: -0.49879413 | WP64: 4.2239992 | WQ64: 1.6533151 | WR64: 2.7271691 | WS64: 4.0707895 | WT64: 0.26347129 | WU64: 1.115766 | WV64: 1.6911017 | WW64: 1.8790934 | WX64: 2.8709299 | WY64: 2.9285908 | WZ64: 1.9353913 | XA64: 2.0242165 | XB64: 1.8559961 | XC64: 0.84709774 | XD64: 1.4059709 | XE64: 1.8796982 | XF64: 0.69838935 | XG64: 1.072502 | XH64: 2.2390477 | XI64: 2.9192121 | XJ64: 3.7706909 | XK64: 3.2870814 | XL64: 1.0745049 | XM64: 1.3534113 | XN64: -0.78050388 | XO64: 1.0816728 | XP64: -0.74166159 | XQ64: -0.24731079 | XR64: 1.7611171 | XS64: 2.3854236 | XT64: 2.4807101 | XU64: 1.0310351 | XV64: 1.5935054 | XW64: 2.8288137 | XX64: 2.697621 | XY64: 0.94435874 | XZ64: 2.5100803 | YA64: 0.99035776 | YB64: 2.9205396 | YC64: 0.87242925 | YD64: 2.9812112 | YE64: 1.1026494 | YF64: -0.86174498 | YG64: 0.9313545 | YH64: 1.8032295 | YI64: 2.3820392 | YJ64: 3.3982147 | YK64: 1.7913978 | YL64: -1.5467918 | YM64: 2.913085 | YN64: 1.2652335 | YO64: 2.5910366 | YP64: 2.3962774 | YQ64: 0.50631713 | YR64: 1.6578332 | YS64: 3.9395385 | YT64: 1.3263718 | YU64: 2.590228 | YV64: 1.0095782 | YW64: 1.3207894 | YX64: 2.8403909 | YY64: 2.0365505 | YZ64: 0.4023465 | ZA64: 3.6558363 | ZB64: 1.6810173 | ZC64: 1.1365012 | ZD64: 1.9396954 | ZE64: 0.30888121 | ZF64: 2.6149593 | ZG64: 1.1828752 | ZH64: -1.6968346 | ZI64: 1.0927062 | ZJ64: 2.0967319 | ZK64: 1.0454599 | ZL64: 1.3125008 | ZM64: 1.6327017 | ZN64: 1.0575538 | ZO64: 0.87837316 | ZP64: 0.78757415 | ZQ64: 2.4101406 | ZR64: -0.25478606 | ZS64: 2.3604875 | ZT64: 1.4886485 | ZU64: 0.70686013 | ZV64: 1.3649325 | ZW64: 1.1073139 | ZX64: 2.7777657 | ZY64: 1.7952975 | ZZ64: 1.3278237 | AAA64: 0.78320695 | AAB64: 0.80703023 | AAC64: 0.11651987 | AAD64: 1.990369 | AAE64: 1.9339856 | AAF64: 3.1582397 | AAG64: 1.9356343 | AAH64: 2.273735 | AAI64: 2.2165923 | AAJ64: 3.991336 | AAK64: 2.5180511 | AAL64: 2.1591314 | AAM64: 1.619677 | AAN64: 4.0437182 | AAO64: 2.3259408 | AAP64: 2.659505 | AAQ64: 3.786597 | AAR64: 2.3788692 | AAS64: 2.2439464 | AAT64: 1.7014192 | AAU64: 1.6283664 | AAV64: 1.5848374 | AAW64: 2.4479654 | AAX64: 1.4472688 | AAY64: 1.3929147 | AAZ64: 3.7418787 | ABA64: 1.7786614 | ABB64: -0.88743066 | ABC64: 2.1185001 | ABD64: 1.1768532 | ABE64: 1.3060664 | ABF64: 2.0496751 | ABG64: 2.9715513 | ABH64: 3.2818839 | ABI64: 0.15039653 | ABJ64: 1.341358 | ABK64: 0.069477726 | ABL64: 2.6819692 | ABM64: 0.35052461 | ABN64: 2.2420588 | ABO64: 2.1547552 | ABP64: 1.8282242 | ABQ64: -0.69025092 | ABR64: 0.65780269 | ABS64: 2.4073627 | ABT64: 0.92984378 | ABU64: 1.8921145 | ABV64: 2.8749064 | ABW64: 2.2833442 | ABX64: 0.42860765 | ABY64: 2.983649 | ABZ64: 2.5848082 | ACA64: -0.18257601 | ACB64: 2.1477267 | ACC64: 3.4190691 | ACD64: 0.31556064 | ACE64: 3.5300766 | ACF64: 1.7521375 | ACG64: 1.2768922 | ACH64: 3.5391085 | ACI64: 0.016126521 | ACJ64: 0.38076744 | ACK64: 2.729164 | ACL64: 3.3310002 | ACM64: 2.5123702 | ACN64: 1.8914937 | ACO64: 1.2175491 | ACP64: 2.2904384 | ACQ64: 1.7466299 | ACR64: 3.4078059 | ACS64: 1.9303882 | ACT64: 0.72352806 | ACU64: 2.1718232 | ACV64: -0.6598186 | ACW64: 0.28842922 | ACX64: 1.300988 | ACY64: 2.3376188 | ACZ64: 1.5845356 | ADA64: 1.7183743 | ADB64: -0.49213911 | ADC64: 2.9759433 | ADD64: 3.5424262 | ADE64: 1.5580992 | ADF64: -0.13942626 | ADG64: 2.6733474 | ADH64: -0.14162726 | ADI64: 1.3713756 | ADJ64: 0.74184926 | ADK64: 2.6868188 | ADL64: 1.4798167 | ADM64: 3.9405217 | ADN64: 2.5637654 | ADO64: 2.3027401 | ADP64: -0.1654472 | ADQ64: -0.35874793 | ADR64: 1.8494193 | ADS64: 2.4497529 | ADT64: 1.3355227 | ADU64: 1.4256345 | ADV64: 2.9375366 | ADW64: 1.9777042 | ADX64: 2.0016888 | ADY64: 2.2036434 | ADZ64: 0.8223157 | AEA64: 1.3484728 | AEB64: 3.6330359 | AEC64: 0.56337458 | AED64: 1.3916684 | AEE64: -0.19915608 | AEF64: 1.7458726 | AEG64: 1.6443417 | AEH64: 4.4320153 | AEI64: 1.4019391 | AEJ64: 2.1264136 | AEK64: 1.530587 | AEL64: -0.14679995 | AEM64: 2.3717641 | AEN64: 0.93435433 | AEO64: 1.3689168 | AEP64: 3.4627783 | AEQ64: 1.5989366 | AER64: 2.1548811 | AES64: 2.9613241 | AET64: 1.7914808 | AEU64: 0.91772665 | AEV64: 3.0478899 | AEW64: 0.95816186 | AEX64: 3.0932314 | AEY64: 3.365202 | AEZ64: 1.4477558 | AFA64: -0.22058943 | AFB64: 1.6357144 | AFC64: 1.7892473 | AFD64: 4.6482326 | AFE64: 3.2136577 | AFF64: 0.10563233 | AFG64: 4.417971 | AFH64: 2.1749321 | AFI64: 1.0305027 | AFJ64: 2.1472248 | AFK64: 2.3739028 | AFL64: 1.6056049 | AFM64: 3.241712 | AFN64: 1.5702559 | AFO64: 0.6246532 | AFP64: 1.4138633 | AFQ64: -1.2041431 | AFR64: 3.0575309 | AFS64: 2.3175672 | AFT64: 0.35983938 | AFU64: 1.1616136 | AFV64: 1.8280497 | AFW64: 1.2359886 | AFX64: 1.8949103 | AFY64: 2.7888539 | AFZ64: 2.8361941 | AGA64: 1.3042788 | AGB64: 4.4865425 | AGC64: 0.42173161 | AGD64: 0.33874005 | AGE64: 0.36265808 | AGF64: 1.7053615 | AGG64: 2.1200622 | AGH64: 2.2313833 | AGI64: 1.5705337 | AGJ64: 1.6410437 | AGK64: 1.4126164 | AGL64: 4.0147816 | AGM64: 2.4057634 | AGN64: 0.58613679 | AGO64: 0.95178931 | AGP64: 2.3601812 | AGQ64: 0.62798365 | AGR64: 3.8518246 | AGS64: 2.5290448 | AGT64: 1.2873692 | AGU64: 0.039258977 | AGV64: 0.9406572 | AGW64: 1.5124925 | AGX64: 1.0696253 | AGY64: 0.38772824 | AGZ64: 1.6149815 | AHA64: 1.3393916 | AHB64: 1.648367 | AHC64: 1.7273387 | AHD64: 2.2942314 | AHE64: 5.3417224 | AHF64: 3.7110564 | AHG64: 0.13179494 | AHH64: 1.4615558 | AHI64: 2.3824812 | AHJ64: 1.8792204 | AHK64: 2.1424377 | AHL64: 1.3255522 | AHM64: 0.61788845 | AHN64: 1.6684139 | AHO64: 2.1767846 | AHP64: 0.34921588 | AHQ64: 1.8591301 | AHR64: 0.58563775 | AHS64: 1.449213 | AHT64: 2.7379426 | AHU64: 2.0833961 | AHV64: 3.360169 | AHW64: -0.092495733 | AHX64: -0.20443773 | AHY64: 1.5266995 | AHZ64: 2.0801959 | AIA64: 3.8682242 | AIB64: 1.7576571 | AIC64: 3.7682256 | AID64: 0.98350332 | AIE64: 1.048346 | AIF64: 1.5200005 | AIG64: 2.480509 | AIH64: 1.9806713 | AII64: 0.87186202 | AIJ64: 3.2939608 | AIK64: 1.5977642 | AIL64: 2.0658245 | AIM64: 3.2131111 | AIN64: 1.9581497 | AIO64: 1.2960044 | AIP64: 3.2184218 | AIQ64: 1.0614826 | AIR64: 0.80936958 | AIS64: 1.3111789 | AIT64: 3.8756751 | AIU64: 0.59777874 | AIV64: 2.283725 | AIW64: 1.933906 | AIX64: 2.629347 | AIY64: 0.84009373 | AIZ64: 1.1311915 | AJA64: 1.6609595 | AJB64: 2.9984843 | AJC64: 0.04058912 | AJD64: 1.8523347 | AJE64: 2.3701644 | AJF64: 0.58366942 | AJG64: 1.8867748 | AJH64: 1.3072036 | AJI64: 2.4077997 | AJJ64: 2.0231075 | AJK64: 0.91290105 | AJL64: 2.0177473 | AJM64: 0.18681839 | AJN64: -0.42061363 | AJO64: 3.6994706 | AJP64: 2.2875487 | AJQ64: 1.3686655 | AJR64: 1.2839117 | AJS64: 3.0069656 | AJT64: 1.1786459 | AJU64: 2.601528 | AJV64: 1.0870046 | AJW64: 1.2803355 | AJX64: 1.3537602 | AJY64: 0.58550819 | AJZ64: 2.7213252 | AKA64: 1.8956876 | AKB64: 1.0568953 | AKC64: 2.6482009 | AKD64: 2.0413735 | AKE64: 2.1939989 | AKF64: 1.1979093 | AKG64: -0.28908354 | AKH64: 1.3101374 | AKI64: 1.26638 | AKJ64: 2.3183608 | AKK64: 0.68352094 | AKL64: 1.7822678 | AKM64: 2.9687222 | AKN64: 1.6353097 | AKO64: 2.8389085 | AKP64: 2.3488878 | AKQ64: 1.3765254 | AKR64: 1.4051002 | AKS64: 4.3161395 | AKT64: 3.1510814 | AKU64: 2.711622 | AKV64: 2.3232292 | AKW64: 2.0712444 | AKX64: 2.7801766 | AKY64: 1.2552876 | AKZ64: 2.4323794 | ALA64: 0.87916533 | ALB64: 1.8995955 | ALC64: 1.5800536 | ALD64: 0.65793941 | ALE64: 1.7921376 | ALF64: 4.0043898 | ALG64: 2.4534427 | ALH64: 1.2108532 | ALI64: 1.8770193 | ALJ64: 0.087335391 | ALK64: 4.2436479 | ALL64: 2.5708879 | ALM64: 1.7151822
A65: 33 | B65: =_xlfn.NORM.INV(RAND(),'Inflation Rates '!$B$401,'Inflation Rates '!$B$402) -> -0.31242409 | C65: 3.8198782 | D65: 2.1509466 | E65: -0.16009467 | F65: 1.5773907 | G65: 1.7852323 | H65: 0.87762973 | I65: 1.3695718 | J65: 2.020123 | K65: 2.3313341 | L65: 2.5802471 | M65: -0.82830645 | N65: 4.2757844 | O65: 1.4573713 | P65: 2.2647289 | Q65: 2.2044303 | R65: 2.108017 | S65: 0.4299405 | T65: 3.6167263 | U65: 2.3226439 | V65: 1.9342955 | W65: 2.8678753 | X65: -1.861641 | Y65: 3.2402916 | Z65: 0.81473121 | AA65: 1.3383027 | AB65: 0.7043238 | AC65: 0.8089642 | AD65: 3.1744972 | AE65: 0.81884808 | AF65: 0.55179313 | AG65: 3.556346 | AH65: 2.1500494 | AI65: 1.4499027 | AJ65: 2.4604504 | AK65: 3.0900456 | AL65: 2.574413 | AM65: 2.7830149 | AN65: 3.0596502 | AO65: -0.5751382 | AP65: 1.9580966 | AQ65: 4.349653 | AR65: 0.33357293 | AS65: 2.3556267 | AT65: 2.0762681 | AU65: 1.7649364 | AV65: 1.950133 | AW65: 1.9969321 | AX65: 2.3746431 | AY65: 0.89751472 | AZ65: 2.9937114 | BA65: 3.4898621 | BB65: 2.1337774 | BC65: 1.0781008 | BD65: 0.35951155 | BE65: 1.4539046 | BF65: 0.56803231 | BG65: 1.2734318 | BH65: 3.2247595 | BI65: 1.4314776 | BJ65: 1.7986526 | BK65: 1.182476 | BL65: 3.3622015 | BM65: 0.4666729 | BN65: 1.3778305 | BO65: -1.1681119 | BP65: 2.8117337 | BQ65: 1.5984728 | BR65: 0.42143561 | BS65: 2.2136593 | BT65: 1.5832103 | BU65: 0.34800037 | BV65: 2.6799453 | BW65: 0.77315696 | BX65: 0.7668396 | BY65: 1.966483 | BZ65: 2.7529231 | CA65: 0.91900967 | CB65: 1.2494443 | CC65: -0.33180621 | CD65: 1.3548997 | CE65: 1.4971205 | CF65: 0.48771385 | CG65: 2.977992 | CH65: 0.39797845 | CI65: -0.045038812 | CJ65: 2.5697956 | CK65: -0.70901034 | CL65: 2.7415023 | CM65: 0.28024874 | CN65: 2.2527152 | CO65: 1.544958 | CP65: 2.2567667 | CQ65: 0.6634714 | CR65: 1.362724 | CS65: 1.5050956 | CT65: 1.190448 | CU65: 0.2626465 | CV65: 2.9633814 | CW65: 2.5528474 | CX65: -0.78719861 | CY65: -1.3343211 | CZ65: 2.4167336 | DA65: 0.5254108 | DB65: 1.3029998 | DC65: 1.7248901 | DD65: 0.51806654 | DE65: 0.25768725 | DF65: 1.4146676 | DG65: 1.174568 | DH65: 1.2721123 | DI65: 0.5424288 | DJ65: 1.3664197 | DK65: 4.0296468 | DL65: -0.7234376 | DM65: 3.7470575 | DN65: 3.9789924 | DO65: 1.6766854 | DP65: 1.0115918 | DQ65: 2.039587 | DR65: 2.058969 | DS65: 0.1319819 | DT65: -0.41707518 | DU65: 1.4755227 | DV65: 3.8947228 | DW65: -0.13079913 | DX65: 2.0037825 | DY65: 2.5975772 | DZ65: 0.90453837 | EA65: 2.5546503 | EB65: 0.72495155 | EC65: 2.5008107 | ED65: 0.98067606 | EE65: 2.3642856 | EF65: 2.9220246 | EG65: 1.5382807 | EH65: 1.9559098 | EI65: 0.80655228 | EJ65: 0.5397708 | EK65: 2.007846 | EL65: 3.763561 | EM65: 1.1645368 | EN65: 0.59501328 | EO65: 2.7437411 | EP65: -0.66517292 | EQ65: 3.7338715 | ER65: -0.60333013 | ES65: 1.041792 | ET65: -0.11760465 | EU65: 0.76570511 | EV65: 2.3602896 | EW65: 0.95490794 | EX65: -1.0301851 | EY65: -0.080382031 | EZ65: 1.7504969 | FA65: 0.85048156 | FB65: 3.9178532 | FC65: -1.533457 | FD65: 2.3908611 | FE65: 1.2080173 | FF65: 3.5378811 | FG65: 2.369502 | FH65: 0.85123352 | FI65: 2.839348 | FJ65: 1.544341 | FK65: 3.5256443 | FL65: 2.168824 | FM65: 1.9144235 | FN65: 2.3408911 | FO65: 1.2830734 | FP65: -1.6413161 | FQ65: 1.959731 | FR65: 0.65626611 | FS65: -0.13249753 | FT65: 3.8070982 | FU65: 2.8867617 | FV65: 0.20272263 | FW65: 1.3734632 | FX65: 2.2955292 | FY65: 1.5360537 | FZ65: 1.0732609 | GA65: -0.022205793 | GB65: 2.1330637 | GC65: 3.7967315 | GD65: 1.6781729 | GE65: 1.6787962 | GF65: 0.82619835 | GG65: 1.6585786 | GH65: 1.0859572 | GI65: 1.1303444 | GJ65: 2.1587662 | GK65: 2.2434201 | GL65: 0.77739258 | GM65: 1.7452614 | GN65: 3.4237788 | GO65: 2.7560353 | GP65: 0.99375079 | GQ65: 0.3538795 | GR65: 1.7429899 | GS65: 2.8020283 | GT65: 2.4220147 | GU65: -0.35032433 | GV65: 4.3629051 | GW65: 2.2642497 | GX65: 1.143454 | GY65: 1.6433963 | GZ65: 4.9686989 | HA65: 1.8374292 | HB65: 0.32666662 | HC65: 2.4585614 | HD65: 0.73226218 | HE65: 1.6867947 | HF65: 2.8170845 | HG65: 3.4958155 | HH65: 1.4984922 | HI65: 2.6838811 | HJ65: 3.7645346 | HK65: 2.5332299 | HL65: 2.2441149 | HM65: 1.2421623 | HN65: 0.3534516 | HO65: 3.4404214 | HP65: 0.062182222 | HQ65: 2.3852864 | HR65: 3.2092046 | HS65: 0.76217769 | HT65: -0.30076032 | HU65: 1.415178 | HV65: 1.0117315 | HW65: 1.4862039 | HX65: 2.5360882 | HY65: 0.84827856 | HZ65: -0.85305871 | IA65: 2.3634987 | IB65: 1.6816373 | IC65: 2.0447679 | ID65: 3.0280626 | IE65: 3.6854546 | IF65: 1.6217846 | IG65: 2.9813412 | IH65: 3.0908868 | II65: 1.4727821 | IJ65: 1.5717948 | IK65: 2.6328061 | IL65: 1.441845 | IM65: 1.2955084 | IN65: 2.5204311 | IO65: 1.8453309 | IP65: -0.14095247 | IQ65: 1.1992677 | IR65: 2.05232 | IS65: 0.24247649 | IT65: 1.6146967 | IU65: 2.0815037 | IV65: 1.8304585 | IW65: 2.7561062 | IX65: 0.36217194 | IY65: 1.7896635 | IZ65: 0.66326348 | JA65: 1.1487664 | JB65: 1.4612649 | JC65: 1.6626072 | JD65: 2.4684037 | JE65: 0.81627574 | JF65: 2.1826519 | JG65: 1.0178605 | JH65: 3.9163766 | JI65: 0.53103601 | JJ65: -1.0640591 | JK65: 0.26060563 | JL65: 1.3479204 | JM65: 0.48089368 | JN65: 1.5501703 | JO65: 2.2110212 | JP65: 2.5625722 | JQ65: 0.6106666 | JR65: 2.2480363 | JS65: 2.8313344 | JT65: 1.7638458 | JU65: 0.24031003 | JV65: 2.344767 | JW65: 2.002117 | JX65: 3.0529029 | JY65: 0.063645467 | JZ65: 2.3782377 | KA65: 2.1296905 | KB65: -0.55281718 | KC65: 1.4237048 | KD65: 2.1714309 | KE65: 4.0635433 | KF65: 1.9981471 | KG65: 2.076536 | KH65: 1.7748482 | KI65: 0.069985568 | KJ65: 4.0324133 | KK65: -0.70368866 | KL65: 3.1266207 | KM65: 2.7364694 | KN65: 0.57404257 | KO65: 1.9874121 | KP65: 1.5102101 | KQ65: 0.63259233 | KR65: 4.2015309 | KS65: 2.3066468 | KT65: -0.034178508 | KU65: 1.2359953 | KV65: -0.12126252 | KW65: 1.1051989 | KX65: 1.5720938 | KY65: 1.8241551 | KZ65: 3.2771575 | LA65: 3.6242071 | LB65: 1.2235312 | LC65: 0.92016642 | LD65: 3.708474 | LE65: 2.1416464 | LF65: 2.5205239 | LG65: 1.8608589 | LH65: 1.9966104 | LI65: 1.8814753 | LJ65: 2.08408 | LK65: 1.8328289 | LL65: -0.35173625 | LM65: 1.0936182 | LN65: 0.41638176 | LO65: 1.479017 | LP65: 2.549514 | LQ65: -0.6673033 | LR65: 2.1633099 | LS65: 1.5789415 | LT65: 1.199704 | LU65: 1.7163181 | LV65: 2.3107315 | LW65: 1.5544936 | LX65: 0.08468108 | LY65: 3.6874047 | LZ65: 1.8835894 | MA65: -0.50084873 | MB65: -0.16502956 | MC65: 2.0324316 | MD65: -0.04155261 | ME65: 1.5077743 | MF65: 1.6534954 | MG65: 3.2244747 | MH65: 1.0643712 | MI65: 0.83915881 | MJ65: 0.6902535 | MK65: 0.75180541 | ML65: 2.4536178 | MM65: 4.0745531 | MN65: 2.7725542 | MO65: 1.5404989 | MP65: 1.9838044 | MQ65: 1.892413 | MR65: 0.97266572 | MS65: 1.9416272 | MT65: 2.9923116 | MU65: 2.1182307 | MV65: 0.81115172 | MW65: 1.6842151 | MX65: 3.2499645 | MY65: 1.7061517 | MZ65: -2.4142339 | NA65: 2.6614119 | NB65: 0.64632612 | NC65: 0.15525036 | ND65: 1.8213373 | NE65: 2.4380018 | NF65: 1.1761351 | NG65: 0.64454988 | NH65: 1.0390649 | NI65: 0.090921986 | NJ65: 0.78612426 | NK65: 1.5016395 | NL65: 0.88773602 | NM65: 3.5925662 | NN65: 1.6296962 | NO65: 1.517466 | NP65: 0.80831105 | NQ65: 2.3747501 | NR65: 1.6160794 | NS65: 1.0917041 | NT65: 2.6752427 | NU65: 2.8738152 | NV65: 1.067593 | NW65: 1.8052305 | NX65: 0.89666188 | NY65: 0.91129164 | NZ65: -0.71363197 | OA65: 1.4977398 | OB65: 2.8054054 | OC65: 1.0607308 | OD65: 1.9414959 | OE65: 1.1538927 | OF65: 1.0884417 | OG65: 1.922489 | OH65: 0.71713516 | OI65: 0.96832896 | OJ65: 1.03987 | OK65: 3.7476427 | OL65: 2.9512799 | OM65: 1.5739892 | ON65: 0.78722712 | OO65: 3.5509639 | OP65: 3.4474942 | OQ65: 4.092708 | OR65: 0.1024795 | OS65: 1.1939611 | OT65: 1.7231996 | OU65: 2.6109181 | OV65: 1.4081518 | OW65: 0.28143588 | OX65: -0.20814405 | OY65: 0.2991961 | OZ65: 2.7071343 | PA65: 2.2465887 | PB65: 1.5080399 | PC65: 0.91122306 | PD65: 1.0622508 | PE65: 0.98543806 | PF65: 2.2280208 | PG65: 0.14209853 | PH65: -0.60545594 | PI65: 0.82825514 | PJ65: 3.4300056 | PK65: 3.9426838 | PL65: 1.7316819 | PM65: 1.8245658 | PN65: 1.3747169 | PO65: 3.4244017 | PP65: 2.2502472 | PQ65: 2.0978684 | PR65: 2.5402609 | PS65: 2.1314737 | PT65: 3.2774121 | PU65: 1.4343039 | PV65: 2.0884186 | PW65: 0.944513 | PX65: 0.20003211 | PY65: 0.74497358 | PZ65: 2.4095019 | QA65: 2.2846647 | QB65: 2.6802607 | QC65: 1.1828515 | QD65: 1.2605 | QE65: 3.5142809 | QF65: 1.1483928 | QG65: 1.1555661 | QH65: 0.095016542 | QI65: 1.0670877 | QJ65: 1.9215354 | QK65: 1.0708783 | QL65: 0.43181334 | QM65: 0.32684901 | QN65: 1.5312895 | QO65: -0.11520665 | QP65: 0.23539435 | QQ65: 0.33284116 | QR65: 4.4582027 | QS65: 3.1551219 | QT65: 3.486691 | QU65: 0.75763554 | QV65: 2.0832753 | QW65: 1.2273766 | QX65: 3.3885345 | QY65: 2.6721523 | QZ65: 1.2468419 | RA65: 1.1800692 | RB65: 2.2620598 | RC65: -1.5092479 | RD65: 1.903675 | RE65: 1.881751 | RF65: 3.5004436 | RG65: 2.3388357 | RH65: 1.3184622 | RI65: -0.70369894 | RJ65: 1.4145005 | RK65: 2.9168181 | RL65: 4.1176406 | RM65: 1.6333041 | RN65: 3.3457281 | RO65: 1.8224725 | RP65: 1.2882477 | RQ65: 2.3265992 | RR65: 0.84745335 | RS65: 0.7778789 | RT65: 0.7812167 | RU65: 1.2604932 | RV65: 0.83371128 | RW65: 2.9488124 | RX65: 2.1563744 | RY65: 2.7149175 | RZ65: 2.280287 | SA65: 1.5435243 | SB65: 1.0164268 | SC65: 3.9758143 | SD65: 0.39513031 | SE65: 0.36268693 | SF65: 2.4780697 | SG65: 2.3486714 | SH65: 1.0662682 | SI65: 0.2845235 | SJ65: 0.3184235 | SK65: 2.0213929 | SL65: 2.0222475 | SM65: 0.4362529 | SN65: 0.52213696 | SO65: 0.20917376 | SP65: -0.49100181 | SQ65: 2.178991 | SR65: -0.47451054 | SS65: 0.71058989 | ST65: 1.6108821 | SU65: 0.76255832 | SV65: 2.7541039 | SW65: 0.73220482 | SX65: -0.068786002 | SY65: 0.42353688 | SZ65: 1.4196485 | TA65: 2.5296353 | TB65: 1.3719462 | TC65: 2.3927337 | TD65: 3.1104065 | TE65: 4.2115873 | TF65: 1.0790886 | TG65: 3.2676061 | TH65: 0.58168517 | TI65: 2.852155 | TJ65: 2.4209863 | TK65: 1.1392768 | TL65: 3.1228334 | TM65: 0.38006517 | TN65: 1.1610352 | TO65: 3.4743011 | TP65: 1.1269156 | TQ65: 3.8910453 | TR65: 2.1209756 | TS65: 5.980839 | TT65: 0.79530446 | TU65: 2.3223787 | TV65: 3.3698116 | TW65: 2.41155 | TX65: 1.3189492 | TY65: 2.9938301 | TZ65: 1.5403766 | UA65: 1.8831276 | UB65: 3.048758 | UC65: 1.9610908 | UD65: 0.61371912 | UE65: 0.63066652 | UF65: 1.02112 | UG65: 2.6565124 | UH65: 2.9975298 | UI65: -0.35208719 | UJ65: 3.94408 | UK65: 2.4303275 | UL65: 2.4186748 | UM65: -0.35540828 | UN65: 1.6802097 | UO65: 1.3231501 | UP65: 2.9110766 | UQ65: 2.7765739 | UR65: 1.3134314 | US65: 1.0945922 | UT65: 1.0636411 | UU65: -1.0755509 | UV65: 2.1082456 | UW65: 1.5358723 | UX65: 2.2854482 | UY65: 2.5345592 | UZ65: 3.5434825 | VA65: 2.2808064 | VB65: 2.6104754 | VC65: 0.301555 | VD65: 1.0854598 | VE65: 2.9493876 | VF65: 3.2916024 | VG65: 1.6664099 | VH65: 0.3361479 | VI65: 0.82462533 | VJ65: 2.2237105 | VK65: -0.48036332 | VL65: 2.7193619 | VM65: 0.60916908 | VN65: 2.3254671 | VO65: 1.2686378 | VP65: 3.4193472 | VQ65: 3.5541428 | VR65: 0.88194174 | VS65: 1.6186267 | VT65: 0.65450767 | VU65: 2.444463 | VV65: 1.5031128 | VW65: 3.4077328 | VX65: 1.1268834 | VY65: -0.72158581 | VZ65: 0.54523772 | WA65: 1.3166935 | WB65: 1.80665 | WC65: 1.6841212 | WD65: 2.7551476 | WE65: 2.5053178 | WF65: -0.19916746 | WG65: 2.1330826 | WH65: 1.1978017 | WI65: 0.57117323 | WJ65: 2.1101707 | WK65: 1.6342389 | WL65: 3.0738009 | WM65: 0.38495637 | WN65: 0.87976837 | WO65: -0.11955726 | WP65: 0.82916673 | WQ65: 3.3120201 | WR65: 1.1411585 | WS65: 2.6480396 | WT65: 4.3330249 | WU65: 2.6417681 | WV65: 4.6843082 | WW65: 2.4396391 | WX65: 1.0029386 | WY65: 3.4739346 | WZ65: 1.1991044 | XA65: -0.012790987 | XB65: 1.9599805 | XC65: 3.9706687 | XD65: -0.26044862 | XE65: 1.8416641 | XF65: 1.7612377 | XG65: 0.062311255 | XH65: 1.2848408 | XI65: 0.44449717 | XJ65: 0.53172904 | XK65: 2.9172387 | XL65: 2.0335335 | XM65: 1.2401674 | XN65: 0.70861562 | XO65: 2.0260207 | XP65: 2.5701588 | XQ65: 2.1120246 | XR65: 0.53453976 | XS65: 2.3800902 | XT65: 1.1957064 | XU65: 0.58717731 | XV65: 1.6741637 | XW65: 1.5769294 | XX65: 0.71186219 | XY65: 2.1893712 | XZ65: 0.32580976 | YA65: 1.3803533 | YB65: 1.8408038 | YC65: 3.3096879 | YD65: 1.3611824 | YE65: 1.2370926 | YF65: 2.1114385 | YG65: 0.038631645 | YH65: 0.62803246 | YI65: 1.9748913 | YJ65: 2.57067 | YK65: 0.10035525 | YL65: 1.6500475 | YM65: 1.8123514 | YN65: 3.049651 | YO65: 1.5131109 | YP65: -0.10763122 | YQ65: 2.3910168 | YR65: 2.2333296 | YS65: 1.0181001 | YT65: 0.39760236 | YU65: 3.1910888 | YV65: 1.8028983 | YW65: 0.74490077 | YX65: 2.6735849 | YY65: 0.383139 | YZ65: 1.9871559 | ZA65: 2.147498 | ZB65: 2.7540669 | ZC65: 3.8148575 | ZD65: 2.6855917 | ZE65: 3.6042175 | ZF65: 0.4193345 | ZG65: 2.3589449 | ZH65: 1.6399056 | ZI65: 0.90638461 | ZJ65: 0.68673754 | ZK65: 0.066461966 | ZL65: 1.8722867 | ZM65: 3.2736446 | ZN65: 1.7532702 | ZO65: 2.3374905 | ZP65: 2.5638423 | ZQ65: 0.65658118 | ZR65: 2.0919651 | ZS65: 1.3254085 | ZT65: 0.18612089 | ZU65: 3.2788359 | ZV65: 2.8122206 | ZW65: 0.46438937 | ZX65: 3.0503549 | ZY65: -0.1982515 | ZZ65: 2.6063935 | AAA65: 1.8435865 | AAB65: 3.0358255 | AAC65: 1.1156655 | AAD65: 2.4720471 | AAE65: 2.0546083 | AAF65: 2.799197 | AAG65: 2.1304632 | AAH65: 1.0304298 | AAI65: 3.9720782 | AAJ65: 0.902935 | AAK65: 2.9983665 | AAL65: 1.0051616 | AAM65: 1.9512187 | AAN65: 3.4687503 | AAO65: 2.0008771 | AAP65: 1.4952458 | AAQ65: 1.5540147 | AAR65: 2.3513881 | AAS65: 1.1532669 | AAT65: 0.35151272 | AAU65: 0.82659349 | AAV65: 3.3778465 | AAW65: 1.8109164 | AAX65: 0.86166398 | AAY65: 1.9027099 | AAZ65: 0.0021557972 | ABA65: 0.36004906 | ABB65: 1.5265779 | ABC65: 0.66804144 | ABD65: 1.4300716 | ABE65: 3.7910552 | ABF65: 3.3674094 | ABG65: 2.6926775 | ABH65: 3.0719929 | ABI65: 0.44672245 | ABJ65: 2.9155723 | ABK65: 1.2782659 | ABL65: 0.85081206 | ABM65: 2.2285125 | ABN65: 3.8528073 | ABO65: 0.13612623 | ABP65: 3.5464739 | ABQ65: 2.0929891 | ABR65: 2.0728227 | ABS65: -0.828639 | ABT65: 1.8597405 | ABU65: 1.3988532 | ABV65: 2.8830285 | ABW65: 1.3505804 | ABX65: 0.53103076 | ABY65: 1.3588128 | ABZ65: 4.1428097 | ACA65: 2.1344489 | ACB65: 1.3021859 | ACC65: 0.88180504 | ACD65: 1.6459873 | ACE65: 1.1570386 | ACF65: 2.7568206 | ACG65: 1.8093908 | ACH65: -0.83157628 | ACI65: 1.058847 | ACJ65: 2.1429605 | ACK65: 1.6007527 | ACL65: 2.0844033 | ACM65: 2.0935621 | ACN65: 2.4408854 | ACO65: 2.2311469 | ACP65: 0.38880058 | ACQ65: -0.14239349 | ACR65: 2.6259357 | ACS65: 0.14705247 | ACT65: 1.8396795 | ACU65: 1.3262415 | ACV65: 0.87190256 | ACW65: 1.0612186 | ACX65: 1.7493493 | ACY65: -0.14923681 | ACZ65: 2.4006975 | ADA65: 2.6950383 | ADB65: 0.80737323 | ADC65: 4.0432538 | ADD65: -0.52261309 | ADE65: 0.69457873 | ADF65: 2.583808 | ADG65: 0.049711288 | ADH65: 2.1094933 | ADI65: 0.049586218 | ADJ65: 1.8057704 | ADK65: 1.9671805 | ADL65: 1.2211513 | ADM65: 1.726169 | ADN65: 3.048529 | ADO65: 2.3012601 | ADP65: 1.5647698 | ADQ65: 2.5880492 | ADR65: 1.2504659 | ADS65: 1.4116782 | ADT65: 2.0974077 | ADU65: 0.6103907 | ADV65: 3.3580619 | ADW65: 3.1241528 | ADX65: 0.57774636 | ADY65: 2.3531129 | ADZ65: 0.47514051 | AEA65: 1.9037375 | AEB65: 1.9306868 | AEC65: -0.38471781 | AED65: 1.2193167 | AEE65: 2.3393159 | AEF65: 2.995328 | AEG65: 1.7680585 | AEH65: 2.5954233 | AEI65: 1.9916675 | AEJ65: 3.0899412 | AEK65: -1.3748913 | AEL65: 1.4451254 | AEM65: 1.0960089 | AEN65: 2.2864421 | AEO65: 2.6213044 | AEP65: 0.016821834 | AEQ65: 2.7140078 | AER65: 0.1061012 | AES65: 1.7163384 | AET65: 0.51270859 | AEU65: 3.9126594 | AEV65: 2.9496612 | AEW65: 1.9369051 | AEX65: 2.4185093 | AEY65: 1.0825691 | AEZ65: -0.74896573 | AFA65: 2.5949339 | AFB65: 2.2340156 | AFC65: 3.641292 | AFD65: 4.2102281 | AFE65: 1.6929996 | AFF65: 2.3216174 | AFG65: 2.3450505 | AFH65: -1.2170207 | AFI65: 1.1679623 | AFJ65: 2.7014056 | AFK65: 0.3158339 | AFL65: 0.44897393 | AFM65: 0.39401372 | AFN65: 1.6386873 | AFO65: 3.9895566 | AFP65: 1.6793349 | AFQ65: 2.5303756 | AFR65: 2.9419118 | AFS65: 2.6480795 | AFT65: 1.61239 | AFU65: 1.5155326 | AFV65: 2.6089073 | AFW65: 1.7914417 | AFX65: 2.4824961 | AFY65: 0.5710783 | AFZ65: 0.70295725 | AGA65: 1.7228976 | AGB65: 1.4214025 | AGC65: 2.0952739 | AGD65: 1.759337 | AGE65: 0.52170498 | AGF65: 2.0934076 | AGG65: 1.5597325 | AGH65: -0.45282775 | AGI65: 2.3992441 | AGJ65: 2.7983149 | AGK65: 1.7201018 | AGL65: -0.84069111 | AGM65: 1.9326929 | AGN65: 1.6245325 | AGO65: 1.6361878 | AGP65: -0.35873483 | AGQ65: 2.3685717 | AGR65: 2.5276495 | AGS65: 2.7109322 | AGT65: 0.68742164 | AGU65: 2.2577101 | AGV65: 2.6063557 | AGW65: 2.9280923 | AGX65: 0.8751822 | AGY65: 1.3926291 | AGZ65: 2.2866566 | AHA65: 0.13191327 | AHB65: 2.0749557 | AHC65: 2.7330647 | AHD65: 4.2290402 | AHE65: 0.83112286 | AHF65: 0.88658051 | AHG65: 1.656985 | AHH65: 1.8157881 | AHI65: 2.0198992 | AHJ65: 1.6273915 | AHK65: 0.48346438 | AHL65: 0.92896961 | AHM65: 1.5967176 | AHN65: 2.8073452 | AHO65: 2.5932716 | AHP65: 0.20152671 | AHQ65: 1.9761211 | AHR65: 0.40410846 | AHS65: 3.6054561 | AHT65: 2.0989446 | AHU65: 0.33480077 | AHV65: 2.8919254 | AHW65: 3.4129925 | AHX65: 2.1180588 | AHY65: 2.1346706 | AHZ65: 2.5169169 | AIA65: 2.1332005 | AIB65: 1.7049277 | AIC65: 1.7699265 | AID65: 1.4177117 | AIE65: 2.0225114 | AIF65: 0.49644977 | AIG65: 4.2305896 | AIH65: 1.3588719 | AII65: 3.593849 | AIJ65: 3.1328597 | AIK65: 1.0148344 | AIL65: 1.7387976 | AIM65: 1.6686247 | AIN65: 2.2077925 | AIO65: 1.8775238 | AIP65: 2.4724275 | AIQ65: 2.8188879 | AIR65: 2.3939919 | AIS65: 1.035155 | AIT65: 2.5762793 | AIU65: 1.2253472 | AIV65: 0.51692497 | AIW65: 2.7751926 | AIX65: 1.4059022 | AIY65: 2.830811 | AIZ65: 1.6783673 | AJA65: 0.81105704 | AJB65: 2.2231639 | AJC65: 2.9266714 | AJD65: 0.28820213 | AJE65: 1.2704332 | AJF65: 3.6085184 | AJG65: 3.5525289 | AJH65: 1.2197997 | AJI65: 4.1438409 | AJJ65: 3.5247061 | AJK65: 1.3398681 | AJL65: 1.8965421 | AJM65: 0.87567273 | AJN65: 2.1326727 | AJO65: 3.3543133 | AJP65: 1.6643295 | AJQ65: 0.44554569 | AJR65: 1.4228179 | AJS65: 2.1191065 | AJT65: 0.47102071 | AJU65: 0.54400703 | AJV65: 0.91829711 | AJW65: 3.4924236 | AJX65: 0.82670057 | AJY65: 1.0886572 | AJZ65: 1.1643133 | AKA65: 3.4944052 | AKB65: -0.43892586 | AKC65: 1.1744433 | AKD65: 0.15876679 | AKE65: 0.7208107 | AKF65: 0.90521683 | AKG65: 2.7340384 | AKH65: 0.99397279 | AKI65: 3.2946034 | AKJ65: 2.3401245 | AKK65: 0.19129294 | AKL65: 0.41422881 | AKM65: 0.33209019 | AKN65: 0.5858712 | AKO65: 0.90812797 | AKP65: 0.28124145 | AKQ65: 1.1738175 | AKR65: 1.7217512 | AKS65: 2.5872805 | AKT65: 0.060699587 | AKU65: 1.1633858 | AKV65: 1.5939405 | AKW65: -0.60804907 | AKX65: 2.1264851 | AKY65: 3.1262193 | AKZ65: 2.0595686 | ALA65: 1.9707324 | ALB65: 0.81655314 | ALC65: 3.8046469 | ALD65: 2.0666516 | ALE65: -0.5875131 | ALF65: 1.7104613 | ALG65: 2.1045655 | ALH65: 0.21612001 | ALI65: 1.6945545 | ALJ65: 4.038536 | ALK65: 1.2171722 | ALL65: 2.8173693 | ALM65: -1.4670987
A66: 34 | B66: =_xlfn.NORM.INV(RAND(),'Inflation Rates '!$B$401,'Inflation Rates '!$B$402) -> 0.41526539 | C66: 3.2828659 | D66: 1.43932 | E66: 1.2316056 | F66: 3.4469135 | G66: 0.52584567 | H66: 3.8211566 | I66: 0.47127242 | J66: 1.9473405 | K66: -0.052824623 | L66: 0.63942899 | M66: 3.1524942 | N66: 1.081366 | O66: 1.5407431 | P66: 2.3595142 | Q66: 0.40970169 | R66: 1.5225809 | S66: 0.099272717 | T66: 2.9224054 | U66: 1.3702133 | V66: 2.6265619 | W66: 1.9960229 | X66: 1.5746906 | Y66: 1.5917641 | Z66: 3.3702665 | AA66: 2.4494129 | AB66: 2.9994797 | AC66: 1.9562787 | AD66: 1.0602679 | AE66: 0.16267593 | AF66: 0.90186253 | AG66: 2.5163509 | AH66: 0.37554035 | AI66: 3.2151278 | AJ66: -0.28844381 | AK66: 1.5365081 | AL66: -0.69954656 | AM66: 1.3710869 | AN66: 1.7383898 | AO66: 1.9426678 | AP66: 1.2266028 | AQ66: 1.8482019 | AR66: 3.1385575 | AS66: -2.1625959 | AT66: 2.8705291 | AU66: 0.96508558 | AV66: 0.47282713 | AW66: -0.34191456 | AX66: 5.8625288 | AY66: 1.7507636 | AZ66: 2.9266917 | BA66: 1.3358266 | BB66: 1.7593343 | BC66: 1.7383033 | BD66: 2.1854976 | BE66: 2.0869239 | BF66: 1.7323995 | BG66: 3.3034626 | BH66: 1.9801517 | BI66: 0.13454149 | BJ66: 2.5475098 | BK66: 2.1617969 | BL66: 1.7943837 | BM66: 0.93386924 | BN66: 1.6538077 | BO66: 1.2408377 | BP66: 2.0271131 | BQ66: 0.51467383 | BR66: 0.18336015 | BS66: 1.7560553 | BT66: 1.0193362 | BU66: 1.9277564 | BV66: 1.9750596 | BW66: 1.5348106 | BX66: 3.3178494 | BY66: -0.51199552 | BZ66: 2.0750004 | CA66: 0.79248771 | CB66: 2.0941275 | CC66: 2.7787416 | CD66: 1.6904074 | CE66: 3.3001791 | CF66: 1.2100782 | CG66: 0.011663541 | CH66: 1.9618479 | CI66: 1.7878789 | CJ66: 1.9249982 | CK66: 0.15827892 | CL66: 0.1847791 | CM66: 2.819773 | CN66: 3.278415 | CO66: -0.14476931 | CP66: 0.73625446 | CQ66: 2.1268006 | CR66: 0.56180328 | CS66: 1.1905821 | CT66: 2.2696689 | CU66: 0.26318037 | CV66: 3.1991358 | CW66: 1.1791501 | CX66: 0.75225919 | CY66: -0.88352404 | CZ66: 2.5881513 | DA66: 1.4697971 | DB66: 1.7745246 | DC66: 1.9843165 | DD66: 1.6838546 | DE66: 1.5563512 | DF66: 2.056204 | DG66: 0.30109339 | DH66: 1.2668058 | DI66: 2.2689238 | DJ66: 3.3658966 | DK66: -0.56615344 | DL66: 0.17791237 | DM66: 0.11822195 | DN66: 2.0252933 | DO66: 1.9733907 | DP66: 1.9236593 | DQ66: 3.2542966 | DR66: 1.0902394 | DS66: -0.58713203 | DT66: 2.9796257 | DU66: 0.21857441 | DV66: 2.6240466 | DW66: 0.64554273 | DX66: 3.1620332 | DY66: 0.73781056 | DZ66: 2.2493718 | EA66: 0.3678208 | EB66: -2.0350505 | EC66: -0.18408967 | ED66: 2.5450982 | EE66: 3.4523711 | EF66: 2.0250527 | EG66: -0.69955883 | EH66: 2.7571327 | EI66: 0.86337859 | EJ66: 2.9644096 | EK66: -3.1797684 | EL66: 1.0132195 | EM66: 1.2673235 | EN66: 0.74963515 | EO66: 0.25597874 | EP66: 1.3742417 | EQ66: 1.0200471 | ER66: 2.0824785 | ES66: 2.0079225 | ET66: 1.3224677 | EU66: 1.0962628 | EV66: -0.22002339 | EW66: 3.1635658 | EX66: 3.5505045 | EY66: 3.4043037 | EZ66: 1.132688 | FA66: 1.0800537 | FB66: 1.0011534 | FC66: 2.9679026 | FD66: 3.21937 | FE66: 2.6005462 | FF66: 0.387315 | FG66: 1.053536 | FH66: 2.4543027 | FI66: 1.1372507 | FJ66: 0.20692246 | FK66: 0.35062103 | FL66: 0.84764152 | FM66: 0.18010473 | FN66: 2.5640879 | FO66: 1.8952479 | FP66: 1.0082731 | FQ66: 1.9319169 | FR66: 3.2028853 | FS66: 0.94926796 | FT66: 1.1463401 | FU66: 1.8399231 | FV66: 1.086607 | FW66: 3.4534743 | FX66: 2.8454317 | FY66: -0.050960113 | FZ66: 1.7435089 | GA66: 2.0275898 | GB66: 3.7440606 | GC66: 2.9648415 | GD66: 2.7331361 | GE66: 0.46352844 | GF66: 0.18464094 | GG66: 0.19635315 | GH66: 3.3674782 | GI66: 3.2126316 | GJ66: 0.95515345 | GK66: 1.5572434 | GL66: 2.5115209 | GM66: 3.0795318 | GN66: 1.0884367 | GO66: 0.89548223 | GP66: 2.265249 | GQ66: 2.0305849 | GR66: 1.8661441 | GS66: 1.9859451 | GT66: 1.3864732 | GU66: 1.9318544 | GV66: 2.5082297 | GW66: 1.52721 | GX66: 3.0670684 | GY66: 2.9850817 | GZ66: 0.17091428 | HA66: 1.6902138 | HB66: 0.72476127 | HC66: 3.7881427 | HD66: -0.26307515 | HE66: 1.2881136 | HF66: 0.9547903 | HG66: 0.19204319 | HH66: 1.4553994 | HI66: 4.4293942 | HJ66: 1.2735957 | HK66: 3.3527028 | HL66: -0.40289975 | HM66: 2.2510175 | HN66: 1.6603757 | HO66: 2.8068627 | HP66: 0.66875446 | HQ66: 2.39238 | HR66: 0.3743551 | HS66: 2.2687519 | HT66: 2.207908 | HU66: 2.5522503 | HV66: 1.036147 | HW66: 0.8560527 | HX66: 0.83955812 | HY66: 2.6630187 | HZ66: 1.8430745 | IA66: -2.0053328 | IB66: 1.4967954 | IC66: 3.2072417 | ID66: 2.3988867 | IE66: 0.87125679 | IF66: 0.79564653 | IG66: 0.53761642 | IH66: 1.4772649 | II66: 2.3118074 | IJ66: 2.7459818 | IK66: 3.1045228 | IL66: 1.3138881 | IM66: 3.5377439 | IN66: 0.58338777 | IO66: 3.6995287 | IP66: 1.7006219 | IQ66: 2.4080787 | IR66: 0.37219077 | IS66: 4.5434421 | IT66: 1.5539301 | IU66: 2.8146673 | IV66: 0.48766636 | IW66: 0.93526444 | IX66: 1.8094108 | IY66: 3.303887 | IZ66: 2.4460073 | JA66: 3.6511311 | JB66: 1.7631595 | JC66: 2.9202154 | JD66: 2.1195749 | JE66: 3.0811072 | JF66: 3.9587804 | JG66: 3.5837184 | JH66: 3.7690802 | JI66: 1.721282 | JJ66: 1.4957223 | JK66: 2.9042867 | JL66: 4.3907234 | JM66: 1.9009179 | JN66: 1.8097901 | JO66: 1.1408095 | JP66: 2.0266522 | JQ66: 0.65789242 | JR66: 2.5643912 | JS66: 2.5713722 | JT66: 1.0914608 | JU66: 3.1668054 | JV66: 2.6155373 | JW66: 2.0945449 | JX66: 1.3039086 | JY66: 1.3855051 | JZ66: 3.5911034 | KA66: 2.0637971 | KB66: 1.8455497 | KC66: 1.0054241 | KD66: 1.9577744 | KE66: 0.30667313 | KF66: 3.0377666 | KG66: 2.5680614 | KH66: 2.0024676 | KI66: 2.6827546 | KJ66: 3.7992955 | KK66: 3.782758 | KL66: 3.0593885 | KM66: 1.7501312 | KN66: 0.96567544 | KO66: 1.5943643 | KP66: 0.95273415 | KQ66: 0.82110024 | KR66: 1.4162697 | KS66: 0.72337773 | KT66: 2.7626449 | KU66: 2.0644062 | KV66: 2.198517 | KW66: 1.8641638 | KX66: 1.8944809 | KY66: 1.4269679 | KZ66: 2.1130241 | LA66: 1.7465052 | LB66: 0.99080756 | LC66: 1.5869523 | LD66: 0.95584516 | LE66: 1.8765922 | LF66: 0.24929964 | LG66: 2.1872337 | LH66: 2.8149385 | LI66: 0.15913244 | LJ66: 3.0006326 | LK66: 2.0733092 | LL66: 1.5542983 | LM66: 3.6513582 | LN66: 0.17949961 | LO66: 2.1408935 | LP66: 1.8518483 | LQ66: -0.44138302 | LR66: 0.5654045 | LS66: 2.4513954 | LT66: 0.24144139 | LU66: -0.61507275 | LV66: 2.6180267 | LW66: 3.2066749 | LX66: 2.0801052 | LY66: 4.2012722 | LZ66: 1.3725256 | MA66: 2.7369724 | MB66: 3.4773663 | MC66: 3.1455967 | MD66: 2.9143884 | ME66: 2.4033128 | MF66: 2.423312 | MG66: 1.4816061 | MH66: 0.25081156 | MI66: 0.76000472 | MJ66: 4.1936668 | MK66: 3.5638823 | ML66: 3.1203124 | MM66: 4.4900493 | MN66: 1.1627968 | MO66: 1.0474298 | MP66: 2.866253 | MQ66: 0.31703984 | MR66: 1.0236879 | MS66: 1.323993 | MT66: 3.1635253 | MU66: -0.64861495 | MV66: 0.29236656 | MW66: 1.5642301 | MX66: 1.2401543 | MY66: 1.5766598 | MZ66: 2.2529143 | NA66: 5.0666374 | NB66: 1.6312673 | NC66: 2.2129547 | ND66: 3.1781571 | NE66: 1.761263 | NF66: 0.90439076 | NG66: 1.0426065 | NH66: 1.6904738 | NI66: 1.4348608 | NJ66: 1.3307455 | NK66: 3.8321751 | NL66: 1.6390983 | NM66: 3.7297008 | NN66: 1.1126597 | NO66: 2.2975193 | NP66: 0.47794596 | NQ66: 2.6890427 | NR66: 3.0070984 | NS66: 2.9551812 | NT66: 0.30272981 | NU66: 0.85641708 | NV66: 0.063352453 | NW66: 2.8759644 | NX66: 3.7408449 | NY66: 0.99617885 | NZ66: 1.9343632 | OA66: 2.8347182 | OB66: 0.87365108 | OC66: 0.75813753 | OD66: 1.4767595 | OE66: 2.5336313 | OF66: 2.5017185 | OG66: 1.7921982 | OH66: 2.4210743 | OI66: 1.6402606 | OJ66: 2.147453 | OK66: 1.8660186 | OL66: 0.42528366 | OM66: 2.3156908 | ON66: 3.3323596 | OO66: 0.66545578 | OP66: 1.2930552 | OQ66: 2.773381 | OR66: 2.7673927 | OS66: 2.3468713 | OT66: 0.87162775 | OU66: 1.2012743 | OV66: 0.72597931 | OW66: 4.161241 | OX66: 0.53798835 | OY66: 1.3483671 | OZ66: 1.4776585 | PA66: 1.342901 | PB66: 5.0889335 | PC66: 3.1617623 | PD66: 2.606067 | PE66: 0.58373604 | PF66: -0.69659295 | PG66: 0.41667349 | PH66: 1.3132354 | PI66: 0.77782469 | PJ66: -1.5801175 | PK66: -0.44499914 | PL66: 1.2643016 | PM66: -0.82284796 | PN66: -0.49793711 | PO66: 0.70055311 | PP66: -0.12782651 | PQ66: 2.4559968 | PR66: 0.94758143 | PS66: 1.2490258 | PT66: 2.7016403 | PU66: 1.9406357 | PV66: 2.0296183 | PW66: 1.3468453 | PX66: -0.53296329 | PY66: 0.6323373 | PZ66: 4.0255152 | QA66: 1.5920968 | QB66: 1.1078065 | QC66: -0.24004477 | QD66: 2.1430704 | QE66: 2.9928832 | QF66: 2.2835878 | QG66: -0.64603215 | QH66: 4.3309643 | QI66: 2.2481025 | QJ66: 2.7521054 | QK66: 2.5304127 | QL66: 2.095989 | QM66: 2.5652184 | QN66: 0.77600694 | QO66: -0.11604571 | QP66: 1.2634949 | QQ66: 2.6725782 | QR66: 0.13432962 | QS66: 3.0626234 | QT66: 1.3226967 | QU66: 3.0481925 | QV66: 0.76295438 | QW66: -0.71793921 | QX66: 2.762886 | QY66: 0.91995376 | QZ66: 0.92051673 | RA66: 1.4289071 | RB66: 1.0771069 | RC66: 1.5904513 | RD66: 2.2604474 | RE66: -0.54414047 | RF66: 2.2719384 | RG66: 0.95105435 | RH66: 2.5440965 | RI66: 1.746582 | RJ66: 0.92782458 | RK66: 2.2281143 | RL66: 0.13580084 | RM66: 1.2145836 | RN66: 0.54584667 | RO66: 1.7110544 | RP66: 1.332466 | RQ66: 0.53859321 | RR66: 1.5330461 | RS66: 2.0978238 | RT66: 0.73478756 | RU66: -0.00371404 | RV66: 2.0112379 | RW66: 2.3054371 | RX66: 1.8537839 | RY66: 0.28537902 | RZ66: 2.6589301 | SA66: 3.1381517 | SB66: 2.9245818 | SC66: 2.4997534 | SD66: 2.5760172 | SE66: 2.8763351 | SF66: 1.5362196 | SG66: 0.11681317 | SH66: 1.2825742 | SI66: 0.64454108 | SJ66: 3.6798966 | SK66: 2.9816793 | SL66: 1.298192 | SM66: 2.5087015 | SN66: 2.0293593 | SO66: 2.0406741 | SP66: 2.4195519 | SQ66: -0.36133206 | SR66: -0.25040107 | SS66: 3.5931636 | ST66: 3.8180138 | SU66: 0.31239051 | SV66: 1.1488032 | SW66: 2.4647155 | SX66: 0.82931404 | SY66: 1.6444099 | SZ66: 1.4389001 | TA66: 3.1376258 | TB66: 2.8645975 | TC66: -0.3356545 | TD66: 1.8449168 | TE66: 4.3630056 | TF66: 1.9041189 | TG66: 2.0404863 | TH66: 0.48988463 | TI66: 2.015282 | TJ66: 3.3323513 | TK66: 1.49897 | TL66: 3.5638209 | TM66: 0.29468614 | TN66: 1.5926677 | TO66: 1.8781109 | TP66: 2.0179607 | TQ66: 0.92287096 | TR66: 1.1093003 | TS66: 2.751677 | TT66: 3.24161 | TU66: -0.15371571 | TV66: -0.377926 | TW66: -0.45083454 | TX66: 4.5085787 | TY66: 0.2087179 | TZ66: 0.72906359 | UA66: 0.58504464 | UB66: 1.9988841 | UC66: -0.62984396 | UD66: 1.1597048 | UE66: 2.7454279 | UF66: 1.819072 | UG66: 1.0040623 | UH66: -1.923428 | UI66: 1.4190658 | UJ66: 0.91858976 | UK66: 0.70258123 | UL66: 2.2842733 | UM66: 0.58929838 | UN66: 2.0058524 | UO66: 1.9563328 | UP66: 2.1577134 | UQ66: 2.1253055 | UR66: 0.50858061 | US66: 4.073544 | UT66: 0.64034539 | UU66: 0.61915323 | UV66: 1.8154414 | UW66: 2.8945264 | UX66: 0.76867642 | UY66: 0.040065534 | UZ66: 3.0298924 | VA66: 0.67826222 | VB66: 1.8586225 | VC66: -0.37282908 | VD66: 0.45176765 | VE66: 1.4635898 | VF66: -0.38103717 | VG66: 2.74673 | VH66: 1.8284491 | VI66: 0.49957963 | VJ66: 3.9624281 | VK66: 1.0897159 | VL66: 2.529169 | VM66: 1.472378 | VN66: 1.7476419 | VO66: 0.96547511 | VP66: 2.2801097 | VQ66: 0.81815317 | VR66: 3.0843819 | VS66: 3.002913 | VT66: 1.5258492 | VU66: 1.0580991 | VV66: 1.9881848 | VW66: 0.41355367 | VX66: 1.3606313 | VY66: 2.4963085 | VZ66: 2.2790158 | WA66: 2.1366517 | WB66: 0.95150007 | WC66: 2.9888647 | WD66: 3.0495807 | WE66: 2.4234182 | WF66: 2.4727141 | WG66: 3.3090879 | WH66: 2.7398621 | WI66: -0.17055675 | WJ66: -1.8451156 | WK66: 1.5110495 | WL66: 2.6886953 | WM66: 1.4992155 | WN66: -0.65720359 | WO66: 1.1342862 | WP66: 1.5945455 | WQ66: -0.11995051 | WR66: 2.9213234 | WS66: 1.3333846 | WT66: 3.0962717 | WU66: 0.59692011 | WV66: 2.466985 | WW66: 3.9490179 | WX66: 0.82821245 | WY66: 1.8482496 | WZ66: 1.13949 | XA66: 1.3973032 | XB66: 1.2108766 | XC66: 0.16473714 | XD66: 1.563131 | XE66: 1.4321121 | XF66: 1.9840216 | XG66: -0.24189942 | XH66: 2.2427603 | XI66: 3.0014812 | XJ66: 0.33394095 | XK66: 0.89443189 | XL66: 0.22726345 | XM66: 0.52443364 | XN66: 3.0038362 | XO66: 1.5352162 | XP66: 0.28484988 | XQ66: 1.7963834 | XR66: 0.44653785 | XS66: 0.53925944 | XT66: 3.89778 | XU66: 2.8080749 | XV66: 0.91952423 | XW66: 1.6106862 | XX66: 0.8354937 | XY66: 1.3213631 | XZ66: 2.5695544 | YA66: 1.522801 | YB66: 2.4903171 | YC66: 3.208998 | YD66: 0.33045515 | YE66: 1.2607679 | YF66: 0.94709046 | YG66: 2.6941203 | YH66: 0.34193783 | YI66: 0.97295663 | YJ66: 2.5526695 | YK66: 0.4675368 | YL66: 0.39963469 | YM66: 1.2229461 | YN66: 1.9460256 | YO66: 4.8576156 | YP66: 1.9575269 | YQ66: 3.1432909 | YR66: 1.5954069 | YS66: 0.52529124 | YT66: 1.9737557 | YU66: 3.3820706 | YV66: 1.0603499 | YW66: 4.5317192 | YX66: 2.4381314 | YY66: 1.938619 | YZ66: 1.6351107 | ZA66: 0.61437199 | ZB66: 1.3883932 | ZC66: -0.18219621 | ZD66: 0.074326329 | ZE66: 0.58330306 | ZF66: 0.7340683 | ZG66: 2.5747834 | ZH66: 2.5373702 | ZI66: 1.2887292 | ZJ66: 2.2710719 | ZK66: 1.2851524 | ZL66: 3.0201334 | ZM66: 0.66063061 | ZN66: 2.711938 | ZO66: 0.8491951 | ZP66: 2.9238776 | ZQ66: 5.0372391 | ZR66: 1.7922947 | ZS66: 1.2582156 | ZT66: 1.5015092 | ZU66: 2.358126 | ZV66: 2.4014393 | ZW66: 2.6675625 | ZX66: 3.3197424 | ZY66: 1.8864106 | ZZ66: 2.3394615 | AAA66: 0.8306826 | AAB66: 1.3736143 | AAC66: 0.99629926 | AAD66: 1.8144323 | AAE66: 2.6563378 | AAF66: 0.68714224 | AAG66: 2.388618 | AAH66: 1.0784637 | AAI66: 2.5783569 | AAJ66: -0.26199097 | AAK66: 3.1344293 | AAL66: 3.0376157 | AAM66: 2.8973262 | AAN66: 2.6865056 | AAO66: 0.42571107 | AAP66: 2.4626448 | AAQ66: 0.1644485 | AAR66: 1.1975936 | AAS66: 1.6948069 | AAT66: 2.8580999 | AAU66: -0.50809011 | AAV66: 0.48028662 | AAW66: 2.1725972 | AAX66: 0.76088583 | AAY66: 3.3435436 | AAZ66: -1.789041 | ABA66: 2.4917011 | ABB66: 1.1344133 | ABC66: 1.5751057 | ABD66: 3.3316768 | ABE66: 0.8002676 | ABF66: 2.7222179 | ABG66: 1.1592536 | ABH66: 1.9921821 | ABI66: 1.5672057 | ABJ66: -0.0010376439 | ABK66: 4.1945158 | ABL66: 3.3367106 | ABM66: 1.1822605 | ABN66: -2.3049218 | ABO66: 2.498714 | ABP66: 0.66509029 | ABQ66: 0.88493865 | ABR66: 0.55583991 | ABS66: 1.4370867 | ABT66: 2.3274141 | ABU66: 1.9422916 | ABV66: 0.56899409 | ABW66: 3.0610812 | ABX66: 3.0487682 | ABY66: 2.218266 | ABZ66: 2.0673018 | ACA66: 1.9817805 | ACB66: 2.7797218 | ACC66: 2.6230371 | ACD66: 1.4336121 | ACE66: 1.5998619 | ACF66: -1.1302538 | ACG66: 0.20713503 | ACH66: 2.7972155 | ACI66: 2.3444612 | ACJ66: 1.1352659 | ACK66: 1.4197188 | ACL66: 0.4320637 | ACM66: 0.30473211 | ACN66: 2.3338704 | ACO66: 1.3857885 | ACP66: 1.7886389 | ACQ66: 1.2925794 | ACR66: 2.1684219 | ACS66: 0.99644063 | ACT66: 3.2812845 | ACU66: 1.4971713 | ACV66: 1.872728 | ACW66: 5.90195 | ACX66: 1.8894776 | ACY66: 0.84728653 | ACZ66: 2.6783357 | ADA66: 4.5598451 | ADB66: 1.7899454 | ADC66: 0.42409835 | ADD66: 2.1311469 | ADE66: 3.2534716 | ADF66: 0.018568579 | ADG66: -0.45464148 | ADH66: 1.5978627 | ADI66: 2.9532508 | ADJ66: 1.2425812 | ADK66: 2.2976417 | ADL66: 2.8352272 | ADM66: 1.0290247 | ADN66: 1.9872128 | ADO66: 2.3930145 | ADP66: 1.2922646 | ADQ66: 2.493888 | ADR66: 2.7033277 | ADS66: -0.21431175 | ADT66: 2.5795464 | ADU66: 2.9326213 | ADV66: 1.3714326 | ADW66: 2.3675916 | ADX66: 0.39824388 | ADY66: 4.3840268 | ADZ66: 0.33286948 | AEA66: 0.59535343 | AEB66: 2.5267447 | AEC66: 0.13520762 | AED66: 2.6139394 | AEE66: 1.7614254 | AEF66: 0.93624666 | AEG66: 3.0114712 | AEH66: 0.32440937 | AEI66: 0.19541413 | AEJ66: 1.2841105 | AEK66: -1.5654853 | AEL66: 3.767638 | AEM66: 3.4013655 | AEN66: 2.7578988 | AEO66: 3.6684063 | AEP66: 1.8292598 | AEQ66: 2.3547215 | AER66: 5.8759339 | AES66: 3.1340063 | AET66: 3.3810958 | AEU66: 0.75448316 | AEV66: 2.5306142 | AEW66: 2.0336024 | AEX66: 3.3502772 | AEY66: 3.5731318 | AEZ66: 0.82527884 | AFA66: -0.22508771 | AFB66: 3.2683994 | AFC66: 4.7543827 | AFD66: 0.69275592 | AFE66: 2.3875527 | AFF66: 3.2208379 | AFG66: 2.3517666 | AFH66: 0.19267906 | AFI66: 0.86173895 | AFJ66: 1.2047973 | AFK66: 2.8374594 | AFL66: 1.3675087 | AFM66: 0.31920844 | AFN66: 2.0141825 | AFO66: 1.0210487 | AFP66: 1.0898363 | AFQ66: 1.987098 | AFR66: 3.4166972 | AFS66: 2.3474789 | AFT66: 4.1029621 | AFU66: 3.3119766 | AFV66: 1.9120413 | AFW66: 3.987898 | AFX66: 1.2628781 | AFY66: 1.3588328 | AFZ66: 2.8715778 | AGA66: 1.7570409 | AGB66: 1.2776855 | AGC66: 0.99122252 | AGD66: 1.2165257 | AGE66: 4.4005248 | AGF66: 1.4562675 | AGG66: 1.8789492 | AGH66: 3.0647435 | AGI66: 0.45185411 | AGJ66: 3.2557146 | AGK66: 2.6774862 | AGL66: 2.3762087 | AGM66: 3.1810411 | AGN66: 1.3381821 | AGO66: 2.6682546 | AGP66: 1.4564407 | AGQ66: 1.3016372 | AGR66: 1.4878994 | AGS66: 1.9725939 | AGT66: 0.2756839 | AGU66: 1.0400379 | AGV66: 0.75172114 | AGW66: 1.5146444 | AGX66: -0.41023284 | AGY66: 2.2124413 | AGZ66: -0.74993029 | AHA66: -1.2090914 | AHB66: -1.045975 | AHC66: 1.2472901 | AHD66: 2.4029906 | AHE66: 5.0162724 | AHF66: 1.996954 | AHG66: 0.85130467 | AHH66: 3.0929604 | AHI66: 1.8326291 | AHJ66: 0.86332096 | AHK66: 1.2875411 | AHL66: 1.4970821 | AHM66: 0.88746121 | AHN66: 2.0323137 | AHO66: 1.140761 | AHP66: -0.1423582 | AHQ66: 1.9306714 | AHR66: 0.17318842 | AHS66: 2.0388854 | AHT66: 3.8998763 | AHU66: 0.51671504 | AHV66: 1.4064849 | AHW66: 1.0213185 | AHX66: -0.09963165 | AHY66: -1.1690691 | AHZ66: 0.02160439 | AIA66: -0.52600911 | AIB66: 0.46790933 | AIC66: 0.13531089 | AID66: 1.9757354 | AIE66: 4.9487118 | AIF66: 0.88992526 | AIG66: 1.4499018 | AIH66: 1.1045524 | AII66: 4.1116882 | AIJ66: 1.820874 | AIK66: 1.4493872 | AIL66: 2.6750418 | AIM66: 1.5958196 | AIN66: 1.7129088 | AIO66: 1.3942764 | AIP66: 1.7931091 | AIQ66: 4.379615 | AIR66: 1.231937 | AIS66: 3.3841931 | AIT66: 2.9297573 | AIU66: 2.1525003 | AIV66: 0.83299095 | AIW66: -0.84427473 | AIX66: 2.187523 | AIY66: 1.9063273 | AIZ66: 3.2314496 | AJA66: 1.4791982 | AJB66: 1.7772263 | AJC66: 4.2423556 | AJD66: 0.1284674 | AJE66: 3.5756737 | AJF66: -0.50381268 | AJG66: 0.33421728 | AJH66: 3.8668764 | AJI66: 1.1181902 | AJJ66: 2.8245579 | AJK66: 2.662762 | AJL66: 0.52874954 | AJM66: 3.7682097 | AJN66: 2.2480124 | AJO66: 1.503065 | AJP66: 2.8826967 | AJQ66: 2.9103631 | AJR66: 1.397022 | AJS66: 1.5315546 | AJT66: 3.3985181 | AJU66: -1.4094167 | AJV66: 1.7388689 | AJW66: 1.5068995 | AJX66: 1.6055272 | AJY66: 1.7269007 | AJZ66: 2.0425765 | AKA66: 1.2687467 | AKB66: 1.8614722 | AKC66: 1.5603011 | AKD66: 3.1812399 | AKE66: -0.80154529 | AKF66: 1.6378774 | AKG66: 0.32990954 | AKH66: 1.4428515 | AKI66: 3.629038 | AKJ66: 2.6424947 | AKK66: 2.6518549 | AKL66: 1.0830697 | AKM66: 2.3396079 | AKN66: 0.70979587 | AKO66: -0.32145675 | AKP66: 0.43345503 | AKQ66: 1.2549112 | AKR66: 2.3275695 | AKS66: 1.133971 | AKT66: 0.83515347 | AKU66: 3.1552097 | AKV66: 2.6603115 | AKW66: 2.351487 | AKX66: 1.0307233 | AKY66: 1.546752 | AKZ66: 2.617322 | ALA66: 0.51091147 | ALB66: 2.1818384 | ALC66: 1.6997927 | ALD66: 0.1485163 | ALE66: 2.549337 | ALF66: 2.882871 | ALG66: -1.2992221 | ALH66: 2.0617688 | ALI66: 0.28179908 | ALJ66: 1.2801433 | ALK66: -0.30253895 | ALL66: 1.1907783 | ALM66: 4.2759527
A67: 35 | B67: =_xlfn.NORM.INV(RAND(),'Inflation Rates '!$B$401,'Inflation Rates '!$B$402) -> 1.3440627 | C67: -0.5237535 | D67: 4.5361282 | E67: 0.53303487 | F67: 1.7935715 | G67: 3.6165334 | H67: 2.4216322 | I67: 2.8312904 | J67: 2.7482892 | K67: 3.4141765 | L67: 2.4293265 | M67: 1.9697966 | N67: 0.5974889 | O67: 1.1073827 | P67: 1.1804534 | Q67: 1.1463294 | R67: 1.9172825 | S67: 1.2293529 | T67: -0.98953006 | U67: -0.28174347 | V67: 2.0822619 | W67: 0.65777558 | X67: 0.17776455 | Y67: 1.1084608 | Z67: -0.51401751 | AA67: -0.67287449 | AB67: 3.6918203 | AC67: 0.99303466 | AD67: 1.7009288 | AE67: 1.5316132 | AF67: 1.1879049 | AG67: 2.7909279 | AH67: 1.5858788 | AI67: 2.3439538 | AJ67: 0.74762807 | AK67: 1.4216339 | AL67: 2.1673723 | AM67: 0.9898729 | AN67: 0.9677583 | AO67: 2.4246287 | AP67: 1.3463913 | AQ67: 1.2090855 | AR67: 1.8279455 | AS67: 1.3938413 | AT67: 3.6391714 | AU67: 0.89003833 | AV67: 2.2893646 | AW67: 0.66744833 | AX67: 2.4443704 | AY67: 0.49750625 | AZ67: -0.29516603 | BA67: 3.3837998 | BB67: 0.24566989 | BC67: 2.4657534 | BD67: 0.40583956 | BE67: 5.1313066 | BF67: 1.0463978 | BG67: 1.0386655 | BH67: 1.3307322 | BI67: 0.26888213 | BJ67: 2.270339 | BK67: 2.9457728 | BL67: 0.041211489 | BM67: 2.899006 | BN67: 3.2661384 | BO67: 1.355702 | BP67: 0.12768066 | BQ67: 2.2185331 | BR67: -0.07629003 | BS67: 1.3558773 | BT67: 0.94417675 | BU67: 0.7874066 | BV67: 2.7261532 | BW67: 2.956865 | BX67: 2.2195969 | BY67: 1.9292994 | BZ67: 1.1465361 | CA67: -0.66749574 | CB67: 3.1664489 | CC67: 2.3109806 | CD67: 2.3432622 | CE67: 2.1543505 | CF67: 1.8835716 | CG67: 0.78033908 | CH67: 1.4467858 | CI67: 1.6301307 | CJ67: 0.3053658 | CK67: 0.80920025 | CL67: 1.2421348 | CM67: 1.1311323 | CN67: 0.48539797 | CO67: 1.8072235 | CP67: 2.3782826 | CQ67: 1.5690769 | CR67: 1.2080935 | CS67: 1.1823118 | CT67: 1.0905144 | CU67: 3.1034477 | CV67: 3.2049886 | CW67: 0.92302257 | CX67: 0.30881616 | CY67: 2.105543 | CZ67: 3.067902 | DA67: -0.30230739 | DB67: 0.71267157 | DC67: 3.1752976 | DD67: 1.5117344 | DE67: 1.4113707 | DF67: 2.5673688 | DG67: 1.5478028 | DH67: 2.9331983 | DI67: 2.8737676 | DJ67: 0.80950594 | DK67: 2.6187225 | DL67: 2.8088896 | DM67: 1.6134665 | DN67: 2.3015715 | DO67: 1.1324249 | DP67: 1.5769557 | DQ67: 1.6930444 | DR67: 1.784192 | DS67: 1.4103158 | DT67: 3.7582151 | DU67: 4.5317348 | DV67: 1.1117454 | DW67: 0.38720895 | DX67: 1.3928825 | DY67: 2.67151 | DZ67: 0.81943328 | EA67: 1.0914324 | EB67: -0.96232014 | EC67: -0.041940159 | ED67: 1.4613717 | EE67: 1.4251073 | EF67: 0.48260297 | EG67: 2.4308532 | EH67: 1.825565 | EI67: 2.1933203 | EJ67: 3.8907757 | EK67: 1.3014928 | EL67: 1.316739 | EM67: 3.9298512 | EN67: 1.2444302 | EO67: 4.0477817 | EP67: 0.079925569 | EQ67: 1.6847129 | ER67: 1.5635645 | ES67: 2.6537952 | ET67: 1.1043122 | EU67: 0.075246033 | EV67: 1.1910468 | EW67: 2.7031441 | EX67: 3.7523027 | EY67: 0.51979487 | EZ67: 3.8404641 | FA67: 0.62909312 | FB67: 1.9871371 | FC67: 2.2599628 | FD67: 0.25236988 | FE67: 0.34326205 | FF67: 2.7242318 | FG67: 0.72094966 | FH67: 0.86798325 | FI67: 4.1639365 | FJ67: 2.3403703 | FK67: 0.087694027 | FL67: 2.9218949 | FM67: 2.2719189 | FN67: 1.7405018 | FO67: 1.9146705 | FP67: 4.3994229 | FQ67: 2.3943018 | FR67: 2.1400917 | FS67: 1.6519914 | FT67: 0.79018236 | FU67: 1.785031 | FV67: 0.91248536 | FW67: 3.2916137 | FX67: 1.3142082 | FY67: 0.62093125 | FZ67: 0.34918352 | GA67: 2.7189906 | GB67: 1.5860145 | GC67: 1.7640057 | GD67: 0.88990265 | GE67: -0.1292719 | GF67: -0.76993963 | GG67: 1.7402812 | GH67: 3.8225616 | GI67: 0.79595203 | GJ67: 1.4315056 | GK67: 0.47031799 | GL67: 0.80169987 | GM67: 1.869364 | GN67: 1.2466295 | GO67: -0.21743845 | GP67: 1.5038905 | GQ67: 0.57379679 | GR67: 1.9479379 | GS67: 0.29469672 | GT67: 2.6903736 | GU67: 0.034565864 | GV67: 1.987499 | GW67: 1.3001568 | GX67: 1.7112735 | GY67: 2.1722231 | GZ67: 0.48924823 | HA67: 3.2113998 | HB67: 1.7487356 | HC67: 3.1520461 | HD67: 3.1185193 | HE67: 1.064844 | HF67: 0.66135346 | HG67: 1.793242 | HH67: 1.488836 | HI67: 2.0590933 | HJ67: 0.95149227 | HK67: -0.32136676 | HL67: 1.653804 | HM67: 2.1584061 | HN67: 1.2571159 | HO67: 1.8410812 | HP67: 1.3648544 | HQ67: 0.8912476 | HR67: 2.2138732 | HS67: 1.947978 | HT67: 3.5177031 | HU67: 4.7890772 | HV67: -1.2910295 | HW67: 1.8620336 | HX67: 1.6190485 | HY67: 0.11275106 | HZ67: 2.6992608 | IA67: 3.4758687 | IB67: 1.4228239 | IC67: 0.93762019 | ID67: 2.4346611 | IE67: 3.4278918 | IF67: -0.51327919 | IG67: 2.4089031 | IH67: -0.82233544 | II67: 2.7584976 | IJ67: 2.5084145 | IK67: 1.3784883 | IL67: 0.12707186 | IM67: 1.5910331 | IN67: 0.97266305 | IO67: 0.38263344 | IP67: 1.3952671 | IQ67: -0.44255317 | IR67: 0.55824898 | IS67: 2.705096 | IT67: 0.30087867 | IU67: 2.7380589 | IV67: 0.47379756 | IW67: 1.3120664 | IX67: 2.7365206 | IY67: 1.894158 | IZ67: 0.41618177 | JA67: 1.7812051 | JB67: 2.8104383 | JC67: 2.2392482 | JD67: 2.701054 | JE67: 2.3630427 | JF67: 1.1389133 | JG67: 0.44203514 | JH67: 2.9407222 | JI67: 3.2181166 | JJ67: 1.4995428 | JK67: 0.68065865 | JL67: 0.38673719 | JM67: 3.076287 | JN67: 1.813031 | JO67: -0.0018725187 | JP67: 1.7156927 | JQ67: 2.8007729 | JR67: 2.7371231 | JS67: -0.12773037 | JT67: 2.495874 | JU67: -0.28297228 | JV67: 1.8877499 | JW67: 0.45309336 | JX67: 0.52596134 | JY67: 0.17669225 | JZ67: 0.89812722 | KA67: 1.7700078 | KB67: 0.93631997 | KC67: 2.8808505 | KD67: 1.3817751 | KE67: 2.3999645 | KF67: 1.6119635 | KG67: 1.7920562 | KH67: 1.2163864 | KI67: 2.1292131 | KJ67: 1.844498 | KK67: 3.8815231 | KL67: 2.925822 | KM67: 1.9157311 | KN67: 2.6784584 | KO67: -0.27704961 | KP67: -0.25868656 | KQ67: 0.98997704 | KR67: 2.1058798 | KS67: 3.7627499 | KT67: 1.164962 | KU67: 1.2673067 | KV67: 1.9458869 | KW67: 2.8477042 | KX67: 3.5469764 | KY67: 3.8024139 | KZ67: 3.134226 | LA67: 0.80382409 | LB67: 3.5774453 | LC67: 1.6888641 | LD67: 2.5319607 | LE67: 1.3829475 | LF67: 0.46128429 | LG67: 2.1660805 | LH67: 2.5344243 | LI67: 1.7943467 | LJ67: 0.12505897 | LK67: 0.3375875 | LL67: 0.43227121 | LM67: 0.2042395 | LN67: 4.4593826 | LO67: 0.66348794 | LP67: 1.4496982 | LQ67: 2.825098 | LR67: 1.7871633 | LS67: 3.8488711 | LT67: 3.2729883 | LU67: 1.7779117 | LV67: 3.3057896 | LW67: -0.5805069 | LX67: -0.50892062 | LY67: -0.84357023 | LZ67: 2.8436586 | MA67: 2.7688128 | MB67: 0.68405631 | MC67: 0.64216832 | MD67: 3.660021 | ME67: 1.6077371 | MF67: 1.3477354 | MG67: 1.3364672 | MH67: 0.86195882 | MI67: 1.0658179 | MJ67: 1.6295809 | MK67: 0.86633448 | ML67: 1.5074176 | MM67: 1.3979426 | MN67: 4.9922535 | MO67: 2.5632432 | MP67: -1.3506206 | MQ67: -2.1177662 | MR67: -0.38733197 | MS67: 2.004006 | MT67: 1.0192706 | MU67: 1.7602001 | MV67: 1.871012 | MW67: 2.6711623 | MX67: 1.5270452 | MY67: 2.5064042 | MZ67: 1.1660054 | NA67: 2.7422512 | NB67: 2.125445 | NC67: 0.34067947 | ND67: 0.37294932 | NE67: 0.90930739 | NF67: 1.6703031 | NG67: 2.9523681 | NH67: 0.63013795 | NI67: 2.319926 | NJ67: -0.13192526 | NK67: 1.7498139 | NL67: 0.71630876 | NM67: 1.9095088 | NN67: 1.9369141 | NO67: 1.4898261 | NP67: 1.7290224 | NQ67: 1.7986911 | NR67: 1.9942672 | NS67: 0.93003845 | NT67: 1.9697253 | NU67: 1.2070631 | NV67: 0.56286696 | NW67: 1.844588 | NX67: 1.0526873 | NY67: 2.1773464 | NZ67: 2.4372339 | OA67: 2.3440176 | OB67: 2.7457995 | OC67: 2.2942413 | OD67: 4.0671301 | OE67: 2.0932105 | OF67: 2.6606339 | OG67: 2.5445782 | OH67: -1.5597752 | OI67: 0.98077264 | OJ67: 1.1388764 | OK67: 2.8728558 | OL67: 1.6714237 | OM67: 1.713046 | ON67: 1.1742323 | OO67: 2.237979 | OP67: 2.0506012 | OQ67: 2.2361659 | OR67: 2.2960757 | OS67: 1.4608583 | OT67: 2.8050404 | OU67: 1.4086911 | OV67: -1.50037 | OW67: 2.6247426 | OX67: -0.38826048 | OY67: 2.2703006 | OZ67: 1.4464714 | PA67: 0.15429533 | PB67: 2.7428814 | PC67: 3.1322156 | PD67: -0.72616855 | PE67: 1.0371709 | PF67: 2.1244242 | PG67: 2.9529568 | PH67: -0.26968645 | PI67: 2.5142327 | PJ67: 0.81547052 | PK67: 3.8428411 | PL67: 1.784627 | PM67: 3.4143288 | PN67: 3.0553417 | PO67: 2.926297 | PP67: 1.704283 | PQ67: 2.6242347 | PR67: 1.5823133 | PS67: 1.8032699 | PT67: 1.5995554 | PU67: 2.5687528 | PV67: 3.5498666 | PW67: -0.063537212 | PX67: 1.7513755 | PY67: 0.37599644 | PZ67: -0.082827343 | QA67: 0.77868519 | QB67: 2.001583 | QC67: 1.5264794 | QD67: 1.4366232 | QE67: 2.1245594 | QF67: 0.81577271 | QG67: 1.7133368 | QH67: 3.3999141 | QI67: 0.00080451032 | QJ67: -0.40503742 | QK67: 0.78186963 | QL67: 1.354058 | QM67: 0.35336503 | QN67: 1.3670974 | QO67: 2.4531414 | QP67: 2.9578986 | QQ67: 2.5487161 | QR67: 2.781431 | QS67: 0.93673579 | QT67: 2.9018207 | QU67: 2.5678692 | QV67: 1.8957035 | QW67: 3.7246288 | QX67: 3.3451026 | QY67: -0.050319227 | QZ67: 0.7068136 | RA67: 0.70313281 | RB67: 0.61410632 | RC67: 1.9472044 | RD67: 1.8983328 | RE67: 2.4197901 | RF67: 2.0511747 | RG67: 0.93369129 | RH67: 2.3116747 | RI67: 0.37435541 | RJ67: 1.8150623 | RK67: 1.9720183 | RL67: 1.3199695 | RM67: -1.1709807 | RN67: 0.94386304 | RO67: 2.5292901 | RP67: 2.4463945 | RQ67: 0.36482163 | RR67: 3.346035 | RS67: 0.72849366 | RT67: 0.5136328 | RU67: 1.2099973 | RV67: 0.76119284 | RW67: 0.34774905 | RX67: 0.55612587 | RY67: 2.8784153 | RZ67: 2.0891979 | SA67: 1.4470769 | SB67: 3.8753865 | SC67: 0.69800715 | SD67: 3.7411422 | SE67: 2.8724778 | SF67: 2.4336982 | SG67: 1.7095973 | SH67: 1.0294431 | SI67: 1.9194501 | SJ67: 2.4186362 | SK67: 0.68081002 | SL67: 0.088356085 | SM67: 2.2510447 | SN67: 1.4030342 | SO67: 1.6442016 | SP67: 1.797545 | SQ67: 1.6371627 | SR67: 1.5102637 | SS67: 2.1540749 | ST67: 0.25745697 | SU67: 2.6247004 | SV67: 3.3803578 | SW67: 1.3135274 | SX67: 2.7659167 | SY67: 1.1231342 | SZ67: 0.47405707 | TA67: 3.9439404 | TB67: 1.4953109 | TC67: 1.4538791 | TD67: 0.47950343 | TE67: 1.9014286 | TF67: 1.9033953 | TG67: 2.5383277 | TH67: 5.1439961 | TI67: 3.3758117 | TJ67: 4.3270011 | TK67: 0.73118672 | TL67: 1.9717265 | TM67: 2.4712162 | TN67: 0.19334797 | TO67: 0.53932906 | TP67: 1.0246626 | TQ67: 1.6463936 | TR67: 0.33299186 | TS67: 2.345563 | TT67: 2.4628806 | TU67: 1.0744602 | TV67: -0.18692631 | TW67: 2.8015486 | TX67: 2.441773 | TY67: 2.2025996 | TZ67: 1.9601115 | UA67: 2.780655 | UB67: -0.92148156 | UC67: 1.201992 | UD67: -0.99089656 | UE67: 1.450147 | UF67: -0.18893534 | UG67: -0.88209049 | UH67: 1.1753155 | UI67: 0.39296129 | UJ67: 2.0137965 | UK67: 0.95606741 | UL67: -1.0599399 | UM67: 4.5381327 | UN67: 0.24751159 | UO67: 0.074180536 | UP67: 2.1600829 | UQ67: 2.0881458 | UR67: 1.5157502 | US67: 3.1946578 | UT67: 0.48418744 | UU67: 0.81765222 | UV67: 3.2162505 | UW67: 2.4071071 | UX67: 2.8920442 | UY67: 1.8911349 | UZ67: 1.6028153 | VA67: 0.97608792 | VB67: 0.63883691 | VC67: 5.0787916 | VD67: 1.3776078 | VE67: 0.028127112 | VF67: 1.4765035 | VG67: 1.0105354 | VH67: 2.3325006 | VI67: 2.8917611 | VJ67: 3.4623169 | VK67: 1.0437207 | VL67: 2.8195135 | VM67: 3.0487462 | VN67: 2.237941 | VO67: 0.34866328 | VP67: 3.6941807 | VQ67: 2.3553074 | VR67: 3.4518987 | VS67: 1.0588858 | VT67: 1.0115788 | VU67: 1.5174577 | VV67: 1.3241497 | VW67: 2.1303249 | VX67: 2.0488866 | VY67: 0.4170738 | VZ67: 1.5653792 | WA67: 1.0438466 | WB67: 0.95667861 | WC67: 3.1524204 | WD67: 1.8483586 | WE67: 1.4315678 | WF67: 0.010558472 | WG67: 2.9925288 | WH67: -0.56855654 | WI67: 1.4195022 | WJ67: 0.12248831 | WK67: 1.3205254 | WL67: 1.09648 | WM67: 1.3990029 | WN67: 1.3385639 | WO67: 1.0203902 | WP67: 3.1759388 | WQ67: 2.6372431 | WR67: 1.0214331 | WS67: 0.71990102 | WT67: 0.7863542 | WU67: 1.3180695 | WV67: 4.4848323 | WW67: 3.4518925 | WX67: 1.7000387 | WY67: 1.0577812 | WZ67: 2.019774 | XA67: 1.9278799 | XB67: 1.1778177 | XC67: 2.1630795 | XD67: 4.1345265 | XE67: 3.0886029 | XF67: 1.5300661 | XG67: 0.82436701 | XH67: 2.2138269 | XI67: 1.2730927 | XJ67: 1.1745123 | XK67: 1.6083236 | XL67: 1.6530353 | XM67: 0.45630017 | XN67: 1.4032283 | XO67: 1.3166326 | XP67: -0.23733153 | XQ67: 1.1991025 | XR67: 1.6805158 | XS67: 4.1559669 | XT67: 3.1865701 | XU67: 1.1563535 | XV67: -0.025439736 | XW67: 0.82192089 | XX67: -0.053408629 | XY67: 1.9046135 | XZ67: 1.4410906 | YA67: 3.6357319 | YB67: 1.677285 | YC67: 0.77486531 | YD67: 0.77971362 | YE67: 1.9670515 | YF67: 3.6436446 | YG67: 0.91081761 | YH67: 1.1155848 | YI67: 3.1319802 | YJ67: 2.5931981 | YK67: 4.384935 | YL67: 0.91007183 | YM67: 1.8160853 | YN67: 2.1500921 | YO67: 1.2294664 | YP67: 1.1238739 | YQ67: 1.1646916 | YR67: 2.4104938 | YS67: 3.1543103 | YT67: 0.65992229 | YU67: 1.4076931 | YV67: 0.76085938 | YW67: 1.6591652 | YX67: 2.8702193 | YY67: 4.0851431 | YZ67: 2.1600971 | ZA67: 1.1770821 | ZB67: 3.1243286 | ZC67: 1.5799241 | ZD67: 2.3150112 | ZE67: 4.3217962 | ZF67: -0.45142782 | ZG67: 1.761951 | ZH67: 2.0811634 | ZI67: 1.7821634 | ZJ67: 0.92039514 | ZK67: 0.94463829 | ZL67: 1.0573885 | ZM67: 1.3860177 | ZN67: 1.0795193 | ZO67: 0.84028696 | ZP67: 1.8501318 | ZQ67: 0.50010311 | ZR67: 2.416416 | ZS67: -0.19484317 | ZT67: 1.7012115 | ZU67: 2.4078391 | ZV67: 3.1709727 | ZW67: 0.23153416 | ZX67: 2.435855 | ZY67: 1.1518614 | ZZ67: 0.97244226 | AAA67: -0.042566803 | AAB67: 0.867257 | AAC67: 0.82098882 | AAD67: 2.2202722 | AAE67: 1.4091894 | AAF67: 1.4618067 | AAG67: 0.64893764 | AAH67: 3.2255557 | AAI67: 3.711526 | AAJ67: 2.0469001 | AAK67: 1.703338 | AAL67: 1.5775705 | AAM67: 3.9415938 | AAN67: 1.1364446 | AAO67: 2.645899 | AAP67: 2.0610452 | AAQ67: 1.1909298 | AAR67: 1.6710175 | AAS67: -0.80146461 | AAT67: 1.9791675 | AAU67: 3.2521013 | AAV67: 1.7597031 | AAW67: 3.0107029 | AAX67: 1.0723321 | AAY67: 1.1324915 | AAZ67: 1.0836647 | ABA67: 1.5244217 | ABB67: 1.989076 | ABC67: 1.4021268 | ABD67: 1.5144393 | ABE67: 1.4571107 | ABF67: 4.4382386 | ABG67: 1.5416734 | ABH67: 3.866067 | ABI67: 0.95351046 | ABJ67: 2.3611053 | ABK67: 0.26539101 | ABL67: 0.69280455 | ABM67: -0.18764728 | ABN67: 2.3331985 | ABO67: 3.3070889 | ABP67: 1.0255705 | ABQ67: -0.7315644 | ABR67: 3.0447141 | ABS67: 0.93929942 | ABT67: -0.26660237 | ABU67: 2.7771395 | ABV67: 1.8846998 | ABW67: 0.58447758 | ABX67: 2.1821709 | ABY67: 0.65061319 | ABZ67: 2.1089382 | ACA67: 2.1641492 | ACB67: 0.31946133 | ACC67: 0.67957644 | ACD67: 1.8434081 | ACE67: 2.9554072 | ACF67: 1.8299498 | ACG67: 0.96304511 | ACH67: 1.2894544 | ACI67: 2.9404213 | ACJ67: 1.7897798 | ACK67: 1.5657601 | ACL67: 1.1502311 | ACM67: 2.105967 | ACN67: 2.8267927 | ACO67: 2.6989401 | ACP67: 2.0890523 | ACQ67: 1.5130964 | ACR67: 3.7691574 | ACS67: 2.5722523 | ACT67: 2.4105915 | ACU67: -1.3880488 | ACV67: 0.58983469 | ACW67: 0.0038096601 | ACX67: 1.7918707 | ACY67: 1.1212742 | ACZ67: -0.22192144 | ADA67: 0.96626143 | ADB67: 1.5921795 | ADC67: 1.4043764 | ADD67: 0.036336588 | ADE67: 1.9573075 | ADF67: 2.9529552 | ADG67: 1.9973212 | ADH67: 3.3630181 | ADI67: -1.1057515 | ADJ67: 1.4736648 | ADK67: 1.7339186 | ADL67: 0.40887296 | ADM67: 2.1816993 | ADN67: 1.2697818 | ADO67: 0.40934256 | ADP67: 2.4674521 | ADQ67: 2.4762799 | ADR67: 2.2098413 | ADS67: 0.71706786 | ADT67: 0.40792313 | ADU67: 0.87713876 | ADV67: 3.0535801 | ADW67: 1.4829789 | ADX67: 1.0412026 | ADY67: 1.6361714 | ADZ67: 3.4251091 | AEA67: 0.83090056 | AEB67: 2.2191414 | AEC67: -0.44576077 | AED67: -0.83417165 | AEE67: 2.2801795 | AEF67: -0.83980054 | AEG67: 1.3400417 | AEH67: 2.5452971 | AEI67: 0.95524268 | AEJ67: 1.8819976 | AEK67: -0.90943587 | AEL67: 1.183897 | AEM67: 1.6685302 | AEN67: 0.78698064 | AEO67: 2.1919891 | AEP67: 1.7455487 | AEQ67: -1.0745555 | AER67: 0.94140189 | AES67: 1.5511038 | AET67: 3.6835751 | AEU67: 2.3654923 | AEV67: 0.35894037 | AEW67: 2.6526819 | AEX67: 0.93358795 | AEY67: 1.4473213 | AEZ67: 0.48705445 | AFA67: 1.5876787 | AFB67: 0.91770844 | AFC67: 1.3112829 | AFD67: 1.0676684 | AFE67: 1.0451014 | AFF67: 2.0272918 | AFG67: 4.4200411 | AFH67: 3.5447045 | AFI67: -0.15622771 | AFJ67: 1.6348295 | AFK67: 1.8547169 | AFL67: 0.59316605 | AFM67: 2.4524977 | AFN67: -0.20660507 | AFO67: 2.273444 | AFP67: 3.4282232 | AFQ67: 0.84990943 | AFR67: 1.8887502 | AFS67: 1.1608863 | AFT67: 3.0005131 | AFU67: 0.014934241 | AFV67: 0.42167727 | AFW67: -0.10537902 | AFX67: 3.4042088 | AFY67: 3.1796547 | AFZ67: 1.3427174 | AGA67: 1.6675388 | AGB67: 2.6660554 | AGC67: 1.2937729 | AGD67: 2.8524663 | AGE67: 1.7138226 | AGF67: 1.2382565 | AGG67: 0.95034786 | AGH67: 1.5849256 | AGI67: -0.87331468 | AGJ67: 2.4237454 | AGK67: 0.77690295 | AGL67: 1.7184327 | AGM67: 2.1724231 | AGN67: 1.9282353 | AGO67: 0.10870334 | AGP67: 1.4881974 | AGQ67: 1.1746525 | AGR67: 1.7414608 | AGS67: 0.49717763 | AGT67: 0.47475131 | AGU67: 0.63097566 | AGV67: 0.46082607 | AGW67: 0.1807257 | AGX67: 0.92926465 | AGY67: 1.6555116 | AGZ67: 2.12669 | AHA67: 0.13901165 | AHB67: 1.6799179 | AHC67: 1.1605398 | AHD67: 0.19949816 | AHE67: 0.30344471 | AHF67: -0.78724452 | AHG67: 0.56299186 | AHH67: 0.41309596 | AHI67: 1.8710911 | AHJ67: 0.23546744 | AHK67: 2.1672381 | AHL67: 1.9237685 | AHM67: 1.0895968 | AHN67: 1.356997 | AHO67: 3.8853527 | AHP67: 3.8835832 | AHQ67: 2.2341031 | AHR67: 1.1966739 | AHS67: 2.4962827 | AHT67: 1.7206305 | AHU67: 1.9061726 | AHV67: 1.4258738 | AHW67: -0.47988837 | AHX67: 1.8060306 | AHY67: 0.03299197 | AHZ67: 1.4256891 | AIA67: 3.2597791 | AIB67: 1.9776516 | AIC67: 1.5561716 | AID67: 2.1249892 | AIE67: 1.8370403 | AIF67: 1.8418113 | AIG67: 1.93305 | AIH67: 2.0743733 | AII67: 1.8991972 | AIJ67: 0.66082084 | AIK67: -1.1490624 | AIL67: 1.5063969 | AIM67: 0.7177189 | AIN67: 1.7864999 | AIO67: -0.059895424 | AIP67: 1.1529132 | AIQ67: 3.0636641 | AIR67: 2.5868122 | AIS67: 2.5822341 | AIT67: 2.997225 | AIU67: 1.3566001 | AIV67: 2.4915146 | AIW67: 1.4141464 | AIX67: -0.75756312 | AIY67: 3.5251342 | AIZ67: -0.26921435 | AJA67: 1.6096058 | AJB67: 2.2701047 | AJC67: 1.2677793 | AJD67: 2.9184828 | AJE67: 0.80486817 | AJF67: 2.3961763 | AJG67: 1.9459909 | AJH67: 1.6745886 | AJI67: 2.2816785 | AJJ67: 1.3116196 | AJK67: 1.2833721 | AJL67: 3.8259073 | AJM67: 1.9885714 | AJN67: 0.30457032 | AJO67: 2.6434152 | AJP67: 1.1075169 | AJQ67: 2.8089145 | AJR67: -0.15229845 | AJS67: 1.8821784 | AJT67: 2.3389071 | AJU67: 0.55278526 | AJV67: 1.9913132 | AJW67: 1.6590394 | AJX67: 2.2211687 | AJY67: 1.7833632 | AJZ67: 0.18690747 | AKA67: 1.8134462 | AKB67: 1.6753328 | AKC67: 0.21987672 | AKD67: 1.7213542 | AKE67: -0.39493596 | AKF67: 3.1616178 | AKG67: 2.0827376 | AKH67: 1.5684405 | AKI67: 2.1363576 | AKJ67: 1.8567675 | AKK67: 2.2042543 | AKL67: 0.77794387 | AKM67: 2.5280169 | AKN67: 1.1697339 | AKO67: 1.322562 | AKP67: 2.665359 | AKQ67: 2.5430796 | AKR67: 0.95733222 | AKS67: 2.9963484 | AKT67: 0.027680485 | AKU67: 1.6867803 | AKV67: 0.024180415 | AKW67: 1.2774663 | AKX67: 2.4689419 | AKY67: 3.0447117 | AKZ67: 2.6960593 | ALA67: 2.3982373 | ALB67: 0.83393837 | ALC67: 0.38570628 | ALD67: 2.1432969 | ALE67: 2.3143662 | ALF67: 1.6484306 | ALG67: 2.7486809 | ALH67: 0.74697843 | ALI67: 0.015621685 | ALJ67: 1.3663654 | ALK67: -0.73797963 | ALL67: 1.3835499 | ALM67: 0.89791905
A68: 36 | B68: =_xlfn.NORM.INV(RAND(),'Inflation Rates '!$B$401,'Inflation Rates '!$B$402) -> 2.5058612 | C68: 1.3560222 | D68: 2.3245154 | E68: 1.2401654 | F68: 0.33547216 | G68: 2.1692669 | H68: 1.9207558 | I68: 0.13749605 | J68: 0.32429795 | K68: 1.932272 | L68: -0.12915395 | M68: 2.0819968 | N68: 1.9548804 | O68: 1.0301228 | P68: 2.7694156 | Q68: -0.079997959 | R68: 2.2615981 | S68: -1.9031925 | T68: 3.3850544 | U68: 4.6063662 | V68: 1.3723982 | W68: 0.080193669 | X68: -0.52655634 | Y68: 3.7632178 | Z68: 2.1676764 | AA68: 2.6272547 | AB68: 0.5026249 | AC68: 1.6846512 | AD68: 2.4848202 | AE68: 3.0418351 | AF68: -0.96636623 | AG68: 3.3989471 | AH68: 1.0501911 | AI68: 0.27515288 | AJ68: -2.0826949 | AK68: 3.6564265 | AL68: 0.6695281 | AM68: 0.33129133 | AN68: 1.9321657 | AO68: 2.3919768 | AP68: 1.2048415 | AQ68: 2.5449593 | AR68: 2.3228418 | AS68: 2.3211585 | AT68: 1.8656095 | AU68: 2.0048995 | AV68: 2.004186 | AW68: 1.4789411 | AX68: 2.5641288 | AY68: 1.6308187 | AZ68: 2.0357714 | BA68: 2.0391774 | BB68: 1.3660423 | BC68: 1.3574582 | BD68: 1.0629387 | BE68: 0.58593471 | BF68: 0.91481347 | BG68: 1.9686117 | BH68: 2.7571562 | BI68: 1.4597629 | BJ68: 0.45469334 | BK68: 2.9361475 | BL68: 0.84101532 | BM68: 2.4679073 | BN68: -0.50874456 | BO68: 1.5446502 | BP68: 2.141241 | BQ68: 0.83527381 | BR68: 0.51964867 | BS68: 2.4338619 | BT68: 0.27492403 | BU68: 0.70264568 | BV68: 0.82555208 | BW68: 2.4216311 | BX68: -0.22989129 | BY68: 2.1958596 | BZ68: 0.67606714 | CA68: 2.0965659 | CB68: 2.326684 | CC68: 1.947485 | CD68: 3.7345952 | CE68: 2.3797561 | CF68: 3.4743509 | CG68: 2.3679626 | CH68: 1.1757926 | CI68: 0.078396167 | CJ68: 1.2074608 | CK68: 2.4182432 | CL68: 0.49364082 | CM68: 1.7787994 | CN68: 0.64576651 | CO68: -0.68740633 | CP68: 0.99825501 | CQ68: 2.3457902 | CR68: 3.9395682 | CS68: 1.5146997 | CT68: 1.3376567 | CU68: 3.2414772 | CV68: 0.032217336 | CW68: 1.796312 | CX68: 0.34131878 | CY68: 3.785025 | CZ68: -1.1425984 | DA68: 1.52892 | DB68: 1.8504769 | DC68: 2.0976512 | DD68: 1.1852132 | DE68: 2.0597704 | DF68: 2.1740353 | DG68: -1.9020682 | DH68: 1.2219002 | DI68: 1.6927056 | DJ68: 1.3308269 | DK68: 3.0157393 | DL68: 2.0730138 | DM68: 1.9755419 | DN68: 3.4093882 | DO68: 2.7637299 | DP68: 3.1931904 | DQ68: 2.1799183 | DR68: 3.3810636 | DS68: 1.5784436 | DT68: 0.37542169 | DU68: 1.5900447 | DV68: 2.7894918 | DW68: 2.1174083 | DX68: 0.52555606 | DY68: 2.9234057 | DZ68: 1.4812335 | EA68: 1.9798265 | EB68: -1.0204458 | EC68: 1.9560629 | ED68: 2.2817076 | EE68: 2.5902364 | EF68: 2.0392779 | EG68: 3.4823931 | EH68: 3.6069393 | EI68: 1.6549036 | EJ68: 1.8815598 | EK68: 1.1368015 | EL68: 1.3096975 | EM68: 2.3384822 | EN68: 1.8537064 | EO68: -0.051964759 | EP68: 1.5924368 | EQ68: 2.0085143 | ER68: 2.1859066 | ES68: 1.8935557 | ET68: 1.4477014 | EU68: 2.6337024 | EV68: 3.009193 | EW68: 2.6140774 | EX68: 2.831621 | EY68: 3.8149088 | EZ68: 2.3052423 | FA68: 2.0783959 | FB68: 0.8532793 | FC68: 0.22135453 | FD68: 0.58952267 | FE68: -0.041539231 | FF68: 2.747961 | FG68: 2.5614806 | FH68: 1.084319 | FI68: 1.6854138 | FJ68: 1.3507736 | FK68: 3.9963708 | FL68: 2.8265273 | FM68: 0.80062255 | FN68: 2.4961599 | FO68: 0.66332133 | FP68: 0.90956052 | FQ68: -0.36349012 | FR68: -0.30454402 | FS68: 0.66226798 | FT68: 1.3395394 | FU68: 1.7566651 | FV68: 2.0988347 | FW68: 0.18756737 | FX68: 3.0471768 | FY68: 1.3410098 | FZ68: 1.2550998 | GA68: 3.9226008 | GB68: 1.5637215 | GC68: 2.6745842 | GD68: 2.2453208 | GE68: 3.9515601 | GF68: 0.69192239 | GG68: 1.6148764 | GH68: 2.8676684 | GI68: 3.2985671 | GJ68: 2.0328032 | GK68: 1.881476 | GL68: 2.3525848 | GM68: 1.708366 | GN68: 5.6229762 | GO68: 3.3519217 | GP68: 3.1476116 | GQ68: 3.1930077 | GR68: 0.80995816 | GS68: 2.8069202 | GT68: 0.95759981 | GU68: -0.084698247 | GV68: 2.6498435 | GW68: 2.8417356 | GX68: 2.8275557 | GY68: 2.8191825 | GZ68: 1.1528018 | HA68: 0.66908147 | HB68: -0.55481514 | HC68: 1.5059187 | HD68: 2.2757671 | HE68: 2.3577157 | HF68: 1.0852824 | HG68: 2.4590531 | HH68: 2.2790588 | HI68: 1.1137344 | HJ68: 1.9166975 | HK68: 2.1216515 | HL68: 0.97224696 | HM68: 2.4292777 | HN68: 1.3767547 | HO68: 2.2522505 | HP68: 0.16270619 | HQ68: 0.49359101 | HR68: 1.0963236 | HS68: 1.2848574 | HT68: 2.1937065 | HU68: 3.3830141 | HV68: 0.44855463 | HW68: 2.3905318 | HX68: 3.8206318 | HY68: 1.8048804 | HZ68: 1.0895665 | IA68: 2.9913172 | IB68: 0.97455112 | IC68: 1.720652 | ID68: 3.5144171 | IE68: 1.8073525 | IF68: 5.1401975 | IG68: 1.86344 | IH68: 1.8984827 | II68: 3.3507586 | IJ68: -0.19426529 | IK68: 0.92031596 | IL68: 3.6820276 | IM68: 1.5795646 | IN68: 2.527558 | IO68: 0.6383528 | IP68: 1.2038163 | IQ68: -0.42532831 | IR68: 2.1173496 | IS68: 0.65514486 | IT68: 4.2290363 | IU68: 0.89867013 | IV68: 0.82689703 | IW68: 1.5025212 | IX68: 1.4817933 | IY68: 1.791543 | IZ68: 1.3637314 | JA68: -0.60059839 | JB68: 3.5460512 | JC68: 3.3785593 | JD68: 3.4186121 | JE68: 1.3837392 | JF68: 1.9441323 | JG68: 2.6204664 | JH68: 0.25208203 | JI68: 1.3311866 | JJ68: 0.58842689 | JK68: 0.72777244 | JL68: 1.7016025 | JM68: 1.368227 | JN68: 1.6038964 | JO68: 0.92578946 | JP68: 3.3140055 | JQ68: 1.785265 | JR68: 3.5057112 | JS68: 0.91113627 | JT68: 2.1668208 | JU68: -0.3253875 | JV68: 1.3246172 | JW68: 1.642439 | JX68: 2.9658386 | JY68: 1.0766066 | JZ68: 0.32099998 | KA68: 2.9184858 | KB68: 0.78221327 | KC68: 1.4159933 | KD68: 1.3084723 | KE68: 0.81113382 | KF68: 2.1426398 | KG68: 2.4543695 | KH68: -0.86272533 | KI68: -0.71052035 | KJ68: 0.77067543 | KK68: 2.975296 | KL68: 2.4328735 | KM68: 0.82503056 | KN68: 0.38425357 | KO68: 1.7619004 | KP68: 0.11254549 | KQ68: 2.4784245 | KR68: 0.83157049 | KS68: 1.5642925 | KT68: 1.9715834 | KU68: 1.1755174 | KV68: 0.0006937608 | KW68: 1.4842584 | KX68: 2.0190242 | KY68: 0.88308768 | KZ68: 0.058747087 | LA68: 2.781363 | LB68: 1.7536155 | LC68: 3.003122 | LD68: 1.7716001 | LE68: 1.6112669 | LF68: 0.96320326 | LG68: 1.3356539 | LH68: 1.8842606 | LI68: 1.5071066 | LJ68: 0.81773812 | LK68: 2.3277787 | LL68: 2.4742418 | LM68: 2.8043517 | LN68: 3.1171889 | LO68: 3.9548953 | LP68: 1.8927305 | LQ68: 0.63513941 | LR68: 1.1794556 | LS68: 2.5669459 | LT68: 2.59146 | LU68: 0.60990588 | LV68: -0.039546609 | LW68: 2.7380555 | LX68: 0.60343601 | LY68: 0.67561731 | LZ68: 0.44370901 | MA68: 1.0692198 | MB68: 3.0385228 | MC68: 3.5435477 | MD68: 1.3711547 | ME68: 3.2536919 | MF68: 2.6576525 | MG68: 2.4321509 | MH68: 0.73799965 | MI68: 1.7825119 | MJ68: 1.9262518 | MK68: 3.4068326 | ML68: 3.2366786 | MM68: 0.52128961 | MN68: 2.520456 | MO68: 1.2530042 | MP68: 0.47558997 | MQ68: 1.5064047 | MR68: 1.1071729 | MS68: 0.87003865 | MT68: 2.553926 | MU68: 1.008434 | MV68: 1.3141753 | MW68: 2.5350001 | MX68: 1.2174027 | MY68: 0.59756078 | MZ68: 1.3032954 | NA68: 1.2979222 | NB68: -0.68138363 | NC68: 1.4602789 | ND68: 1.420902 | NE68: 3.5769349 | NF68: 1.8343861 | NG68: 1.844488 | NH68: 1.979137 | NI68: 0.71366049 | NJ68: 1.7199461 | NK68: 0.76017564 | NL68: 1.5234786 | NM68: 1.8425149 | NN68: 1.8773536 | NO68: 2.5414581 | NP68: 2.1626506 | NQ68: 0.49698047 | NR68: 0.92837037 | NS68: 2.9455603 | NT68: 2.3714547 | NU68: 0.6953568 | NV68: 1.6585468 | NW68: 1.4296743 | NX68: 2.3260051 | NY68: 2.3314836 | NZ68: 2.298795 | OA68: 1.1732882 | OB68: 0.9995003 | OC68: 2.5030558 | OD68: 0.85735075 | OE68: 4.7740753 | OF68: 1.4537112 | OG68: 2.7260696 | OH68: 4.5922282 | OI68: 2.0920704 | OJ68: 4.3632336 | OK68: 1.7989167 | OL68: 2.5094581 | OM68: 2.7674041 | ON68: 1.5531984 | OO68: 1.2526713 | OP68: 2.3328423 | OQ68: 2.7744771 | OR68: 1.51956 | OS68: 2.1717092 | OT68: 2.9354529 | OU68: 2.1873989 | OV68: 1.4195805 | OW68: 3.2786571 | OX68: 0.94003433 | OY68: 1.2138818 | OZ68: 2.0463686 | PA68: -0.57744306 | PB68: 2.1204891 | PC68: 2.8625668 | PD68: 1.6025813 | PE68: 0.64915815 | PF68: 2.3524616 | PG68: 2.2314229 | PH68: 1.6077103 | PI68: 0.96256431 | PJ68: 0.38962806 | PK68: -1.3576191 | PL68: 4.6419694 | PM68: 1.0997737 | PN68: 0.74797269 | PO68: 2.6128232 | PP68: 2.5323569 | PQ68: 1.581986 | PR68: 0.70749994 | PS68: 2.5720839 | PT68: 1.1210144 | PU68: 3.0256279 | PV68: 2.4792008 | PW68: 3.0267438 | PX68: 3.1814499 | PY68: 3.3565694 | PZ68: 0.065628812 | QA68: 1.3411264 | QB68: 0.95680247 | QC68: 1.5229952 | QD68: -0.60221008 | QE68: 0.89824641 | QF68: -0.19240271 | QG68: 0.24072056 | QH68: 2.946184 | QI68: 1.0912412 | QJ68: 2.9160888 | QK68: 3.7666849 | QL68: 1.1136175 | QM68: 1.4379064 | QN68: 2.2204311 | QO68: 2.3947345 | QP68: 1.6364292 | QQ68: 0.35519507 | QR68: 1.8896018 | QS68: 1.5773566 | QT68: 2.4460315 | QU68: 2.3599513 | QV68: -1.1871902 | QW68: 1.4214869 | QX68: 2.5279338 | QY68: 1.4937088 | QZ68: 1.5722623 | RA68: 2.1189984 | RB68: 2.5218417 | RC68: -0.099681714 | RD68: 1.4567656 | RE68: 3.754518 | RF68: 1.6916944 | RG68: -0.5243693 | RH68: 1.6776069 | RI68: 2.1605885 | RJ68: 0.90238442 | RK68: -0.022054692 | RL68: 3.1033911 | RM68: 2.8106189 | RN68: 2.666706 | RO68: 1.562282 | RP68: 1.7123232 | RQ68: 1.472339 | RR68: 2.0082833 | RS68: -1.0525672 | RT68: 3.21919 | RU68: -0.47861083 | RV68: 2.3555282 | RW68: 0.46209552 | RX68: 3.0974213 | RY68: 3.1102317 | RZ68: 2.2391792 | SA68: 2.1395179 | SB68: 0.70389791 | SC68: -1.2268185 | SD68: -0.3621569 | SE68: 4.3092973 | SF68: 4.5093999 | SG68: 3.6325863 | SH68: 1.8972539 | SI68: 2.373162 | SJ68: 2.9366182 | SK68: 2.1214023 | SL68: 1.3252353 | SM68: 2.1090876 | SN68: 2.9858314 | SO68: 1.8822509 | SP68: 2.3131114 | SQ68: 1.6421962 | SR68: 1.7719549 | SS68: 1.5660015 | ST68: 0.36430681 | SU68: 1.0360007 | SV68: -0.083559075 | SW68: 1.4800496 | SX68: 1.7029688 | SY68: 2.2882734 | SZ68: 1.8525487 | TA68: 2.4364721 | TB68: 2.0920326 | TC68: 0.85231994 | TD68: 2.1205858 | TE68: 2.0240948 | TF68: 3.6371 | TG68: 0.69974706 | TH68: 2.2155856 | TI68: 2.1155816 | TJ68: 2.172825 | TK68: 0.80029341 | TL68: 2.1850655 | TM68: 0.68180299 | TN68: 0.50189255 | TO68: -1.1283372 | TP68: 1.4110336 | TQ68: 2.9158285 | TR68: 0.13796465 | TS68: 1.6177734 | TT68: 2.3897901 | TU68: 0.87189454 | TV68: 2.2807996 | TW68: 0.64536643 | TX68: 2.7656559 | TY68: 0.63488346 | TZ68: 2.4877837 | UA68: 1.904951 | UB68: 2.7644253 | UC68: 1.2061949 | UD68: 0.72591113 | UE68: 0.99796264 | UF68: 1.3844173 | UG68: 2.5065286 | UH68: 2.4227774 | UI68: 1.2407991 | UJ68: 0.079656745 | UK68: 1.5142991 | UL68: -0.1963241 | UM68: 0.87311223 | UN68: 1.4563841 | UO68: 1.3882715 | UP68: 3.0286107 | UQ68: 3.3444249 | UR68: 3.4090854 | US68: 0.15238993 | UT68: 1.8954562 | UU68: 1.575897 | UV68: 1.4599764 | UW68: 1.1923947 | UX68: -0.35319101 | UY68: -2.6120594 | UZ68: 2.7830205 | VA68: 2.7381967 | VB68: 0.50454329 | VC68: 1.5100408 | VD68: 0.86559905 | VE68: 1.2329018 | VF68: 3.7898924 | VG68: 1.8775652 | VH68: -0.086856 | VI68: 2.0332705 | VJ68: 1.3817163 | VK68: 4.4226764 | VL68: 1.7226073 | VM68: 0.82309551 | VN68: 1.9014661 | VO68: 2.3061114 | VP68: 1.9771889 | VQ68: 2.0228718 | VR68: 1.6820885 | VS68: 2.0389586 | VT68: 2.7720505 | VU68: 3.2499282 | VV68: 3.2637176 | VW68: 0.37907333 | VX68: 4.1774412 | VY68: 2.0083802 | VZ68: 1.1278752 | WA68: 2.6534024 | WB68: 1.7061548 | WC68: 0.66393533 | WD68: 2.4395394 | WE68: 1.7843754 | WF68: 2.5970437 | WG68: 3.1460247 | WH68: 3.0157893 | WI68: 2.3919119 | WJ68: 1.3228292 | WK68: 2.1879533 | WL68: 3.0884605 | WM68: 2.635797 | WN68: 2.3146464 | WO68: 2.5134613 | WP68: 0.86192447 | WQ68: 1.6159888 | WR68: 1.791545 | WS68: -1.6737391 | WT68: 1.5859266 | WU68: 2.0663458 | WV68: 1.1372855 | WW68: 0.17606891 | WX68: 2.8270545 | WY68: 0.55203241 | WZ68: 1.1664154 | XA68: 1.2573061 | XB68: 3.2945678 | XC68: 1.0556474 | XD68: -0.287467 | XE68: 1.3724186 | XF68: 1.1852814 | XG68: 2.2854516 | XH68: 2.1508564 | XI68: 2.6000988 | XJ68: 2.0925019 | XK68: 1.1873397 | XL68: 2.7546463 | XM68: 2.0232882 | XN68: 0.39935224 | XO68: 0.24505486 | XP68: 2.2045206 | XQ68: 2.0992095 | XR68: -1.5359824 | XS68: 2.1795935 | XT68: 1.2628125 | XU68: 3.4919783 | XV68: 0.88500166 | XW68: -0.020853503 | XX68: 1.7777319 | XY68: 1.2373427 | XZ68: 3.186979 | YA68: 1.9120665 | YB68: 2.410299 | YC68: 1.757261 | YD68: 2.6906573 | YE68: 2.3134303 | YF68: 2.4573084 | YG68: 2.1220026 | YH68: 1.3597789 | YI68: 0.30790598 | YJ68: 1.8568576 | YK68: 0.35495508 | YL68: 2.0073863 | YM68: 2.7260918 | YN68: 2.5035803 | YO68: 1.5968066 | YP68: 1.9090793 | YQ68: 0.78498203 | YR68: -0.53334703 | YS68: 0.22615879 | YT68: 2.7505378 | YU68: 1.1552554 | YV68: 1.4858684 | YW68: 0.28677642 | YX68: 1.5367137 | YY68: 1.2816063 | YZ68: 2.8707232 | ZA68: 2.8268518 | ZB68: 0.71632182 | ZC68: 1.2964695 | ZD68: 3.3724223 | ZE68: 2.862629 | ZF68: 1.2193867 | ZG68: 1.9815529 | ZH68: 0.12604226 | ZI68: 0.8636883 | ZJ68: 3.33735 | ZK68: 1.7373349 | ZL68: 1.127275 | ZM68: -0.10249521 | ZN68: 3.0874906 | ZO68: 1.049295 | ZP68: 1.7526153 | ZQ68: 2.5789689 | ZR68: 1.024248 | ZS68: 1.1049851 | ZT68: 2.0034282 | ZU68: 2.9904691 | ZV68: 2.674462 | ZW68: 2.117453 | ZX68: 2.0268353 | ZY68: 2.468051 | ZZ68: 3.702242 | AAA68: 3.8701261 | AAB68: 1.8966077 | AAC68: 2.5354876 | AAD68: 1.8674988 | AAE68: 0.83578336 | AAF68: 0.41222597 | AAG68: 0.14580621 | AAH68: 2.0102611 | AAI68: 3.0463247 | AAJ68: 2.244951 | AAK68: 2.0596213 | AAL68: 0.061700376 | AAM68: 1.180488 | AAN68: 2.8557389 | AAO68: 3.9838911 | AAP68: 1.3848549 | AAQ68: 1.9438435 | AAR68: 1.8258399 | AAS68: 0.40662932 | AAT68: 1.5768012 | AAU68: 1.0749926 | AAV68: 1.3140845 | AAW68: 1.329345 | AAX68: -1.0858037 | AAY68: 0.23483375 | AAZ68: 1.8371931 | ABA68: 1.2359496 | ABB68: 1.535427 | ABC68: 1.0269165 | ABD68: 0.54017808 | ABE68: 2.4659715 | ABF68: 0.5957055 | ABG68: 1.4938532 | ABH68: 0.26474271 | ABI68: 4.659695 | ABJ68: 0.41457446 | ABK68: 2.6430861 | ABL68: 0.010877163 | ABM68: 1.8752964 | ABN68: 2.4659638 | ABO68: 2.2514976 | ABP68: -0.7460316 | ABQ68: 0.64807785 | ABR68: 2.0725024 | ABS68: -1.018592 | ABT68: 0.13436323 | ABU68: 3.6169892 | ABV68: 0.37053689 | ABW68: 3.1934815 | ABX68: 2.1901182 | ABY68: -0.26745229 | ABZ68: 2.1051766 | ACA68: 0.91917482 | ACB68: 3.1504186 | ACC68: 2.4123744 | ACD68: 3.5492056 | ACE68: 3.0394805 | ACF68: 0.97402879 | ACG68: 1.6476027 | ACH68: 0.44252132 | ACI68: 3.6694923 | ACJ68: 3.4153792 | ACK68: 1.7411226 | ACL68: 1.911022 | ACM68: 1.3819964 | ACN68: 0.090686437 | ACO68: 2.3521517 | ACP68: 1.774787 | ACQ68: 0.56173959 | ACR68: 2.6776412 | ACS68: 3.3538319 | ACT68: 2.0849263 | ACU68: 0.093018994 | ACV68: 0.34167277 | ACW68: 0.25947935 | ACX68: 2.5896845 | ACY68: 1.6426661 | ACZ68: 1.4633336 | ADA68: -0.47326592 | ADB68: 0.27096855 | ADC68: 1.7456743 | ADD68: 3.4184343 | ADE68: 1.3976303 | ADF68: 1.4543787 | ADG68: 1.6578478 | ADH68: 3.8393707 | ADI68: 4.217344 | ADJ68: 1.4715014 | ADK68: 2.9588876 | ADL68: 1.102297 | ADM68: 2.747052 | ADN68: 1.7777409 | ADO68: 2.2350968 | ADP68: 1.9648545 | ADQ68: 0.14217194 | ADR68: 2.020158 | ADS68: 2.5081245 | ADT68: 0.95234371 | ADU68: 1.0216262 | ADV68: 1.7852949 | ADW68: 3.5251177 | ADX68: -0.14479336 | ADY68: 1.1901981 | ADZ68: 1.6227802 | AEA68: -0.13676114 | AEB68: 2.4806583 | AEC68: 1.217527 | AED68: 2.0170136 | AEE68: 0.80454294 | AEF68: 2.1230822 | AEG68: 2.6028911 | AEH68: 1.1373637 | AEI68: 3.1182099 | AEJ68: 3.0336378 | AEK68: 1.8569116 | AEL68: 1.0444013 | AEM68: 1.6956614 | AEN68: 2.0285325 | AEO68: 0.021368113 | AEP68: 0.66036845 | AEQ68: 2.070011 | AER68: 2.5198474 | AES68: 2.6189433 | AET68: 1.9359481 | AEU68: 1.0511504 | AEV68: 2.3212027 | AEW68: 1.6262816 | AEX68: 1.1919724 | AEY68: 1.2907656 | AEZ68: 2.3112705 | AFA68: 3.2655365 | AFB68: 3.3220151 | AFC68: 2.6358161 | AFD68: 1.8402538 | AFE68: 3.1792128 | AFF68: -0.42564743 | AFG68: -0.25294062 | AFH68: 2.2055573 | AFI68: 1.0292734 | AFJ68: 0.47105429 | AFK68: 1.7278196 | AFL68: 3.3296558 | AFM68: 0.76172914 | AFN68: 0.59273674 | AFO68: 3.0882594 | AFP68: 2.2450241 | AFQ68: 1.9457514 | AFR68: 3.740563 | AFS68: 3.7212085 | AFT68: 2.282103 | AFU68: 1.5609833 | AFV68: -0.071353927 | AFW68: 0.044170895 | AFX68: 3.6722573 | AFY68: 1.2627654 | AFZ68: 1.6174525 | AGA68: 0.47791476 | AGB68: 1.1341946 | AGC68: 2.5622892 | AGD68: 2.7524681 | AGE68: 1.953584 | AGF68: 2.378719 | AGG68: 2.2571536 | AGH68: 1.8285243 | AGI68: 0.84181455 | AGJ68: 2.9894094 | AGK68: 1.0685912 | AGL68: 2.9354127 | AGM68: 2.2948655 | AGN68: 2.672773 | AGO68: 0.26393318 | AGP68: 3.9191843 | AGQ68: 1.2005357 | AGR68: 2.4206943 | AGS68: 2.6880567 | AGT68: 1.5879863 | AGU68: 0.4337094 | AGV68: 1.7603209 | AGW68: 1.3029167 | AGX68: -0.37666045 | AGY68: 0.94106851 | AGZ68: 0.13631169 | AHA68: 1.2938612 | AHB68: -0.39043562 | AHC68: -0.84144156 | AHD68: 2.6913989 | AHE68: 0.063080793 | AHF68: 2.3399395 | AHG68: 0.96789505 | AHH68: 1.4381231 | AHI68: 1.8442874 | AHJ68: 2.6931598 | AHK68: 2.6130907 | AHL68: -0.21967826 | AHM68: 2.8382176 | AHN68: 1.765918 | AHO68: 4.553555 | AHP68: 1.49262 | AHQ68: 3.4689979 | AHR68: 1.9066807 | AHS68: 1.7997734 | AHT68: 0.67042286 | AHU68: 3.0479418 | AHV68: 2.5220944 | AHW68: 1.399509 | AHX68: 3.5020322 | AHY68: 1.8403942 | AHZ68: 1.5023427 | AIA68: 1.3267807 | AIB68: 3.777853 | AIC68: 0.89491601 | AID68: 3.5746004 | AIE68: 3.1727043 | AIF68: 0.46145215 | AIG68: 0.92184283 | AIH68: 0.77884295 | AII68: -0.55403975 | AIJ68: 1.6626941 | AIK68: 3.1406834 | AIL68: 1.674618 | AIM68: 2.0295972 | AIN68: 0.95072059 | AIO68: 1.0518745 | AIP68: 3.1365602 | AIQ68: 0.66865948 | AIR68: 0.68320602 | AIS68: 2.0124459 | AIT68: 0.19886114 | AIU68: 1.148196 | AIV68: 2.0243041 | AIW68: 2.4171315 | AIX68: 2.6683778 | AIY68: 1.3067074 | AIZ68: 0.31607412 | AJA68: 0.11250122 | AJB68: 1.5864789 | AJC68: 2.0108503 | AJD68: 0.83836181 | AJE68: 0.50113409 | AJF68: 1.5516295 | AJG68: 0.055307292 | AJH68: 2.9652397 | AJI68: 2.0723858 | AJJ68: 1.085658 | AJK68: 1.155978 | AJL68: -0.15699814 | AJM68: 3.1262835 | AJN68: 4.4546169 | AJO68: 2.1826639 | AJP68: 0.078449036 | AJQ68: 1.6775212 | AJR68: 3.3496893 | AJS68: 1.8662385 | AJT68: 2.8702749 | AJU68: 4.2726909 | AJV68: 2.4488205 | AJW68: 0.84900857 | AJX68: 2.1107233 | AJY68: 1.6731034 | AJZ68: 3.0247296 | AKA68: 2.295834 | AKB68: 3.6169114 | AKC68: 0.62894765 | AKD68: 0.083953655 | AKE68: -0.60387219 | AKF68: 2.3711891 | AKG68: 2.6994055 | AKH68: 0.31700773 | AKI68: 3.0536117 | AKJ68: 4.077486 | AKK68: 1.7595708 | AKL68: 1.7086584 | AKM68: 3.1659981 | AKN68: 0.75158954 | AKO68: 0.9974251 | AKP68: 1.0167378 | AKQ68: 0.39342883 | AKR68: 2.7589206 | AKS68: 1.4568176 | AKT68: 1.2102377 | AKU68: 1.9475816 | AKV68: 2.7365725 | AKW68: 2.1076313 | AKX68: -0.98940513 | AKY68: 1.6318031 | AKZ68: 2.2092414 | ALA68: 3.1629241 | ALB68: 2.5163618 | ALC68: 3.4000468 | ALD68: 2.0103737 | ALE68: 2.321997 | ALF68: 2.3574531 | ALG68: 2.1832392 | ALH68: 1.0172746 | ALI68: 0.57197489 | ALJ68: 0.15781106 | ALK68: 1.2297604 | ALL68: 1.3336239 | ALM68: -0.55396376
A69: 37 | B69: =_xlfn.NORM.INV(RAND(),'Inflation Rates '!$B$401,'Inflation Rates '!$B$402) -> 2.4953187 | C69: 1.7359163 | D69: 2.5305625 | E69: -1.4112829 | F69: 2.4888332 | G69: 0.87031848 | H69: 2.6672549 | I69: 0.43038871 | J69: 1.2600464 | K69: 2.433605 | L69: 2.4332434 | M69: 1.6463294 | N69: 2.6263766 | O69: 0.95295602 | P69: 2.9297531 | Q69: 2.1388802 | R69: 2.795137 | S69: 1.6010558 | T69: 2.2140537 | U69: -0.42954963 | V69: 0.18483285 | W69: 1.5738054 | X69: 2.01767 | Y69: 1.235957 | Z69: 1.6871003 | AA69: 1.6735131 | AB69: 1.4519879 | AC69: 1.4594961 | AD69: 1.2346518 | AE69: 1.7243704 | AF69: 1.0425588 | AG69: 2.3645437 | AH69: 3.3804059 | AI69: 3.0257575 | AJ69: 1.3531308 | AK69: 2.0107244 | AL69: -0.9934652 | AM69: 3.8882594 | AN69: 3.7608672 | AO69: 2.6284219 | AP69: -0.13934746 | AQ69: 2.2275716 | AR69: 0.55388678 | AS69: 3.1676547 | AT69: 2.5984179 | AU69: 3.3132571 | AV69: -0.16764473 | AW69: 2.7045386 | AX69: 3.1897971 | AY69: 1.0677768 | AZ69: 0.63206301 | BA69: 2.5209245 | BB69: 1.8488089 | BC69: 3.0580618 | BD69: 2.5435178 | BE69: 2.8198329 | BF69: 0.56880441 | BG69: 3.0996213 | BH69: 0.67192657 | BI69: 0.99683013 | BJ69: 0.89239342 | BK69: 0.67147958 | BL69: 1.7053904 | BM69: 1.1553129 | BN69: -0.25506073 | BO69: 2.7148635 | BP69: 0.7139338 | BQ69: 1.2742851 | BR69: 2.2973119 | BS69: 0.99876201 | BT69: 1.5863089 | BU69: 0.17326379 | BV69: 1.9797947 | BW69: 0.56932566 | BX69: 1.1618178 | BY69: 0.25482732 | BZ69: 1.163714 | CA69: 2.432625 | CB69: 1.961651 | CC69: 0.68190668 | CD69: 1.264893 | CE69: 1.9511789 | CF69: -0.31646264 | CG69: 0.4316933 | CH69: 0.65478437 | CI69: 2.1332438 | CJ69: 3.4423873 | CK69: 2.1245065 | CL69: 1.8437439 | CM69: 0.86838545 | CN69: 0.66864955 | CO69: 1.1984694 | CP69: 1.6047751 | CQ69: 1.1006273 | CR69: 0.49003857 | CS69: 2.410443 | CT69: 2.265358 | CU69: 1.4310383 | CV69: 0.31440844 | CW69: 0.89682012 | CX69: 0.047368429 | CY69: 0.81549858 | CZ69: -0.10835179 | DA69: -0.50460679 | DB69: 2.7524855 | DC69: -0.65157107 | DD69: 2.5107433 | DE69: 2.6848108 | DF69: 0.54402371 | DG69: 1.9393845 | DH69: -0.29283639 | DI69: -0.5552061 | DJ69: 0.39862975 | DK69: 0.74744292 | DL69: 0.94874049 | DM69: 0.95936873 | DN69: 2.2199093 | DO69: 3.6238865 | DP69: 2.7295047 | DQ69: 3.4577174 | DR69: 2.659744 | DS69: 3.0355993 | DT69: 2.7049525 | DU69: 2.4219956 | DV69: -0.41003445 | DW69: 1.8865412 | DX69: -0.34886904 | DY69: 2.5188789 | DZ69: 2.054595 | EA69: 1.6373679 | EB69: 1.3407342 | EC69: 2.2826292 | ED69: 2.5316529 | EE69: 1.5225408 | EF69: -0.028344125 | EG69: 2.5132185 | EH69: 1.4247969 | EI69: 1.9430622 | EJ69: -0.54993022 | EK69: 1.4991599 | EL69: 1.5389384 | EM69: 1.9891103 | EN69: 3.4365217 | EO69: 0.51331955 | EP69: 2.9383991 | EQ69: 2.9752392 | ER69: 0.7584405 | ES69: -0.31470993 | ET69: 0.062075928 | EU69: 1.3920092 | EV69: 2.4032598 | EW69: 4.2540485 | EX69: 1.9213445 | EY69: 3.0945187 | EZ69: 1.5226753 | FA69: 3.0773199 | FB69: 1.043366 | FC69: 3.9620539 | FD69: 2.776217 | FE69: 2.734242 | FF69: 2.4752767 | FG69: 1.7284768 | FH69: 1.075039 | FI69: 2.8804501 | FJ69: 2.074825 | FK69: 1.6293958 | FL69: 1.877349 | FM69: 0.11828677 | FN69: 3.4910563 | FO69: 2.5749782 | FP69: 2.7456698 | FQ69: 1.6884768 | FR69: -0.12602211 | FS69: 3.182743 | FT69: 3.1046297 | FU69: 1.8004413 | FV69: 3.1102679 | FW69: 2.6895371 | FX69: 0.59941778 | FY69: 1.6107164 | FZ69: 0.45321023 | GA69: 2.0928045 | GB69: 0.68989127 | GC69: 3.0726518 | GD69: 1.5339049 | GE69: 2.8248841 | GF69: 2.5512827 | GG69: -0.58990855 | GH69: 2.3657462 | GI69: 1.5371503 | GJ69: 3.1016574 | GK69: 0.56632105 | GL69: 1.9003348 | GM69: -1.0402233 | GN69: 1.6689195 | GO69: 1.6426418 | GP69: 3.0213586 | GQ69: 4.0426174 | GR69: 0.50707081 | GS69: 2.1663971 | GT69: 0.68665811 | GU69: 2.2427064 | GV69: 3.6741746 | GW69: 0.90131515 | GX69: 1.210074 | GY69: 0.42592583 | GZ69: -0.10616707 | HA69: 1.7206491 | HB69: 0.27402797 | HC69: 1.6258331 | HD69: 0.37503067 | HE69: 2.4013716 | HF69: 2.8876607 | HG69: -1.0300212 | HH69: 1.2918737 | HI69: 2.1964703 | HJ69: 3.5490863 | HK69: 1.138412 | HL69: 3.0129659 | HM69: -0.15942543 | HN69: 2.4372951 | HO69: 0.89239902 | HP69: 1.8701543 | HQ69: 1.368681 | HR69: 2.1396692 | HS69: 2.7140956 | HT69: 0.86807997 | HU69: 1.1992608 | HV69: 2.1744257 | HW69: 4.3727625 | HX69: 2.6961787 | HY69: 2.6169338 | HZ69: 2.2458931 | IA69: 2.8342048 | IB69: 1.0558457 | IC69: 0.78714913 | ID69: 0.085053376 | IE69: 3.8041728 | IF69: 5.30128 | IG69: 3.1007499 | IH69: 1.7542186 | II69: 1.0107429 | IJ69: 0.29636491 | IK69: 0.41637584 | IL69: 1.4594339 | IM69: 1.0342097 | IN69: 3.5911001 | IO69: 1.6732413 | IP69: 3.6121458 | IQ69: 1.299062 | IR69: 1.4433555 | IS69: 3.3447566 | IT69: 0.74257228 | IU69: 2.060488 | IV69: 0.37658905 | IW69: 1.236443 | IX69: 0.97940621 | IY69: 1.9169305 | IZ69: 1.2891179 | JA69: 1.0638801 | JB69: 2.4514631 | JC69: 1.9172288 | JD69: 3.0742447 | JE69: 1.8382501 | JF69: -0.05606272 | JG69: 2.1691483 | JH69: 3.2372224 | JI69: 0.34467691 | JJ69: 3.7824525 | JK69: 0.28566914 | JL69: 1.528895 | JM69: 1.0368177 | JN69: 1.3140178 | JO69: 1.2474491 | JP69: 2.5137711 | JQ69: 1.5432273 | JR69: 3.928525 | JS69: 1.5409114 | JT69: 3.422997 | JU69: 0.0317385 | JV69: -1.2502806 | JW69: 0.98931199 | JX69: 3.2439724 | JY69: 1.2439214 | JZ69: 0.9123085 | KA69: 3.4488673 | KB69: 2.010207 | KC69: 2.945862 | KD69: 1.4655097 | KE69: -0.062641741 | KF69: 0.81383 | KG69: 2.1482928 | KH69: 0.28702342 | KI69: 3.2686395 | KJ69: 0.23579113 | KK69: 2.6295343 | KL69: 1.8609754 | KM69: 2.3595839 | KN69: 0.21257427 | KO69: 0.99825164 | KP69: 0.51012682 | KQ69: 3.6059556 | KR69: 1.9816202 | KS69: 3.4280334 | KT69: 3.5638703 | KU69: 2.9228258 | KV69: 1.5540384 | KW69: 1.8071767 | KX69: 2.0017477 | KY69: 2.4639936 | KZ69: 2.1811009 | LA69: 2.1492525 | LB69: 1.894943 | LC69: 3.2270726 | LD69: 1.5302812 | LE69: 1.6814328 | LF69: 2.9937532 | LG69: 2.9889284 | LH69: 1.4578108 | LI69: 1.6154051 | LJ69: 0.091193817 | LK69: 0.053078968 | LL69: 2.101906 | LM69: 3.4011822 | LN69: 1.7809622 | LO69: 1.2787316 | LP69: 1.3500589 | LQ69: 1.3506739 | LR69: 0.20018582 | LS69: 0.38591658 | LT69: 0.94362554 | LU69: 3.0477607 | LV69: 1.3972101 | LW69: 1.0029634 | LX69: 0.6520056 | LY69: 1.698966 | LZ69: 4.3039649 | MA69: 0.79708209 | MB69: 1.4435818 | MC69: 0.19937553 | MD69: 1.2012483 | ME69: 2.1718044 | MF69: 1.4720874 | MG69: -0.63356413 | MH69: 1.7731089 | MI69: 2.329436 | MJ69: 1.6516103 | MK69: 3.7088888 | ML69: 0.35761427 | MM69: -0.0098604774 | MN69: -0.15027561 | MO69: 0.92459608 | MP69: 1.5661194 | MQ69: 3.0371635 | MR69: 0.69586319 | MS69: -0.049861303 | MT69: 4.4433822 | MU69: 2.2170816 | MV69: 3.4277003 | MW69: 2.6578164 | MX69: 1.3398452 | MY69: 1.666424 | MZ69: 3.1009958 | NA69: 2.744065 | NB69: 2.9713853 | NC69: 0.8436194 | ND69: 0.42110693 | NE69: 0.69840844 | NF69: 0.41948655 | NG69: 1.4597607 | NH69: 2.6023698 | NI69: 0.84603904 | NJ69: 0.36110402 | NK69: 3.5785151 | NL69: 1.5229575 | NM69: -0.33042168 | NN69: 1.0738011 | NO69: 3.1985717 | NP69: 1.6213525 | NQ69: 5.3362533 | NR69: 1.7240153 | NS69: 0.96102332 | NT69: 1.3595788 | NU69: 2.4192452 | NV69: 2.2712804 | NW69: 3.7978684 | NX69: -1.4479211 | NY69: 0.46907383 | NZ69: -0.32848463 | OA69: 2.9926004 | OB69: 0.9935176 | OC69: 3.0705287 | OD69: -0.86994097 | OE69: 0.20076936 | OF69: 1.5983838 | OG69: 0.39893462 | OH69: 3.6837434 | OI69: 2.1107209 | OJ69: 2.5906156 | OK69: 1.4519806 | OL69: 2.7848335 | OM69: 2.8769053 | ON69: 1.0909083 | OO69: -0.073088006 | OP69: 0.67140564 | OQ69: 3.5433124 | OR69: 2.4389384 | OS69: 1.4996432 | OT69: 1.0755332 | OU69: 2.0813924 | OV69: 1.037328 | OW69: 1.2946432 | OX69: 1.5251504 | OY69: 1.4985257 | OZ69: 3.5493848 | PA69: 1.7365006 | PB69: 1.9204946 | PC69: 3.3765727 | PD69: 1.327823 | PE69: 2.9779606 | PF69: -0.094902318 | PG69: -0.58139149 | PH69: 2.0756176 | PI69: -2.7893558 | PJ69: 1.9045466 | PK69: 1.7282464 | PL69: -1.3063894 | PM69: 1.6068614 | PN69: 2.3687136 | PO69: 2.9633597 | PP69: -0.52663635 | PQ69: 2.0548395 | PR69: 1.1311133 | PS69: 3.0636545 | PT69: 1.7910911 | PU69: 1.353498 | PV69: 2.9712175 | PW69: 2.0241967 | PX69: 1.1952454 | PY69: 2.4456361 | PZ69: 0.093983908 | QA69: 1.6184011 | QB69: -0.019302906 | QC69: 1.5465052 | QD69: 2.7798875 | QE69: 2.6640504 | QF69: 2.5258512 | QG69: 4.3935517 | QH69: 0.34720876 | QI69: 2.8656601 | QJ69: 0.82174758 | QK69: 3.6455562 | QL69: 1.1775226 | QM69: 3.1116647 | QN69: 2.4512015 | QO69: -0.26924781 | QP69: 3.8005252 | QQ69: 1.4700907 | QR69: 2.3510566 | QS69: -0.10431192 | QT69: 0.88096595 | QU69: 4.1618717 | QV69: 2.0541189 | QW69: 2.0932547 | QX69: 0.89934159 | QY69: 0.68409559 | QZ69: 0.61132752 | RA69: 0.057909766 | RB69: 1.9821255 | RC69: 0.45984008 | RD69: 2.0165422 | RE69: 0.58017189 | RF69: 3.0820824 | RG69: -0.063214332 | RH69: 1.7090092 | RI69: 1.5430773 | RJ69: 0.49894457 | RK69: 2.0279102 | RL69: 2.5921036 | RM69: 1.238689 | RN69: 4.1378873 | RO69: 3.9082839 | RP69: 2.6987505 | RQ69: 1.4850963 | RR69: 2.3850521 | RS69: 2.9814728 | RT69: 2.3529249 | RU69: 2.2051981 | RV69: 1.9655932 | RW69: 0.6663694 | RX69: 3.1412117 | RY69: 2.9064633 | RZ69: 0.54592949 | SA69: 0.94501738 | SB69: 2.0771959 | SC69: 0.010077025 | SD69: 2.107058 | SE69: 2.5947276 | SF69: 1.8337469 | SG69: 2.0904577 | SH69: -0.22895331 | SI69: 3.4806268 | SJ69: -0.19176355 | SK69: 1.5808705 | SL69: 1.4988966 | SM69: 2.337069 | SN69: 1.1827248 | SO69: -0.51339299 | SP69: 1.4016309 | SQ69: 0.57541212 | SR69: 1.5657812 | SS69: -0.79163557 | ST69: -0.048422002 | SU69: 0.5212982 | SV69: -0.057594688 | SW69: -0.62509978 | SX69: 0.2234075 | SY69: -0.16275815 | SZ69: 1.1951711 | TA69: 2.9609129 | TB69: 2.2474665 | TC69: 3.0005881 | TD69: 3.4971573 | TE69: 0.38451252 | TF69: 1.5249692 | TG69: 1.0795757 | TH69: 2.5841556 | TI69: 0.87678589 | TJ69: 1.1936686 | TK69: 0.48603107 | TL69: 2.6057649 | TM69: 0.51993016 | TN69: 2.2512611 | TO69: 1.7864199 | TP69: 3.0870783 | TQ69: 0.89739598 | TR69: 0.93974496 | TS69: -0.18427405 | TT69: 0.51181887 | TU69: 0.16575409 | TV69: 2.4108514 | TW69: 0.49565318 | TX69: -0.51220199 | TY69: -0.63298276 | TZ69: 0.57352131 | UA69: 1.8146441 | UB69: 3.3463703 | UC69: 1.7142655 | UD69: 2.8022034 | UE69: 1.6000708 | UF69: 1.3545984 | UG69: 2.6222501 | UH69: 0.78302102 | UI69: 2.9906885 | UJ69: 0.75993042 | UK69: -1.0320029 | UL69: 1.3787022 | UM69: 0.15215553 | UN69: 2.0301928 | UO69: 1.5492761 | UP69: 1.6321041 | UQ69: 2.4885729 | UR69: 3.7405579 | US69: 4.227282 | UT69: 1.8098 | UU69: 2.1415324 | UV69: 3.3222327 | UW69: 1.8062154 | UX69: 1.4347115 | UY69: 0.87356908 | UZ69: 4.4817991 | VA69: 4.3509837 | VB69: 4.2860344 | VC69: 1.089612 | VD69: 4.1858332 | VE69: 0.92146924 | VF69: 2.6315171 | VG69: -0.084687582 | VH69: 1.3359042 | VI69: 2.0293583 | VJ69: 1.2335386 | VK69: 2.4258585 | VL69: 2.3098726 | VM69: -0.12065682 | VN69: 0.48576108 | VO69: 1.2825702 | VP69: 0.11361705 | VQ69: 3.0826421 | VR69: 4.7358723 | VS69: 0.60023116 | VT69: 1.6975238 | VU69: 1.7761461 | VV69: 1.6765968 | VW69: 2.1973419 | VX69: 1.8619642 | VY69: 4.1926998 | VZ69: 2.452141 | WA69: 1.7996069 | WB69: 0.38488219 | WC69: 1.871407 | WD69: 3.2668097 | WE69: 2.5163931 | WF69: 0.87725847 | WG69: 2.6740236 | WH69: 1.761427 | WI69: 1.6624339 | WJ69: 2.336009 | WK69: 1.1536024 | WL69: 4.760388 | WM69: 3.529799 | WN69: 3.0670695 | WO69: 2.8189655 | WP69: 1.3908274 | WQ69: 1.67909 | WR69: 1.0404153 | WS69: 2.7985461 | WT69: 0.69574333 | WU69: 3.58003 | WV69: 0.6221629 | WW69: 3.2641112 | WX69: 4.0024376 | WY69: 2.8387148 | WZ69: 2.0459717 | XA69: 0.59418067 | XB69: 0.53833513 | XC69: 1.4295862 | XD69: 2.3987941 | XE69: 1.0181382 | XF69: 3.3389289 | XG69: 2.2388423 | XH69: 1.1251037 | XI69: 2.8085873 | XJ69: 1.5985474 | XK69: 0.51345464 | XL69: 2.1176935 | XM69: 0.84408144 | XN69: 1.25692 | XO69: 3.1262624 | XP69: -0.13212493 | XQ69: 1.8639763 | XR69: 1.1529765 | XS69: 0.075768824 | XT69: 0.84712901 | XU69: 1.7884931 | XV69: 3.7567907 | XW69: 1.9835791 | XX69: 1.0625174 | XY69: 3.4869016 | XZ69: 0.71392374 | YA69: 1.7625165 | YB69: 2.7101505 | YC69: 1.0297909 | YD69: 1.2926547 | YE69: 3.4875265 | YF69: 2.6556478 | YG69: 1.9181693 | YH69: -0.66083155 | YI69: -0.8014969 | YJ69: 1.8058577 | YK69: 1.5525388 | YL69: 3.0115728 | YM69: 2.2671293 | YN69: 1.387205 | YO69: 3.0555765 | YP69: 2.089824 | YQ69: 2.0927429 | YR69: 0.94075468 | YS69: 1.6437722 | YT69: 2.299733 | YU69: 1.6386346 | YV69: -0.041752633 | YW69: 2.4017782 | YX69: 1.8310238 | YY69: 2.2050518 | YZ69: 3.4659821 | ZA69: 1.8766576 | ZB69: 3.4388889 | ZC69: 3.5852353 | ZD69: 2.5328966 | ZE69: 3.4324842 | ZF69: 1.7064991 | ZG69: 2.527296 | ZH69: 0.53921278 | ZI69: 0.8306363 | ZJ69: -0.33918589 | ZK69: 1.8797327 | ZL69: 1.8379107 | ZM69: 4.4239302 | ZN69: 1.2950365 | ZO69: 1.7520353 | ZP69: 1.3933322 | ZQ69: 3.3877129 | ZR69: 3.1783453 | ZS69: 1.2524401 | ZT69: 3.2741725 | ZU69: 2.2675889 | ZV69: 2.0989435 | ZW69: 2.1665348 | ZX69: 2.0048191 | ZY69: 1.7840426 | ZZ69: 0.60308583 | AAA69: 2.0120723 | AAB69: 2.4119271 | AAC69: -0.63557541 | AAD69: 1.4701422 | AAE69: 2.0074338 | AAF69: 3.3062529 | AAG69: 0.96281091 | AAH69: 1.8101051 | AAI69: 1.2001432 | AAJ69: 0.97973125 | AAK69: 3.1804336 | AAL69: 0.39031039 | AAM69: 0.24108915 | AAN69: 2.0025336 | AAO69: 2.5153278 | AAP69: -0.22543134 | AAQ69: 2.2895013 | AAR69: 2.210764 | AAS69: 0.93865688 | AAT69: -0.18876224 | AAU69: 0.44571106 | AAV69: 1.681852 | AAW69: 1.4644632 | AAX69: 2.7942579 | AAY69: 2.0248729 | AAZ69: 1.1600815 | ABA69: 2.6755153 | ABB69: 1.2318885 | ABC69: 3.0126334 | ABD69: 0.46423316 | ABE69: 3.3473129 | ABF69: 2.2041741 | ABG69: 0.45249055 | ABH69: 3.0956103 | ABI69: 2.842575 | ABJ69: 3.0690516 | ABK69: 2.7543827 | ABL69: 2.2616585 | ABM69: 2.9903682 | ABN69: 0.20987111 | ABO69: 3.6136748 | ABP69: 1.810293 | ABQ69: 0.035838748 | ABR69: 3.7104865 | ABS69: 1.961206 | ABT69: -0.44692066 | ABU69: -0.036140721 | ABV69: 1.9661981 | ABW69: 1.8138438 | ABX69: 1.0342832 | ABY69: 1.1619655 | ABZ69: 2.7853075 | ACA69: 2.7672528 | ACB69: 1.8277185 | ACC69: 0.74680423 | ACD69: 2.499449 | ACE69: -0.93558329 | ACF69: 3.5509041 | ACG69: 1.3398752 | ACH69: 0.89190314 | ACI69: 0.26714671 | ACJ69: 0.77182669 | ACK69: 0.48794753 | ACL69: 0.37770652 | ACM69: 1.662001 | ACN69: 1.5953902 | ACO69: 1.2105237 | ACP69: 2.1016758 | ACQ69: 1.6447088 | ACR69: 1.1946724 | ACS69: 0.72443719 | ACT69: 1.7530229 | ACU69: 1.8048123 | ACV69: 2.9660797 | ACW69: 3.0496259 | ACX69: 0.3180024 | ACY69: 2.1612654 | ACZ69: 3.2865209 | ADA69: 0.5638474 | ADB69: 1.4118669 | ADC69: 1.4983375 | ADD69: 2.3501414 | ADE69: -0.7132448 | ADF69: 0.53378407 | ADG69: 1.9599081 | ADH69: 0.70800388 | ADI69: 2.1526276 | ADJ69: 1.9654082 | ADK69: 1.4034588 | ADL69: 1.2808856 | ADM69: 1.2503706 | ADN69: 1.2247214 | ADO69: 1.0844745 | ADP69: 1.9704775 | ADQ69: 2.5825757 | ADR69: 4.2943687 | ADS69: 3.2623727 | ADT69: 1.1071883 | ADU69: 0.5621745 | ADV69: 0.87140387 | ADW69: 3.8926231 | ADX69: 3.1517456 | ADY69: 2.7353354 | ADZ69: 1.6030287 | AEA69: -0.1240096 | AEB69: 2.3531969 | AEC69: 1.1085828 | AED69: 2.4596966 | AEE69: 2.1945577 | AEF69: 1.1432204 | AEG69: 1.5944388 | AEH69: 3.3816131 | AEI69: 0.88095767 | AEJ69: 2.0496466 | AEK69: 1.6998007 | AEL69: 0.22651479 | AEM69: 2.2266913 | AEN69: 2.2895963 | AEO69: 4.1010058 | AEP69: 2.8913608 | AEQ69: 1.5767662 | AER69: 3.2619319 | AES69: 1.7322216 | AET69: 2.6233768 | AEU69: 3.2192821 | AEV69: 1.3904844 | AEW69: 1.1553076 | AEX69: 2.8018014 | AEY69: 2.7995588 | AEZ69: 0.067340464 | AFA69: 0.5716948 | AFB69: 1.4543798 | AFC69: 2.1110956 | AFD69: 4.0623334 | AFE69: 1.5950635 | AFF69: 1.9446137 | AFG69: 1.8911406 | AFH69: 1.7559956 | AFI69: 1.5711214 | AFJ69: 1.0475103 | AFK69: 1.8823855 | AFL69: -0.27278769 | AFM69: 2.0942796 | AFN69: 1.1493446 | AFO69: 0.32574436 | AFP69: 3.7308405 | AFQ69: 1.2280774 | AFR69: 3.2138078 | AFS69: -1.7707527 | AFT69: 1.4185429 | AFU69: 2.5752329 | AFV69: 2.320582 | AFW69: 2.1224647 | AFX69: 2.4929802 | AFY69: 1.459235 | AFZ69: 2.3541531 | AGA69: 0.49662274 | AGB69: 1.9573271 | AGC69: 3.0172129 | AGD69: 0.32518835 | AGE69: 3.0798644 | AGF69: 0.61844229 | AGG69: 1.4071066 | AGH69: 1.3567476 | AGI69: 1.0704384 | AGJ69: 2.8777901 | AGK69: 2.4399819 | AGL69: 1.7422836 | AGM69: 0.59170042 | AGN69: 2.2135145 | AGO69: 2.6683223 | AGP69: 2.4104586 | AGQ69: 0.35984321 | AGR69: 2.5563008 | AGS69: 2.2602241 | AGT69: 1.4929361 | AGU69: 3.6328382 | AGV69: 1.4630622 | AGW69: 0.72307922 | AGX69: 1.7926775 | AGY69: 1.3978562 | AGZ69: 0.4833927 | AHA69: 0.79013266 | AHB69: 0.34165959 | AHC69: 1.6320464 | AHD69: -0.037464343 | AHE69: 1.5634461 | AHF69: 2.5724745 | AHG69: 2.183044 | AHH69: 1.1752847 | AHI69: 2.6927465 | AHJ69: 1.5174567 | AHK69: 0.48216759 | AHL69: 2.1213108 | AHM69: -0.47797891 | AHN69: 2.489519 | AHO69: 2.2214302 | AHP69: 1.6895558 | AHQ69: 1.809408 | AHR69: 2.1720461 | AHS69: 1.7872881 | AHT69: 3.3846609 | AHU69: 1.0950045 | AHV69: 0.18497222 | AHW69: 0.82058672 | AHX69: 0.15576373 | AHY69: 0.84496452 | AHZ69: 1.8806385 | AIA69: 0.59313614 | AIB69: 1.8958508 | AIC69: 1.7060095 | AID69: 1.7824659 | AIE69: 1.9804693 | AIF69: 1.8423704 | AIG69: 2.3493717 | AIH69: 0.326475 | AII69: 1.1004301 | AIJ69: 3.5780064 | AIK69: 1.8514197 | AIL69: -0.20768974 | AIM69: 3.4801016 | AIN69: -0.87219138 | AIO69: 1.4788639 | AIP69: 1.0367436 | AIQ69: 2.1324818 | AIR69: 2.175218 | AIS69: 0.99862179 | AIT69: 2.3205202 | AIU69: 0.17475369 | AIV69: 1.5260579 | AIW69: 2.5992375 | AIX69: -0.7925818 | AIY69: 1.8017084 | AIZ69: 3.3036759 | AJA69: 0.32421501 | AJB69: 3.2439839 | AJC69: 0.26568214 | AJD69: 2.2682406 | AJE69: 0.83842235 | AJF69: 0.46923561 | AJG69: 0.2612404 | AJH69: 2.8387377 | AJI69: 1.7788099 | AJJ69: -0.3218816 | AJK69: 0.92510073 | AJL69: 2.0114015 | AJM69: 2.3003133 | AJN69: 3.5504224 | AJO69: 2.2111145 | AJP69: 2.0353592 | AJQ69: 1.3156069 | AJR69: 2.4456345 | AJS69: 1.7484994 | AJT69: 1.7669745 | AJU69: 2.3345531 | AJV69: 1.4057677 | AJW69: 0.47454504 | AJX69: 3.4678498 | AJY69: 0.62258737 | AJZ69: 0.41081305 | AKA69: 1.512221 | AKB69: 1.9196614 | AKC69: 3.3800175 | AKD69: 2.1027862 | AKE69: 3.8005596 | AKF69: 1.3343654 | AKG69: 0.68539162 | AKH69: 0.68489104 | AKI69: 0.86655449 | AKJ69: 1.9791867 | AKK69: 1.3234857 | AKL69: 2.9495345 | AKM69: 1.2239248 | AKN69: 1.1970175 | AKO69: 2.0505653 | AKP69: -0.061541242 | AKQ69: 1.6976264 | AKR69: 1.9371187 | AKS69: 0.52736146 | AKT69: 2.5664873 | AKU69: 1.5359504 | AKV69: 1.257425 | AKW69: 1.8264888 | AKX69: -0.38430845 | AKY69: 1.8643549 | AKZ69: 1.2648466 | ALA69: 0.29725647 | ALB69: -0.67250751 | ALC69: 0.36483571 | ALD69: 1.2115058 | ALE69: -0.50765741 | ALF69: -0.053825899 | ALG69: 2.4374664 | ALH69: 0.48596101 | ALI69: 0.97961988 | ALJ69: 0.33664766 | ALK69: -0.16733041 | ALL69: 3.4266078 | ALM69: -0.12889028
A70: 38 | B70: =_xlfn.NORM.INV(RAND(),'Inflation Rates '!$B$401,'Inflation Rates '!$B$402) -> 3.4170301 | C70: -0.90433961 | D70: 2.8448835 | E70: 0.28397501 | F70: 3.2759012 | G70: 1.5296921 | H70: 3.9661336 | I70: 2.8645988 | J70: 1.7647598 | K70: 3.6207281 | L70: 2.2781139 | M70: 0.9080763 | N70: -0.5595187 | O70: 2.5849986 | P70: 1.0108122 | Q70: 2.2982551 | R70: 2.5732247 | S70: 1.3048315 | T70: 2.2033772 | U70: 3.0707042 | V70: 1.4621182 | W70: 1.9714111 | X70: 2.7869794 | Y70: 0.19245598 | Z70: 4.0076327 | AA70: 1.0908612 | AB70: 3.1860022 | AC70: 0.88848081 | AD70: 1.8196098 | AE70: 1.3574466 | AF70: 1.7166021 | AG70: 2.6452513 | AH70: 1.8302434 | AI70: 0.72887282 | AJ70: 1.0405989 | AK70: 0.75826692 | AL70: 2.3106197 | AM70: 2.5643016 | AN70: 1.6158778 | AO70: 2.3882693 | AP70: 2.0905095 | AQ70: 2.4800266 | AR70: 4.5457333 | AS70: 1.410297 | AT70: 1.2344579 | AU70: 1.2430235 | AV70: 1.4520876 | AW70: 0.10282492 | AX70: 2.4274442 | AY70: 2.0674975 | AZ70: 2.2073933 | BA70: 1.1413033 | BB70: 1.0787099 | BC70: 3.9024621 | BD70: 3.1263787 | BE70: 2.555416 | BF70: 1.4976516 | BG70: 0.2915259 | BH70: 2.0016661 | BI70: 1.0404441 | BJ70: 0.52053334 | BK70: 2.9808725 | BL70: 3.521331 | BM70: -0.66843564 | BN70: 0.2451819 | BO70: 0.91213597 | BP70: -0.14325952 | BQ70: 3.8476389 | BR70: 1.9172487 | BS70: 1.7154247 | BT70: 1.6796326 | BU70: 0.40938332 | BV70: 2.9867987 | BW70: 2.1336715 | BX70: 4.0353771 | BY70: -0.065563469 | BZ70: 1.2233357 | CA70: 4.8281825 | CB70: 3.7757324 | CC70: 1.7928747 | CD70: 3.1527422 | CE70: 2.0738436 | CF70: 0.422572 | CG70: 1.6147636 | CH70: 0.89108842 | CI70: 2.3523646 | CJ70: 0.50252945 | CK70: 2.7443774 | CL70: 3.1372622 | CM70: 1.0517692 | CN70: 1.9584434 | CO70: 1.2959979 | CP70: 1.8880536 | CQ70: 1.2614373 | CR70: 2.668226 | CS70: 2.3279175 | CT70: 1.8343362 | CU70: 4.4618139 | CV70: -0.15279395 | CW70: 3.6377758 | CX70: -1.1192189 | CY70: 2.063002 | CZ70: 0.45970989 | DA70: 2.3817696 | DB70: 0.8254554 | DC70: 0.71804814 | DD70: 0.76127066 | DE70: 1.1361605 | DF70: -0.068820589 | DG70: 2.4683914 | DH70: 1.6526759 | DI70: 0.97614778 | DJ70: 2.4623562 | DK70: 0.93298364 | DL70: 2.7012871 | DM70: 1.7722191 | DN70: 2.8124205 | DO70: 0.23528476 | DP70: 3.323595 | DQ70: 2.1461412 | DR70: 4.2834206 | DS70: 0.82124144 | DT70: 0.17110571 | DU70: 0.81687425 | DV70: 1.0152578 | DW70: 3.2584616 | DX70: 1.3323479 | DY70: 2.4533359 | DZ70: 1.7067191 | EA70: 1.6679176 | EB70: 3.2167598 | EC70: 0.40063687 | ED70: 0.28032009 | EE70: 1.4532685 | EF70: 3.2071049 | EG70: -1.3425783 | EH70: 2.4739243 | EI70: 5.4020023 | EJ70: 0.98004871 | EK70: 2.3963044 | EL70: 2.2155598 | EM70: 0.61233642 | EN70: 1.5256684 | EO70: 2.5299653 | EP70: 0.51888511 | EQ70: 0.94909915 | ER70: -0.95188973 | ES70: 3.4032844 | ET70: 3.080324 | EU70: 0.87992257 | EV70: 0.78543174 | EW70: -0.3187888 | EX70: 3.3199118 | EY70: 1.5725624 | EZ70: 2.1706325 | FA70: 0.76460063 | FB70: -0.083585263 | FC70: 2.0929158 | FD70: 1.8249629 | FE70: 0.37230203 | FF70: 4.0010006 | FG70: 2.1748333 | FH70: 4.2944142 | FI70: 0.37139747 | FJ70: 1.8448858 | FK70: -0.33768641 | FL70: 1.3760002 | FM70: 1.9315556 | FN70: 2.8694343 | FO70: 2.0651201 | FP70: 4.3511757 | FQ70: 3.8706277 | FR70: 1.9296457 | FS70: 3.1455565 | FT70: 1.8187124 | FU70: 1.412217 | FV70: 2.0776518 | FW70: 1.1509765 | FX70: 4.1334983 | FY70: 1.1230778 | FZ70: 0.067506947 | GA70: 1.6592398 | GB70: 2.5173675 | GC70: 5.0691969 | GD70: 3.474351 | GE70: 2.3922733 | GF70: 1.6223109 | GG70: 0.84267639 | GH70: 2.6109029 | GI70: -0.34908882 | GJ70: 1.8928057 | GK70: 1.4577103 | GL70: 2.1334717 | GM70: 2.6586372 | GN70: 0.55432716 | GO70: 3.8171038 | GP70: 2.9266267 | GQ70: 2.3023912 | GR70: 1.3050125 | GS70: 0.96244165 | GT70: 3.1801423 | GU70: 3.0518541 | GV70: 0.65659247 | GW70: 1.7095914 | GX70: 0.70314664 | GY70: 3.3133168 | GZ70: 0.92577999 | HA70: 1.9369145 | HB70: 2.9558203 | HC70: 0.096076739 | HD70: 0.49926681 | HE70: 0.56951254 | HF70: 2.7642564 | HG70: 2.4376573 | HH70: 4.2795429 | HI70: 0.56771076 | HJ70: 2.0388459 | HK70: 3.0956649 | HL70: 1.6444974 | HM70: 1.8526861 | HN70: 4.4753568 | HO70: 3.8160612 | HP70: 1.9162412 | HQ70: 0.78773092 | HR70: 4.3579268 | HS70: 1.3807687 | HT70: 2.7922253 | HU70: 1.4137207 | HV70: 1.7817275 | HW70: 2.1887179 | HX70: 1.0238285 | HY70: 0.28156138 | HZ70: 3.7376066 | IA70: 0.80653527 | IB70: 2.3291281 | IC70: 1.1478734 | ID70: 2.0171969 | IE70: 2.7631815 | IF70: 3.0649768 | IG70: -0.27525499 | IH70: 1.77711 | II70: 1.8350099 | IJ70: 2.0545081 | IK70: -0.85014205 | IL70: 1.2162202 | IM70: 1.3891762 | IN70: 0.53061971 | IO70: 1.802788 | IP70: 2.9749834 | IQ70: -0.091342496 | IR70: 3.678231 | IS70: 1.5990699 | IT70: 0.76076443 | IU70: 1.3961768 | IV70: 1.4323144 | IW70: 1.4472679 | IX70: 2.0717342 | IY70: 3.6376555 | IZ70: 0.12174061 | JA70: 1.9791328 | JB70: 0.74092724 | JC70: 1.938336 | JD70: 3.2097532 | JE70: 1.8951546 | JF70: 1.7933659 | JG70: 2.6785443 | JH70: 1.6415689 | JI70: 0.89999398 | JJ70: 2.9425309 | JK70: 2.5641532 | JL70: -0.41680629 | JM70: 1.6722363 | JN70: 1.7268195 | JO70: 1.1989597 | JP70: 1.4449024 | JQ70: 0.27539316 | JR70: 1.8440278 | JS70: 0.71694258 | JT70: 2.5196726 | JU70: 3.754619 | JV70: 1.5236005 | JW70: 1.9419716 | JX70: 1.2661917 | JY70: 2.8066361 | JZ70: 3.176528 | KA70: 2.379369 | KB70: 1.4946291 | KC70: 0.49973424 | KD70: 2.899925 | KE70: 2.5742471 | KF70: 1.6577885 | KG70: 0.95769381 | KH70: 0.048046353 | KI70: 0.066722168 | KJ70: 2.2867043 | KK70: 0.89910841 | KL70: 2.6287308 | KM70: 1.9222681 | KN70: 2.2569755 | KO70: 1.8377611 | KP70: 0.77515272 | KQ70: 1.4437904 | KR70: 2.578224 | KS70: 1.6734389 | KT70: 0.21319214 | KU70: 0.81909443 | KV70: -0.63481708 | KW70: 0.63471698 | KX70: 0.14717928 | KY70: 0.89534439 | KZ70: -0.55359825 | LA70: 2.2351019 | LB70: -0.18235863 | LC70: 2.0562979 | LD70: 1.3912814 | LE70: 0.27515995 | LF70: 3.5467028 | LG70: 0.4265751 | LH70: 2.407575 | LI70: 0.30849371 | LJ70: 1.5113562 | LK70: 2.0591093 | LL70: -0.55885707 | LM70: 1.5028471 | LN70: 1.1490464 | LO70: 0.932174 | LP70: 1.6560724 | LQ70: 2.7739921 | LR70: -0.3872994 | LS70: -0.5950386 | LT70: 3.5499637 | LU70: 1.5866032 | LV70: 1.9798135 | LW70: 2.2460373 | LX70: 0.50119941 | LY70: 4.4189488 | LZ70: 2.2532543 | MA70: 2.1666126 | MB70: 2.7526146 | MC70: 1.6827064 | MD70: 1.4831765 | ME70: 1.2099494 | MF70: 1.7407416 | MG70: 1.4953183 | MH70: 0.95448722 | MI70: 0.31437946 | MJ70: 1.7898144 | MK70: 1.9640284 | ML70: 1.7979535 | MM70: 0.60154556 | MN70: 3.4767621 | MO70: 0.74397302 | MP70: 3.0093024 | MQ70: 0.52758788 | MR70: 3.3604726 | MS70: 2.5888293 | MT70: 2.3894115 | MU70: 2.2570861 | MV70: 1.3668807 | MW70: 2.4413657 | MX70: 2.4077419 | MY70: 1.595597 | MZ70: 0.36187145 | NA70: -0.52343815 | NB70: 0.44679721 | NC70: 3.5094109 | ND70: 2.6101246 | NE70: 2.6737245 | NF70: 1.7010252 | NG70: 0.68750112 | NH70: 5.2191731 | NI70: 1.886795 | NJ70: 1.8004619 | NK70: 1.4525265 | NL70: 1.6892537 | NM70: 0.0003511597 | NN70: 0.15346104 | NO70: 3.2601875 | NP70: 1.156892 | NQ70: 0.98660689 | NR70: 0.54466013 | NS70: -0.69906287 | NT70: 3.6873326 | NU70: 2.4476497 | NV70: 0.82715172 | NW70: 1.7021752 | NX70: 2.9763836 | NY70: 2.3686716 | NZ70: 2.1177778 | OA70: 1.5565227 | OB70: 1.9845932 | OC70: 1.0157423 | OD70: 3.6571842 | OE70: 1.4040069 | OF70: -0.01984828 | OG70: 2.7395029 | OH70: 2.7391189 | OI70: 1.0984561 | OJ70: 3.6678574 | OK70: 0.73263962 | OL70: 2.5578994 | OM70: 2.2548227 | ON70: -0.6719188 | OO70: 1.9639329 | OP70: 2.6171778 | OQ70: 3.6297967 | OR70: 3.0924889 | OS70: 2.4572911 | OT70: 1.1105759 | OU70: 2.78128 | OV70: 1.0839869 | OW70: 2.7041323 | OX70: 1.7154108 | OY70: 2.125172 | OZ70: 2.3784998 | PA70: 3.0073408 | PB70: 1.8893138 | PC70: 0.58753299 | PD70: 1.774819 | PE70: 0.43902251 | PF70: 2.3075568 | PG70: 0.36191772 | PH70: 2.6501885 | PI70: 3.2744039 | PJ70: 2.4362912 | PK70: 1.7257532 | PL70: 0.079262171 | PM70: 2.9693813 | PN70: 2.0171178 | PO70: 0.7221345 | PP70: 2.5843331 | PQ70: 1.9901461 | PR70: 1.6079016 | PS70: 0.81618383 | PT70: -0.40385731 | PU70: 4.0424929 | PV70: 1.8483376 | PW70: 2.615831 | PX70: 3.8490963 | PY70: -0.6023786 | PZ70: 2.2306859 | QA70: 1.0815766 | QB70: -0.21319314 | QC70: -0.26205104 | QD70: 1.359423 | QE70: 2.6356027 | QF70: 2.3386677 | QG70: 0.39943768 | QH70: 2.399457 | QI70: -1.342306 | QJ70: 1.6958976 | QK70: 2.9759772 | QL70: -0.054722597 | QM70: 0.45445192 | QN70: 0.93653883 | QO70: 1.6183354 | QP70: 1.3648933 | QQ70: 0.90045456 | QR70: 3.9865563 | QS70: 2.3490658 | QT70: 3.8510582 | QU70: -0.56620857 | QV70: 1.7508866 | QW70: 1.8964698 | QX70: 0.094072209 | QY70: 3.3791311 | QZ70: 3.2590869 | RA70: 1.2440947 | RB70: 2.9303168 | RC70: 3.5268695 | RD70: 3.0363597 | RE70: 2.6347467 | RF70: 1.7380682 | RG70: 2.9483582 | RH70: 1.1400969 | RI70: 1.6912592 | RJ70: 3.8858986 | RK70: 3.6815042 | RL70: 3.3264207 | RM70: 1.2948281 | RN70: 2.0807837 | RO70: 1.2141149 | RP70: 2.112294 | RQ70: 0.1680279 | RR70: 1.6603806 | RS70: 0.54046486 | RT70: 1.414064 | RU70: 2.5745799 | RV70: 2.4578921 | RW70: 0.79176407 | RX70: 1.1261106 | RY70: 0.36854221 | RZ70: 2.7280823 | SA70: 3.4766068 | SB70: 2.1495256 | SC70: 0.3801295 | SD70: 4.047685 | SE70: 2.6244971 | SF70: 0.85332764 | SG70: 2.2516869 | SH70: -0.058845055 | SI70: 2.2354633 | SJ70: 1.5041256 | SK70: 1.3101583 | SL70: 0.92193332 | SM70: 2.8016419 | SN70: 1.2716029 | SO70: 0.32582368 | SP70: 0.07265374 | SQ70: 1.9249479 | SR70: 2.0076863 | SS70: 3.03562 | ST70: 1.0819667 | SU70: -0.022849516 | SV70: 1.7964512 | SW70: 1.6042764 | SX70: 0.46215997 | SY70: 1.3150108 | SZ70: 1.2538484 | TA70: 3.4410462 | TB70: 1.431017 | TC70: 3.1772557 | TD70: 0.11668629 | TE70: 1.088421 | TF70: 2.0653533 | TG70: 0.9887016 | TH70: 2.6247386 | TI70: 0.32064212 | TJ70: 2.8846185 | TK70: 1.2936372 | TL70: 0.61021462 | TM70: 1.28617 | TN70: 2.5498558 | TO70: 1.0831614 | TP70: 0.9863792 | TQ70: 2.4826128 | TR70: 2.5436042 | TS70: 0.93679344 | TT70: 1.1305092 | TU70: 0.11347509 | TV70: 1.5269936 | TW70: 2.0327703 | TX70: -0.91771693 | TY70: 1.8587281 | TZ70: 0.81154712 | UA70: 2.6201348 | UB70: 2.2389641 | UC70: 1.0923611 | UD70: 0.73293091 | UE70: 0.80030941 | UF70: 3.1800133 | UG70: 2.0361894 | UH70: 0.15309223 | UI70: 2.7621949 | UJ70: 2.0704827 | UK70: 2.578793 | UL70: 1.6110838 | UM70: 3.0244449 | UN70: 2.5753593 | UO70: 3.6113957 | UP70: -0.30910405 | UQ70: 0.79568809 | UR70: 1.0432164 | US70: 1.9543625 | UT70: 0.1746687 | UU70: 0.8921077 | UV70: -0.11828149 | UW70: 1.1896257 | UX70: -0.24958303 | UY70: 2.4366127 | UZ70: 2.4801626 | VA70: 0.55456891 | VB70: 2.5936704 | VC70: 2.3021167 | VD70: 2.5069692 | VE70: 2.1175482 | VF70: 3.2163625 | VG70: -0.25223902 | VH70: -0.87666037 | VI70: 1.7507183 | VJ70: 0.60742581 | VK70: 2.1567127 | VL70: 1.2829911 | VM70: 1.5021971 | VN70: 1.1885008 | VO70: 2.5126752 | VP70: 1.6779141 | VQ70: 1.8147005 | VR70: 1.5180831 | VS70: 2.3059476 | VT70: 3.7978395 | VU70: 2.4747441 | VV70: 0.44020045 | VW70: 1.9820087 | VX70: 1.0894391 | VY70: 0.24139457 | VZ70: 1.2369079 | WA70: 1.4286742 | WB70: 1.1112012 | WC70: 0.42130797 | WD70: 2.5994943 | WE70: 0.88482472 | WF70: 3.8156776 | WG70: -1.0010407 | WH70: 0.67047739 | WI70: 0.90009822 | WJ70: 0.54618712 | WK70: 2.8039576 | WL70: 1.4731607 | WM70: 0.10171425 | WN70: -0.56128982 | WO70: 0.084683728 | WP70: 0.3120662 | WQ70: 1.5383216 | WR70: 2.4042537 | WS70: 1.053215 | WT70: 2.0623874 | WU70: 0.36650319 | WV70: 1.7905107 | WW70: 2.5934314 | WX70: -0.037713395 | WY70: 1.8694724 | WZ70: 2.0342888 | XA70: 2.9435882 | XB70: 1.6892 | XC70: 2.3020829 | XD70: 3.0181923 | XE70: 1.109613 | XF70: 2.6317172 | XG70: 0.45340362 | XH70: -0.27394581 | XI70: 0.041575404 | XJ70: 0.46676178 | XK70: 1.1826627 | XL70: 1.894327 | XM70: 3.5690378 | XN70: 2.0178357 | XO70: 1.6529742 | XP70: 1.7647398 | XQ70: 2.6060567 | XR70: 0.036047082 | XS70: 0.92984922 | XT70: 2.1420466 | XU70: 2.4826537 | XV70: 0.042436068 | XW70: 1.5491335 | XX70: 0.86119888 | XY70: 3.3570838 | XZ70: 1.85361 | YA70: 2.6824523 | YB70: 2.3755011 | YC70: 2.4197971 | YD70: 1.0300558 | YE70: 0.52445747 | YF70: 3.0537275 | YG70: 2.890164 | YH70: 0.5416997 | YI70: 2.6151781 | YJ70: 1.3555324 | YK70: 5.0592785 | YL70: 1.3569879 | YM70: 3.2942956 | YN70: 1.4219493 | YO70: 2.9040737 | YP70: 2.1105216 | YQ70: 1.9339238 | YR70: 1.0577541 | YS70: 0.65173177 | YT70: 0.21146823 | YU70: 3.6400083 | YV70: 3.8447682 | YW70: 0.88797617 | YX70: 1.0687738 | YY70: 3.0584711 | YZ70: 0.70602484 | ZA70: 0.96891703 | ZB70: 2.0267646 | ZC70: 2.9939462 | ZD70: 0.94310093 | ZE70: 2.4263793 | ZF70: 3.6515111 | ZG70: 2.2723718 | ZH70: 1.7740119 | ZI70: 0.99985067 | ZJ70: 1.7391702 | ZK70: 4.0458275 | ZL70: 1.2342399 | ZM70: 1.4129866 | ZN70: 2.1545943 | ZO70: 1.8417441 | ZP70: 4.0065604 | ZQ70: 3.1102141 | ZR70: 1.2992219 | ZS70: -0.37821333 | ZT70: 1.3070797 | ZU70: 3.3605033 | ZV70: 0.7052078 | ZW70: 2.5816862 | ZX70: 0.092568101 | ZY70: 4.4545543 | ZZ70: 2.3047468 | AAA70: 2.6922696 | AAB70: 3.7624405 | AAC70: 1.3597498 | AAD70: 1.0555995 | AAE70: 0.033626964 | AAF70: -0.70730415 | AAG70: 2.6057059 | AAH70: 1.6418905 | AAI70: 2.3347174 | AAJ70: 1.6314367 | AAK70: 2.6896203 | AAL70: 0.083547129 | AAM70: 0.68465476 | AAN70: -1.9789792 | AAO70: 0.65166431 | AAP70: -0.30137126 | AAQ70: 1.9237404 | AAR70: 1.2530654 | AAS70: 1.8293936 | AAT70: 1.3480736 | AAU70: 1.6425081 | AAV70: 2.051648 | AAW70: 0.69103423 | AAX70: 1.5679729 | AAY70: 0.55548614 | AAZ70: 1.6333304 | ABA70: 1.6688329 | ABB70: -0.62971121 | ABC70: 1.8640159 | ABD70: 0.15418703 | ABE70: 1.2518484 | ABF70: 3.9428953 | ABG70: 3.5556091 | ABH70: 4.3700077 | ABI70: 1.3018268 | ABJ70: 2.0527485 | ABK70: 3.029005 | ABL70: 2.0005282 | ABM70: 3.6193177 | ABN70: -0.043962444 | ABO70: 2.293113 | ABP70: 2.0138111 | ABQ70: 2.8104181 | ABR70: 3.8007226 | ABS70: -0.14373335 | ABT70: 2.6426126 | ABU70: -0.71295498 | ABV70: 1.6261093 | ABW70: 0.36201577 | ABX70: 1.3707486 | ABY70: 0.11833934 | ABZ70: -0.15654972 | ACA70: 2.9691962 | ACB70: -0.91573109 | ACC70: 1.2071732 | ACD70: 0.99232453 | ACE70: 0.6653347 | ACF70: 2.5255822 | ACG70: 2.9418357 | ACH70: 1.2706841 | ACI70: 1.6728895 | ACJ70: 3.8298714 | ACK70: 1.5417066 | ACL70: 0.80738584 | ACM70: 3.4657375 | ACN70: 1.6762919 | ACO70: 0.71404573 | ACP70: 1.9573681 | ACQ70: 2.5073114 | ACR70: 1.8396403 | ACS70: 0.74525952 | ACT70: 2.0310248 | ACU70: 2.4305722 | ACV70: 2.4305216 | ACW70: 2.5953524 | ACX70: 1.9685777 | ACY70: 4.335359 | ACZ70: 1.2273924 | ADA70: 1.1604253 | ADB70: 1.8405122 | ADC70: -0.45406197 | ADD70: 0.00017870729 | ADE70: 1.6624877 | ADF70: 1.103606 | ADG70: 2.8436498 | ADH70: 3.6907728 | ADI70: 4.7587393 | ADJ70: 3.295924 | ADK70: 2.1251479 | ADL70: 0.33722763 | ADM70: 0.079321473 | ADN70: 2.5248749 | ADO70: 4.0304902 | ADP70: 1.5100772 | ADQ70: 0.26032475 | ADR70: 0.91015157 | ADS70: 1.6802801 | ADT70: -0.153721 | ADU70: 2.5360619 | ADV70: 1.1605566 | ADW70: 1.5015921 | ADX70: 0.56612768 | ADY70: 1.5762913 | ADZ70: 0.76567627 | AEA70: 4.4364841 | AEB70: 2.2224782 | AEC70: 0.92953229 | AED70: 0.059342195 | AEE70: 3.4736654 | AEF70: 0.23033809 | AEG70: 0.32025831 | AEH70: 1.4255498 | AEI70: 3.046874 | AEJ70: 2.8897877 | AEK70: 0.90016777 | AEL70: 1.7272319 | AEM70: 1.8518626 | AEN70: 0.54637064 | AEO70: 1.7571874 | AEP70: 3.5747543 | AEQ70: 1.859768 | AER70: 2.4605357 | AES70: 1.2197599 | AET70: 1.5357214 | AEU70: 0.48109721 | AEV70: 2.4912265 | AEW70: 0.97899883 | AEX70: 4.4279237 | AEY70: 0.97802099 | AEZ70: 1.4832654 | AFA70: 3.8986868 | AFB70: 0.13065243 | AFC70: 2.5621386 | AFD70: 2.4029646 | AFE70: 1.7999399 | AFF70: 3.6906694 | AFG70: 1.3414638 | AFH70: 1.3882006 | AFI70: 1.9499212 | AFJ70: 1.7669576 | AFK70: 1.6557055 | AFL70: 1.6982513 | AFM70: 3.1165028 | AFN70: 0.91785574 | AFO70: 4.517909 | AFP70: 2.24511 | AFQ70: 2.943347 | AFR70: -0.70212415 | AFS70: 4.0448307 | AFT70: -0.19444438 | AFU70: 1.9329936 | AFV70: 2.2476791 | AFW70: 2.4005276 | AFX70: 0.66221581 | AFY70: 2.5617443 | AFZ70: -0.53947617 | AGA70: 0.64204865 | AGB70: 0.35038858 | AGC70: 1.6058177 | AGD70: 2.1026012 | AGE70: 0.89191915 | AGF70: 1.4794418 | AGG70: 1.1157937 | AGH70: 2.0694576 | AGI70: 1.0098981 | AGJ70: 2.8029243 | AGK70: 2.492812 | AGL70: 1.0896377 | AGM70: 2.2638421 | AGN70: 1.1888299 | AGO70: 2.4186906 | AGP70: -0.28541691 | AGQ70: 0.89846157 | AGR70: 2.0865503 | AGS70: 2.8370227 | AGT70: 0.72280966 | AGU70: 3.6680668 | AGV70: 0.18414254 | AGW70: 1.1777883 | AGX70: 1.0083773 | AGY70: 0.86939619 | AGZ70: 1.1507193 | AHA70: 0.80776829 | AHB70: 0.39043091 | AHC70: 1.9890041 | AHD70: 1.4377024 | AHE70: 2.0035911 | AHF70: 2.5695734 | AHG70: 1.5192572 | AHH70: -0.40684341 | AHI70: 0.25122244 | AHJ70: 0.31213168 | AHK70: -0.43857452 | AHL70: -1.3731154 | AHM70: 1.0048656 | AHN70: 0.33753939 | AHO70: 3.2548064 | AHP70: 2.4242288 | AHQ70: 2.4257701 | AHR70: -0.15691279 | AHS70: 0.094272241 | AHT70: 0.54322454 | AHU70: 3.1468873 | AHV70: 1.1143077 | AHW70: 3.0197675 | AHX70: 0.39792153 | AHY70: 1.9222409 | AHZ70: 1.7975601 | AIA70: 1.4135509 | AIB70: 3.1010627 | AIC70: 1.7415654 | AID70: -0.20222121 | AIE70: 3.1295419 | AIF70: -0.44068612 | AIG70: 1.9251596 | AIH70: 0.85730886 | AII70: 5.0228123 | AIJ70: 1.7159294 | AIK70: 3.6133943 | AIL70: 3.2926152 | AIM70: -0.14871103 | AIN70: -0.22296484 | AIO70: 4.160497 | AIP70: 2.7294804 | AIQ70: 1.2197358 | AIR70: 2.2552753 | AIS70: 2.3019491 | AIT70: 3.6335096 | AIU70: -0.34774842 | AIV70: 1.1359545 | AIW70: 2.7161458 | AIX70: 4.358749 | AIY70: 4.3675933 | AIZ70: 1.4110935 | AJA70: -1.4269043 | AJB70: 1.6818241 | AJC70: 2.5769719 | AJD70: 2.1335314 | AJE70: 1.904546 | AJF70: -0.45847341 | AJG70: 1.6122524 | AJH70: 0.032398442 | AJI70: 1.5306718 | AJJ70: 3.0000661 | AJK70: 0.52603393 | AJL70: -0.21544683 | AJM70: 0.56619154 | AJN70: 0.81747028 | AJO70: 3.3432888 | AJP70: 1.8835787 | AJQ70: 3.1414427 | AJR70: 0.91048916 | AJS70: 1.4637075 | AJT70: 4.9606407 | AJU70: 1.114896 | AJV70: 2.578738 | AJW70: 0.99647071 | AJX70: 2.1595412 | AJY70: 1.4555785 | AJZ70: 0.69256178 | AKA70: 2.6600713 | AKB70: 2.4522148 | AKC70: 1.2322164 | AKD70: 0.95742372 | AKE70: -0.15103823 | AKF70: 3.5580616 | AKG70: 0.7914764 | AKH70: 1.6636515 | AKI70: 1.4689831 | AKJ70: 2.4367975 | AKK70: 4.1244445 | AKL70: 1.4068538 | AKM70: 0.76776495 | AKN70: 0.53523714 | AKO70: 3.0076472 | AKP70: 3.8801826 | AKQ70: 1.8929188 | AKR70: -0.244755 | AKS70: 2.0384571 | AKT70: 2.2430962 | AKU70: 2.9516941 | AKV70: 2.1973009 | AKW70: 1.8460673 | AKX70: 0.38876017 | AKY70: 3.8212904 | AKZ70: 2.3268058 | ALA70: 2.5456279 | ALB70: -1.4122917 | ALC70: -1.1646165 | ALD70: 1.3914471 | ALE70: 3.5426985 | ALF70: 1.0284883 | ALG70: 0.60869818 | ALH70: 3.2245273 | ALI70: 1.496734 | ALJ70: 1.6288089 | ALK70: 1.8938622 | ALL70: 4.5812855 | ALM70: 0.8949047
